[{"pattern": {"nes": {"Parkinson": 1}, "cds": {}}, "sp": 0, "ne": 5, "cd": 0, "sid": "1", "total": 5, "doc_id": "./anns_v2/Pedrosa et al., (2012) - Essential tremor and tremor in PD are associated with distinct tremor clusters in ventral thalamus_annotated_ann.json"}, {"pattern": {"sp_index": -1, "sub": ["tremor", "entities"], "pred": ["be", "ameliorated"], "nes": {"DBS": 1, "Essential Tremor": 1, "Parkinson": 1, "Deep Brain Stimulation": 1}, "cds": {}}, "sp": 0, "ne": 16, "cd": 0, "sid": "2", "total": 16, "doc_id": "./anns_v2/Pedrosa et al., (2012) - Essential tremor and tremor in PD are associated with distinct tremor clusters in ventral thalamus_annotated_ann.json"}, {"pattern": {"nes": {}, "cds": {}}, "sp": 0, "ne": 0, "cd": 0, "sid": "3", "total": 0, "doc_id": "./anns_v2/Pedrosa et al., (2012) - Essential tremor and tremor in PD are associated with distinct tremor clusters in ventral thalamus_annotated_ann.json"}, {"pattern": {"sp_index": 4, "sub": ["we"], "pred": ["investigated"], "nes": {"ET": 1, "LFP": 1}, "cds": {}}, "sp": 9, "ne": 4, "cd": 0, "sid": "4", "total": 13, "doc_id": "./anns_v2/Pedrosa et al., (2012) - Essential tremor and tremor in PD are associated with distinct tremor clusters in ventral thalamus_annotated_ann.json"}, {"pattern": {"sp_index": -1, "sub": ["field", "potentials"], "pred": ["were", "recorded"], "nes": {"EMGs": 1, "Local": 1, "LFPs": 1}, "cds": {"patients": 1}}, "sp": 0, "ne": 2, "cd": 126, "sid": "5", "total": 128, "doc_id": "./anns_v2/Pedrosa et al., (2012) - Essential tremor and tremor in PD are associated with distinct tremor clusters in ventral thalamus_annotated_ann.json"}, {"pattern": {"sp_index": -1, "sub": ["Data", "analysis"], "pred": ["revealed"], "nes": {"Data": 1}, "cds": {}}, "sp": 0, "ne": 0, "cd": 0, "sid": "6", "total": 0, "doc_id": "./anns_v2/Pedrosa et al., (2012) - Essential tremor and tremor in PD are associated with distinct tremor clusters in ventral thalamus_annotated_ann.json"}, {"pattern": {"sp_index": -1, "sub": ["Patterns"], "pred": ["observed"], "nes": {"Patterns": 1, "VLp": 1}, "cds": {}}, "sp": 0, "ne": 8, "cd": 0, "sid": "7", "total": 8, "doc_id": "./anns_v2/Pedrosa et al., (2012) - Essential tremor and tremor in PD are associated with distinct tremor clusters in ventral thalamus_annotated_ann.json"}, {"pattern": {"sp_index": -1, "sub": ["data"], "pred": ["suggest"], "nes": {"VLp": 1, "ET": 1}, "cds": {"Inc": 1}}, "sp": 0, "ne": 10, "cd": 0, "sid": "8", "total": 10, "doc_id": "./anns_v2/Pedrosa et al., (2012) - Essential tremor and tremor in PD are associated with distinct tremor clusters in ventral thalamus_annotated_ann.json"}, {"pattern": {"sp_index": -1, "sub": ["rights"], "pred": ["reserved"], "nes": {}, "cds": {}}, "sp": 0, "ne": 0, "cd": 0, "sid": "9", "total": 0, "doc_id": "./anns_v2/Pedrosa et al., (2012) - Essential tremor and tremor in PD are associated with distinct tremor clusters in ventral thalamus_annotated_ann.json"}, {"pattern": {"nes": {}, "cds": {}}, "sp": 0, "ne": 0, "cd": 0, "sid": "10", "total": 0, "doc_id": "./anns_v2/Pedrosa et al., (2012) - Essential tremor and tremor in PD are associated with distinct tremor clusters in ventral thalamus_annotated_ann.json"}, {"pattern": {"sp_index": -1, "sub": ["thalamus"], "pred": ["was", "identified"], "nes": {"Garonzik": 1}, "cds": {}}, "sp": 0, "ne": 0, "cd": 0, "sid": "11", "total": 0, "doc_id": "./anns_v2/Pedrosa et al., (2012) - Essential tremor and tremor in PD are associated with distinct tremor clusters in ventral thalamus_annotated_ann.json"}, {"pattern": {"sp_index": -1, "sub": ["it"], "pred": ["became"], "nes": {"DBS": 1, "Benabid": 1, "Deep Brain Stimulation": 1}, "cds": {}}, "sp": 0, "ne": 11, "cd": 0, "sid": "12", "total": 11, "doc_id": "./anns_v2/Pedrosa et al., (2012) - Essential tremor and tremor in PD are associated with distinct tremor clusters in ventral thalamus_annotated_ann.json"}, {"pattern": {"sp_index": -1, "sub": ["its", "parts"], "pred": ["are", "considered"], "nes": {}, "cds": {}}, "sp": 0, "ne": 0, "cd": 0, "sid": "13", "total": 0, "doc_id": "./anns_v2/Pedrosa et al., (2012) - Essential tremor and tremor in PD are associated with distinct tremor clusters in ventral thalamus_annotated_ann.json"}, {"pattern": {"sp_index": 1359, "sub": ["Following", "Hirai", "Jones"], "pred": ["be", "divided", "posterior"], "nes": {"Jones": 1, "VLa": 1, "Hirai": 1, "VLp": 1}, "cds": {}}, "sp": 1, "ne": 9, "cd": 0, "sid": "14", "total": 10, "doc_id": "./anns_v2/Pedrosa et al., (2012) - Essential tremor and tremor in PD are associated with distinct tremor clusters in ventral thalamus_annotated_ann.json"}, {"pattern": {"sp_index": -1, "sub": ["author"], "pred": ["Corresponding"], "nes": {"Neurology": 1, "University Hospital Cologne": 1}, "cds": {}}, "sp": 0, "ne": 0, "cd": 0, "sid": "15", "total": 0, "doc_id": "./anns_v2/Pedrosa et al., (2012) - Essential tremor and tremor in PD are associated with distinct tremor clusters in ventral thalamus_annotated_ann.json"}, {"pattern": {"nes": {"Germany": 1}, "cds": {"K\u00f6ln": 1}}, "sp": 0, "ne": 0, "cd": 0, "sid": "16", "total": 0, "doc_id": "./anns_v2/Pedrosa et al., (2012) - Essential tremor and tremor in PD are associated with distinct tremor clusters in ventral thalamus_annotated_ann.json"}, {"pattern": {"nes": {"Fax": 1}, "cds": {}}, "sp": 0, "ne": 0, "cd": 0, "sid": "17", "total": 0, "doc_id": "./anns_v2/Pedrosa et al., (2012) - Essential tremor and tremor in PD are associated with distinct tremor clusters in ventral thalamus_annotated_ann.json"}, {"pattern": {"nes": {}, "cds": {}}, "sp": 0, "ne": 0, "cd": 0, "sid": "18", "total": 0, "doc_id": "./anns_v2/Pedrosa et al., (2012) - Essential tremor and tremor in PD are associated with distinct tremor clusters in ventral thalamus_annotated_ann.json"}, {"pattern": {"sp_index": -1, "sub": ["authors"], "pred": ["contributed"], "nes": {}, "cds": {}}, "sp": 0, "ne": 0, "cd": 0, "sid": "19", "total": 0, "doc_id": "./anns_v2/Pedrosa et al., (2012) - Essential tremor and tremor in PD are associated with distinct tremor clusters in ventral thalamus_annotated_ann.json"}, {"pattern": {"sp_index": 589, "sub": ["$"], "pred": ["see"], "nes": {}, "cds": {"Inc": 1}}, "sp": 1, "ne": 0, "cd": 0, "sid": "20", "total": 1, "doc_id": "./anns_v2/Pedrosa et al., (2012) - Essential tremor and tremor in PD are associated with distinct tremor clusters in ventral thalamus_annotated_ann.json"}, {"pattern": {"nes": {}, "cds": {}}, "sp": 0, "ne": 0, "cd": 0, "sid": "21", "total": 0, "doc_id": "./anns_v2/Pedrosa et al., (2012) - Essential tremor and tremor in PD are associated with distinct tremor clusters in ventral thalamus_annotated_ann.json"}, {"pattern": {"nes": {}, "cds": {}}, "sp": 0, "ne": 0, "cd": 0, "sid": "22", "total": 0, "doc_id": "./anns_v2/Pedrosa et al., (2012) - Essential tremor and tremor in PD are associated with distinct tremor clusters in ventral thalamus_annotated_ann.json"}, {"pattern": {"nes": {}, "cds": {}}, "sp": 0, "ne": 0, "cd": 0, "sid": "23", "total": 0, "doc_id": "./anns_v2/Pedrosa et al., (2012) - Essential tremor and tremor in PD are associated with distinct tremor clusters in ventral thalamus_annotated_ann.json"}, {"pattern": {"sp_index": 1332, "sub": ["Hirai"], "pred": ["corresponding"], "nes": {"Jones": 1, "VLp": 1, "Hirai": 1, "Hassler": 1, "Krack": 1}, "cds": {}}, "sp": 1, "ne": 9, "cd": 0, "sid": "24", "total": 10, "doc_id": "./anns_v2/Pedrosa et al., (2012) - Essential tremor and tremor in PD are associated with distinct tremor clusters in ventral thalamus_annotated_ann.json"}, {"pattern": {"sp_index": -1, "sub": ["area"], "pred": ["receives"], "nes": {"Jones": 1, "Macchi": 1, "Asanuma": 1}, "cds": {}}, "sp": 0, "ne": 0, "cd": 0, "sid": "25", "total": 0, "doc_id": "./anns_v2/Pedrosa et al., (2012) - Essential tremor and tremor in PD are associated with distinct tremor clusters in ventral thalamus_annotated_ann.json"}, {"pattern": {"sp_index": 710, "sub": ["Patients"], "pred": ["suffer"], "nes": {"ET": 1}, "cds": {"Hz": 1}}, "sp": 1, "ne": 2, "cd": 0, "sid": "26", "total": 3, "doc_id": "./anns_v2/Pedrosa et al., (2012) - Essential tremor and tremor in PD are associated with distinct tremor clusters in ventral thalamus_annotated_ann.json"}, {"pattern": {"nes": {}, "cds": {}}, "sp": 0, "ne": 0, "cd": 0, "sid": "27", "total": 0, "doc_id": "./anns_v2/Pedrosa et al., (2012) - Essential tremor and tremor in PD are associated with distinct tremor clusters in ventral thalamus_annotated_ann.json"}, {"pattern": {"sp_index": -1, "sub": ["electrodes"], "pred": ["is", "considered"], "nes": {"Koller": 1, "VLp": 1, "DBS": 1, "Blomstedt": 1}, "cds": {}}, "sp": 0, "ne": 19, "cd": 0, "sid": "28", "total": 19, "doc_id": "./anns_v2/Pedrosa et al., (2012) - Essential tremor and tremor in PD are associated with distinct tremor clusters in ventral thalamus_annotated_ann.json"}, {"pattern": {"sp_index": -1, "sub": ["Patients"], "pred": ["present"], "nes": {}, "cds": {"tremor": 1}}, "sp": 0, "ne": 0, "cd": 0, "sid": "29", "total": 0, "doc_id": "./anns_v2/Pedrosa et al., (2012) - Essential tremor and tremor in PD are associated with distinct tremor clusters in ventral thalamus_annotated_ann.json"}, {"pattern": {"sp_index": 19, "sub": null, "pred": ["is"], "nes": {}, "cds": {}}, "sp": 5, "ne": 0, "cd": 0, "sid": "30", "total": 5, "doc_id": "./anns_v2/Pedrosa et al., (2012) - Essential tremor and tremor in PD are associated with distinct tremor clusters in ventral thalamus_annotated_ann.json"}, {"pattern": {"nes": {}, "cds": {}}, "sp": 0, "ne": 0, "cd": 0, "sid": "31", "total": 0, "doc_id": "./anns_v2/Pedrosa et al., (2012) - Essential tremor and tremor in PD are associated with distinct tremor clusters in ventral thalamus_annotated_ann.json"}, {"pattern": {"sp_index": -1, "sub": ["nomenclature"], "pred": ["refer"], "nes": {"VLp": 1}, "cds": {}}, "sp": 0, "ne": 8, "cd": 0, "sid": "32", "total": 8, "doc_id": "./anns_v2/Pedrosa et al., (2012) - Essential tremor and tremor in PD are associated with distinct tremor clusters in ventral thalamus_annotated_ann.json"}, {"pattern": {"sp_index": -1, "sub": ["tremor"], "pred": ["be"], "nes": {"Deuschl": 1}, "cds": {}}, "sp": 0, "ne": 0, "cd": 0, "sid": "33", "total": 0, "doc_id": "./anns_v2/Pedrosa et al., (2012) - Essential tremor and tremor in PD are associated with distinct tremor clusters in ventral thalamus_annotated_ann.json"}, {"pattern": {"sp_index": -1, "sub": ["tremor"], "pred": ["emerge"], "nes": {}, "cds": {"s": 1}}, "sp": 0, "ne": 0, "cd": 3, "sid": "34", "total": 3, "doc_id": "./anns_v2/Pedrosa et al., (2012) - Essential tremor and tremor in PD are associated with distinct tremor clusters in ventral thalamus_annotated_ann.json"}, {"pattern": {"sp_index": -1, "sub": ["improvement"], "pred": ["be", "achieved"], "nes": {"VLp": 1, "DBS": 1}, "cds": {}}, "sp": 0, "ne": 19, "cd": 0, "sid": "35", "total": 19, "doc_id": "./anns_v2/Pedrosa et al., (2012) - Essential tremor and tremor in PD are associated with distinct tremor clusters in ventral thalamus_annotated_ann.json"}, {"pattern": {"sp_index": -1, "sub": ["tremor"], "pred": ["be"], "nes": {"Hilker": 1}, "cds": {}}, "sp": 0, "ne": 0, "cd": 0, "sid": "36", "total": 0, "doc_id": "./anns_v2/Pedrosa et al., (2012) - Essential tremor and tremor in PD are associated with distinct tremor clusters in ventral thalamus_annotated_ann.json"}, {"pattern": {"sp_index": -1, "sub": ["treatment"], "pred": ["is", "performed"], "nes": {}, "cds": {}}, "sp": 0, "ne": 0, "cd": 0, "sid": "37", "total": 0, "doc_id": "./anns_v2/Pedrosa et al., (2012) - Essential tremor and tremor in PD are associated with distinct tremor clusters in ventral thalamus_annotated_ann.json"}, {"pattern": {"sp_index": -1, "sub": ["patients"], "pred": ["are", "implanted"], "nes": {}, "cds": {}}, "sp": 0, "ne": 0, "cd": 0, "sid": "38", "total": 0, "doc_id": "./anns_v2/Pedrosa et al., (2012) - Essential tremor and tremor in PD are associated with distinct tremor clusters in ventral thalamus_annotated_ann.json"}, {"pattern": {"sp_index": -1, "sub": ["oscillator"], "pred": ["is", "assumed"], "nes": {}, "cds": {}}, "sp": 0, "ne": 0, "cd": 0, "sid": "39", "total": 0, "doc_id": "./anns_v2/Pedrosa et al., (2012) - Essential tremor and tremor in PD are associated with distinct tremor clusters in ventral thalamus_annotated_ann.json"}, {"pattern": {"sp_index": -1, "sub": ["oscillator"], "pred": ["is", "supposed"], "nes": {}, "cds": {}}, "sp": 0, "ne": 0, "cd": 0, "sid": "40", "total": 0, "doc_id": "./anns_v2/Pedrosa et al., (2012) - Essential tremor and tremor in PD are associated with distinct tremor clusters in ventral thalamus_annotated_ann.json"}, {"pattern": {"sp_index": -1, "sub": ["network"], "pred": ["comprise"], "nes": {"Schnitzler": 1}, "cds": {}}, "sp": 0, "ne": 0, "cd": 0, "sid": "41", "total": 0, "doc_id": "./anns_v2/Pedrosa et al., (2012) - Essential tremor and tremor in PD are associated with distinct tremor clusters in ventral thalamus_annotated_ann.json"}, {"pattern": {"sp_index": -1, "sub": ["oscillations"], "pred": ["were", "demonstrated"], "nes": {"VLp": 1, "Marsden": 1, "Lenz": 2}, "cds": {}}, "sp": 0, "ne": 8, "cd": 0, "sid": "42", "total": 8, "doc_id": "./anns_v2/Pedrosa et al., (2012) - Essential tremor and tremor in PD are associated with distinct tremor clusters in ventral thalamus_annotated_ann.json"}, {"pattern": {"sp_index": -1, "sub": ["recordings"], "pred": ["revealed"], "nes": {"Amtage": 1, "STN": 1, "Florin": 1, "Parkinsonian": 1, "Reck": 1}, "cds": {}}, "sp": 0, "ne": 32, "cd": 0, "sid": "43", "total": 32, "doc_id": "./anns_v2/Pedrosa et al., (2012) - Essential tremor and tremor in PD are associated with distinct tremor clusters in ventral thalamus_annotated_ann.json"}, {"pattern": {"sp_index": -1, "sub": ["segregation"], "pred": ["had", "been", "hypothesized"], "nes": {"Raethjen": 1}, "cds": {}}, "sp": 0, "ne": 0, "cd": 0, "sid": "44", "total": 0, "doc_id": "./anns_v2/Pedrosa et al., (2012) - Essential tremor and tremor in PD are associated with distinct tremor clusters in ventral thalamus_annotated_ann.json"}, {"pattern": {"sp_index": -1, "sub": ["it"], "pred": ["remains"], "nes": {}, "cds": {}}, "sp": 0, "ne": 0, "cd": 0, "sid": "45", "total": 0, "doc_id": "./anns_v2/Pedrosa et al., (2012) - Essential tremor and tremor in PD are associated with distinct tremor clusters in ventral thalamus_annotated_ann.json"}, {"pattern": {"sp_index": -1, "sub": null, "pred": ["seems"], "nes": {}, "cds": {}}, "sp": 0, "ne": 0, "cd": 0, "sid": "46", "total": 0, "doc_id": "./anns_v2/Pedrosa et al., (2012) - Essential tremor and tremor in PD are associated with distinct tremor clusters in ventral thalamus_annotated_ann.json"}, {"pattern": {"sp_index": -1, "sub": ["We"], "pred": ["hypothesized"], "nes": {"VLp": 1, "Reck": 1}, "cds": {}}, "sp": 0, "ne": 8, "cd": 0, "sid": "47", "total": 8, "doc_id": "./anns_v2/Pedrosa et al., (2012) - Essential tremor and tremor in PD are associated with distinct tremor clusters in ventral thalamus_annotated_ann.json"}, {"pattern": {"sp_index": -1, "sub": ["we"], "pred": ["investigated", "constitutes"], "nes": {}, "cds": {}}, "sp": 0, "ne": 0, "cd": 0, "sid": "48", "total": 0, "doc_id": "./anns_v2/Pedrosa et al., (2012) - Essential tremor and tremor in PD are associated with distinct tremor clusters in ventral thalamus_annotated_ann.json"}, {"pattern": {"sp_index": 911, "sub": ["we"], "pred": ["investigated", "analyzed"], "nes": {"VLp": 1, "LFP": 1}, "cds": {}}, "sp": 1, "ne": 10, "cd": 0, "sid": "49", "total": 11, "doc_id": "./anns_v2/Pedrosa et al., (2012) - Essential tremor and tremor in PD are associated with distinct tremor clusters in ventral thalamus_annotated_ann.json"}, {"pattern": {"sp_index": 535, "sub": ["We", "accord"], "pred": ["rest", "ii", "analyzed"], "nes": {"VLp": 1, "EMG": 1, "LFPs": 1}, "cds": {"ET": 1, "patients": 2}}, "sp": 1, "ne": 13, "cd": 126, "sid": "50", "total": 140, "doc_id": "./anns_v2/Pedrosa et al., (2012) - Essential tremor and tremor in PD are associated with distinct tremor clusters in ventral thalamus_annotated_ann.json"}, {"pattern": {"nes": {"VLp": 32, "LFP Number": 2, "Parkinson": 1, "Heights": 2}, "cds": {"characteristics": 1, "Disease": 2, "years": 2, "VLp": 26, "Tremor-frequency": 2, "Mean": 4}}, "sp": 0, "ne": 0, "cd": 0, "sid": "51", "total": 0, "doc_id": "./anns_v2/Pedrosa et al., (2012) - Essential tremor and tremor in PD are associated with distinct tremor clusters in ventral thalamus_annotated_ann.json"}, {"pattern": {"nes": {}, "cds": {}}, "sp": 0, "ne": 0, "cd": 0, "sid": "52", "total": 0, "doc_id": "./anns_v2/Pedrosa et al., (2012) - Essential tremor and tremor in PD are associated with distinct tremor clusters in ventral thalamus_annotated_ann.json"}, {"pattern": {"sp_index": 1399, "sub": ["patients"], "pred": ["were", "implanted", "enrolled"], "nes": {"ET": 1, "VLp": 1}, "cds": {"patients": 2}}, "sp": 1, "ne": 10, "cd": 126, "sid": "53", "total": 137, "doc_id": "./anns_v2/Pedrosa et al., (2012) - Essential tremor and tremor in PD are associated with distinct tremor clusters in ventral thalamus_annotated_ann.json"}, {"pattern": {"sp_index": -1, "sub": ["ET", "patients"], "pred": ["showed", "were", "excluded"], "nes": {}, "cds": {"patients": 1}}, "sp": 0, "ne": 0, "cd": 126, "sid": "54", "total": 126, "doc_id": "./anns_v2/Pedrosa et al., (2012) - Essential tremor and tremor in PD are associated with distinct tremor clusters in ventral thalamus_annotated_ann.json"}, {"pattern": {"sp_index": -1, "sub": ["ET", "patients"], "pred": ["had"], "nes": {}, "cds": {"years": 4}}, "sp": 0, "ne": 0, "cd": 6, "sid": "55", "total": 6, "doc_id": "./anns_v2/Pedrosa et al., (2012) - Essential tremor and tremor in PD are associated with distinct tremor clusters in ventral thalamus_annotated_ann.json"}, {"pattern": {"sp_index": -1, "sub": ["Mean", "disease", "duration"], "pred": ["was"], "nes": {"Mean": 1}, "cds": {"years": 2}}, "sp": 0, "ne": 1, "cd": 6, "sid": "56", "total": 7, "doc_id": "./anns_v2/Pedrosa et al., (2012) - Essential tremor and tremor in PD are associated with distinct tremor clusters in ventral thalamus_annotated_ann.json"}, {"pattern": {"sp_index": -1, "sub": ["data"], "pred": ["are", "provided"], "nes": {}, "cds": {}}, "sp": 0, "ne": 0, "cd": 0, "sid": "57", "total": 0, "doc_id": "./anns_v2/Pedrosa et al., (2012) - Essential tremor and tremor in PD are associated with distinct tremor clusters in ventral thalamus_annotated_ann.json"}, {"pattern": {"sp_index": 674, "sub": ["ET", "patients"], "pred": ["presented"], "nes": {}, "cds": {"patient": 1}}, "sp": 1, "ne": 0, "cd": 4, "sid": "58", "total": 5, "doc_id": "./anns_v2/Pedrosa et al., (2012) - Essential tremor and tremor in PD are associated with distinct tremor clusters in ventral thalamus_annotated_ann.json"}, {"pattern": {"sp_index": -1, "sub": ["tremor"], "pred": ["showed"], "nes": {}, "cds": {}}, "sp": 0, "ne": 0, "cd": 0, "sid": "59", "total": 0, "doc_id": "./anns_v2/Pedrosa et al., (2012) - Essential tremor and tremor in PD are associated with distinct tremor clusters in ventral thalamus_annotated_ann.json"}, {"pattern": {"sp_index": -1, "sub": ["Tremor"], "pred": ["was", "refractory"], "nes": {"Tremor": 1}, "cds": {}}, "sp": 0, "ne": 0, "cd": 0, "sid": "60", "total": 0, "doc_id": "./anns_v2/Pedrosa et al., (2012) - Essential tremor and tremor in PD are associated with distinct tremor clusters in ventral thalamus_annotated_ann.json"}, {"pattern": {"sp_index": 2, "sub": null, "pred": ["was"], "nes": {}, "cds": {}}, "sp": 10, "ne": 0, "cd": 0, "sid": "61", "total": 10, "doc_id": "./anns_v2/Pedrosa et al., (2012) - Essential tremor and tremor in PD are associated with distinct tremor clusters in ventral thalamus_annotated_ann.json"}, {"pattern": {"sp_index": -1, "sub": ["study"], "pred": ["was", "approved"], "nes": {}, "cds": {}}, "sp": 0, "ne": 0, "cd": 0, "sid": "62", "total": 0, "doc_id": "./anns_v2/Pedrosa et al., (2012) - Essential tremor and tremor in PD are associated with distinct tremor clusters in ventral thalamus_annotated_ann.json"}, {"pattern": {"sp_index": -1, "sub": ["D\u00fcsseldorf"], "pred": ["2459", "carried"], "nes": {"Cologne": 1, "D\u00fcsseldorf": 1, "Helsinki": 1}, "cds": {}}, "sp": 0, "ne": 0, "cd": 0, "sid": "63", "total": 0, "doc_id": "./anns_v2/Pedrosa et al., (2012) - Essential tremor and tremor in PD are associated with distinct tremor clusters in ventral thalamus_annotated_ann.json"}, {"pattern": {"sp_index": -1, "sub": ["patients"], "pred": ["had", "given"], "nes": {}, "cds": {}}, "sp": 0, "ne": 0, "cd": 0, "sid": "64", "total": 0, "doc_id": "./anns_v2/Pedrosa et al., (2012) - Essential tremor and tremor in PD are associated with distinct tremor clusters in ventral thalamus_annotated_ann.json"}, {"pattern": {"sp_index": -1, "sub": ["Electrodes"], "pred": ["were", "implanted"], "nes": {"Cologne": 1, "Stereotaxy": 1, "Functional Neurosurgery": 1}, "cds": {"h": 1}}, "sp": 0, "ne": 0, "cd": 1, "sid": "65", "total": 1, "doc_id": "./anns_v2/Pedrosa et al., (2012) - Essential tremor and tremor in PD are associated with distinct tremor clusters in ventral thalamus_annotated_ann.json"}, {"pattern": {"sp_index": -1, "sub": ["VLp"], "pred": ["was", "targeted"], "nes": {"VLp": 1, "Schaltenbrand": 1, "MRI": 1}, "cds": {}}, "sp": 0, "ne": 31, "cd": 0, "sid": "66", "total": 31, "doc_id": "./anns_v2/Pedrosa et al., (2012) - Essential tremor and tremor in PD are associated with distinct tremor clusters in ventral thalamus_annotated_ann.json"}, {"pattern": {"sp_index": 607, "sub": ["standard"], "pred": ["coordinates"], "nes": {"VLp": 1, "PD": 1, "MCP": 1}, "cds": {"posterior": 1}}, "sp": 1, "ne": 21, "cd": 0, "sid": "67", "total": 22, "doc_id": "./anns_v2/Pedrosa et al., (2012) - Essential tremor and tremor in PD are associated with distinct tremor clusters in ventral thalamus_annotated_ann.json"}, {"pattern": {"sp_index": 1, "sub": ["We"], "pred": ["used"], "nes": {"VLp": 1}, "cds": {}}, "sp": 14, "ne": 8, "cd": 0, "sid": "68", "total": 22, "doc_id": "./anns_v2/Pedrosa et al., (2012) - Essential tremor and tremor in PD are associated with distinct tremor clusters in ventral thalamus_annotated_ann.json"}, {"pattern": {"sp_index": -1, "sub": ["place"], "pred": ["was", "based"], "nes": {"DBS": 1, "MN": 1, "USA": 1, "Minneapolis": 1, "Medtronic": 1}, "cds": {}}, "sp": 0, "ne": 11, "cd": 0, "sid": "69", "total": 11, "doc_id": "./anns_v2/Pedrosa et al., (2012) - Essential tremor and tremor in PD are associated with distinct tremor clusters in ventral thalamus_annotated_ann.json"}, {"pattern": {"sp_index": -1, "sub": ["recordings"], "pred": ["were", "performed"], "nes": {"Emmendingen": 1, "Germany": 1, "INOMED": 1}, "cds": {"beta": 1}}, "sp": 0, "ne": 0, "cd": 0, "sid": "70", "total": 0, "doc_id": "./anns_v2/Pedrosa et al., (2012) - Essential tremor and tremor in PD are associated with distinct tremor clusters in ventral thalamus_annotated_ann.json"}, {"pattern": {"sp_index": -1, "sub": ["procedure"], "pred": ["was", "performed"], "nes": {"Florin": 1}, "cds": {}}, "sp": 0, "ne": 0, "cd": 0, "sid": "71", "total": 0, "doc_id": "./anns_v2/Pedrosa et al., (2012) - Essential tremor and tremor in PD are associated with distinct tremor clusters in ventral thalamus_annotated_ann.json"}, {"pattern": {"sp_index": 7, "sub": ["we"], "pred": ["used"], "nes": {"Briefly": 1}, "cds": {"mm": 1}}, "sp": 8, "ne": 0, "cd": 1, "sid": "72", "total": 9, "doc_id": "./anns_v2/Pedrosa et al., (2012) - Essential tremor and tremor in PD are associated with distinct tremor clusters in ventral thalamus_annotated_ann.json"}, {"pattern": {"sp_index": -1, "sub": ["electrodes"], "pred": ["consist"], "nes": {}, "cds": {"mm": 1, "\u03bcm": 2}}, "sp": 0, "ne": 0, "cd": 1, "sid": "73", "total": 1, "doc_id": "./anns_v2/Pedrosa et al., (2012) - Essential tremor and tremor in PD are associated with distinct tremor clusters in ventral thalamus_annotated_ann.json"}, {"pattern": {"sp_index": -1, "sub": ["macroelectrodes"], "pred": ["are", "were", "used"], "nes": {"LFPs": 1}, "cds": {"k\u03a9": 1}}, "sp": 0, "ne": 1, "cd": 0, "sid": "74", "total": 1, "doc_id": "./anns_v2/Pedrosa et al., (2012) - Essential tremor and tremor in PD are associated with distinct tremor clusters in ventral thalamus_annotated_ann.json"}, {"pattern": {"sp_index": -1, "sub": ["patients"], "pred": ["except"], "nes": {}, "cds": {"patient": 1}}, "sp": 0, "ne": 0, "cd": 4, "sid": "75", "total": 4, "doc_id": "./anns_v2/Pedrosa et al., (2012) - Essential tremor and tremor in PD are associated with distinct tremor clusters in ventral thalamus_annotated_ann.json"}, {"pattern": {"sp_index": -1, "sub": null, "pred": ["were", "implanted"], "nes": {}, "cds": {}}, "sp": 0, "ne": 0, "cd": 0, "sid": "76", "total": 0, "doc_id": "./anns_v2/Pedrosa et al., (2012) - Essential tremor and tremor in PD are associated with distinct tremor clusters in ventral thalamus_annotated_ann.json"}, {"pattern": {"sp_index": 172, "sub": ["We"], "pred": ["were"], "nes": {}, "cds": {}}, "sp": 2, "ne": 0, "cd": 0, "sid": "77", "total": 2, "doc_id": "./anns_v2/Pedrosa et al., (2012) - Essential tremor and tremor in PD are associated with distinct tremor clusters in ventral thalamus_annotated_ann.json"}, {"pattern": {"sp_index": -1, "sub": ["LFPs"], "pred": ["were", "obtained"], "nes": {"VLp": 1, "LFPs": 1}, "cds": {"mm": 4}}, "sp": 0, "ne": 9, "cd": 1, "sid": "78", "total": 10, "doc_id": "./anns_v2/Pedrosa et al., (2012) - Essential tremor and tremor in PD are associated with distinct tremor clusters in ventral thalamus_annotated_ann.json"}, {"pattern": {"nes": {}, "cds": {"conditions": 1}}, "sp": 0, "ne": 0, "cd": 3, "sid": "79", "total": 3, "doc_id": "./anns_v2/Pedrosa et al., (2012) - Essential tremor and tremor in PD are associated with distinct tremor clusters in ventral thalamus_annotated_ann.json"}, {"pattern": {"nes": {}, "cds": {"s": 1}}, "sp": 0, "ne": 0, "cd": 3, "sid": "80", "total": 3, "doc_id": "./anns_v2/Pedrosa et al., (2012) - Essential tremor and tremor in PD are associated with distinct tremor clusters in ventral thalamus_annotated_ann.json"}, {"pattern": {"sp_index": -1, "sub": ["Sedation"], "pred": ["was", "withdrawn"], "nes": {"Sedation": 1}, "cds": {"min": 1}}, "sp": 0, "ne": 0, "cd": 3, "sid": "81", "total": 3, "doc_id": "./anns_v2/Pedrosa et al., (2012) - Essential tremor and tremor in PD are associated with distinct tremor clusters in ventral thalamus_annotated_ann.json"}, {"pattern": {"sp_index": 391, "sub": ["We"], "pred": ["recorded"], "nes": {"EMG": 1}, "cds": {}}, "sp": 1, "ne": 4, "cd": 0, "sid": "82", "total": 5, "doc_id": "./anns_v2/Pedrosa et al., (2012) - Essential tremor and tremor in PD are associated with distinct tremor clusters in ventral thalamus_annotated_ann.json"}, {"pattern": {"sp_index": -1, "sub": ["LFP", "EMG-signals"], "pred": ["were"], "nes": {}, "cds": {"Hz": 1, "kHz": 1}}, "sp": 0, "ne": 0, "cd": 0, "sid": "83", "total": 0, "doc_id": "./anns_v2/Pedrosa et al., (2012) - Essential tremor and tremor in PD are associated with distinct tremor clusters in ventral thalamus_annotated_ann.json"}, {"pattern": {"sp_index": -1, "sub": ["rate"], "pred": ["was", "chosen"], "nes": {}, "cds": {"kHz": 1, "bits": 1}}, "sp": 0, "ne": 0, "cd": 0, "sid": "84", "total": 0, "doc_id": "./anns_v2/Pedrosa et al., (2012) - Essential tremor and tremor in PD are associated with distinct tremor clusters in ventral thalamus_annotated_ann.json"}, {"pattern": {"sp_index": -1, "sub": ["LFP"], "pred": ["were", "stored", "imported"], "nes": {"CED": 1, "Cambridge Electronic": 1, "Cambridge": 1}, "cds": {}}, "sp": 0, "ne": 0, "cd": 0, "sid": "85", "total": 0, "doc_id": "./anns_v2/Pedrosa et al., (2012) - Essential tremor and tremor in PD are associated with distinct tremor clusters in ventral thalamus_annotated_ann.json"}, {"pattern": {"sp_index": -1, "sub": ["artefacts"], "pred": ["were", "included"], "nes": {}, "cds": {}}, "sp": 0, "ne": 0, "cd": 0, "sid": "86", "total": 0, "doc_id": "./anns_v2/Pedrosa et al., (2012) - Essential tremor and tremor in PD are associated with distinct tremor clusters in ventral thalamus_annotated_ann.json"}, {"pattern": {"sp_index": -1, "sub": ["Data"], "pred": ["were", "analyzed", "written"], "nes": {"MathWorks": 1, "USA": 1, "Natick MA": 1}, "cds": {"language": 1}}, "sp": 0, "ne": 0, "cd": 1, "sid": "87", "total": 1, "doc_id": "./anns_v2/Pedrosa et al., (2012) - Essential tremor and tremor in PD are associated with distinct tremor clusters in ventral thalamus_annotated_ann.json"}, {"pattern": {"sp_index": 797, "sub": ["data"], "pred": ["were"], "nes": {}, "cds": {"Hz": 1}}, "sp": 1, "ne": 0, "cd": 0, "sid": "88", "total": 1, "doc_id": "./anns_v2/Pedrosa et al., (2012) - Essential tremor and tremor in PD are associated with distinct tremor clusters in ventral thalamus_annotated_ann.json"}, {"pattern": {"sp_index": -1, "sub": ["we"], "pred": ["calculated"], "nes": {"Welch": 1}, "cds": {"points": 1}}, "sp": 0, "ne": 0, "cd": 2, "sid": "89", "total": 2, "doc_id": "./anns_v2/Pedrosa et al., (2012) - Essential tremor and tremor in PD are associated with distinct tremor clusters in ventral thalamus_annotated_ann.json"}, {"pattern": {"sp_index": 1041, "sub": null, "pred": ["resulted"], "nes": {}, "cds": {"Hz": 2}}, "sp": 1, "ne": 0, "cd": 0, "sid": "90", "total": 1, "doc_id": "./anns_v2/Pedrosa et al., (2012) - Essential tremor and tremor in PD are associated with distinct tremor clusters in ventral thalamus_annotated_ann.json"}, {"pattern": {"sp_index": -1, "sub": ["coherence"], "pred": ["was", "estimated"], "nes": {"EMG": 1, "LFP": 2}, "cds": {}}, "sp": 0, "ne": 6, "cd": 0, "sid": "91", "total": 6, "doc_id": "./anns_v2/Pedrosa et al., (2012) - Essential tremor and tremor in PD are associated with distinct tremor clusters in ventral thalamus_annotated_ann.json"}, {"pattern": {"sp_index": -1, "sub": ["method"], "pred": ["is"], "nes": {}, "cds": {}}, "sp": 0, "ne": 0, "cd": 0, "sid": "92", "total": 0, "doc_id": "./anns_v2/Pedrosa et al., (2012) - Essential tremor and tremor in PD are associated with distinct tremor clusters in ventral thalamus_annotated_ann.json"}, {"pattern": {"sp_index": -1, "sub": ["Coherence"], "pred": ["ranges"], "nes": {"Coherence": 1}, "cds": {}}, "sp": 0, "ne": 0, "cd": 0, "sid": "93", "total": 0, "doc_id": "./anns_v2/Pedrosa et al., (2012) - Essential tremor and tremor in PD are associated with distinct tremor clusters in ventral thalamus_annotated_ann.json"}, {"pattern": {"sp_index": -1, "sub": ["we"], "pred": ["computed"], "nes": {}, "cds": {"%": 3, "limits": 1}}, "sp": 0, "ne": 0, "cd": 0, "sid": "94", "total": 0, "doc_id": "./anns_v2/Pedrosa et al., (2012) - Essential tremor and tremor in PD are associated with distinct tremor clusters in ventral thalamus_annotated_ann.json"}, {"pattern": {"sp_index": -1, "sub": ["significance", "level"], "pred": ["be", "used"], "nes": {}, "cds": {}}, "sp": 0, "ne": 0, "cd": 0, "sid": "95", "total": 0, "doc_id": "./anns_v2/Pedrosa et al., (2012) - Essential tremor and tremor in PD are associated with distinct tremor clusters in ventral thalamus_annotated_ann.json"}, {"pattern": {"sp_index": -1, "sub": ["example"], "pred": ["is", "shown"], "nes": {}, "cds": {}}, "sp": 0, "ne": 0, "cd": 0, "sid": "96", "total": 0, "doc_id": "./anns_v2/Pedrosa et al., (2012) - Essential tremor and tremor in PD are associated with distinct tremor clusters in ventral thalamus_annotated_ann.json"}, {"pattern": {"sp_index": -1, "sub": ["we"], "pred": ["calculated"], "nes": {"EDC": 1, "EMG": 1, "FDL": 1, "LFP": 1}, "cds": {}}, "sp": 0, "ne": 6, "cd": 0, "sid": "97", "total": 6, "doc_id": "./anns_v2/Pedrosa et al., (2012) - Essential tremor and tremor in PD are associated with distinct tremor clusters in ventral thalamus_annotated_ann.json"}, {"pattern": {"sp_index": -1, "sub": ["coherences"], "pred": ["were", "plotted"], "nes": {}, "cds": {}}, "sp": 0, "ne": 0, "cd": 0, "sid": "98", "total": 0, "doc_id": "./anns_v2/Pedrosa et al., (2012) - Essential tremor and tremor in PD are associated with distinct tremor clusters in ventral thalamus_annotated_ann.json"}, {"pattern": {"sp_index": -1, "sub": ["we"], "pred": ["calculated"], "nes": {}, "cds": {}}, "sp": 0, "ne": 0, "cd": 0, "sid": "99", "total": 0, "doc_id": "./anns_v2/Pedrosa et al., (2012) - Essential tremor and tremor in PD are associated with distinct tremor clusters in ventral thalamus_annotated_ann.json"}, {"pattern": {"sp_index": -1, "sub": null, "pred": ["allows"], "nes": {"FFT": 1, "Rosenberg": 1}, "cds": {}}, "sp": 0, "ne": 0, "cd": 0, "sid": "100", "total": 0, "doc_id": "./anns_v2/Pedrosa et al., (2012) - Essential tremor and tremor in PD are associated with distinct tremor clusters in ventral thalamus_annotated_ann.json"}, {"pattern": {"sp_index": -1, "sub": ["Details"], "pred": ["have", "been", "described"], "nes": {"Reck": 1}, "cds": {}}, "sp": 0, "ne": 0, "cd": 0, "sid": "101", "total": 0, "doc_id": "./anns_v2/Pedrosa et al., (2012) - Essential tremor and tremor in PD are associated with distinct tremor clusters in ventral thalamus_annotated_ann.json"}, {"pattern": {"sp_index": 875, "sub": ["we"], "pred": ["tested"], "nes": {}, "cds": {}}, "sp": 1, "ne": 0, "cd": 0, "sid": "102", "total": 1, "doc_id": "./anns_v2/Pedrosa et al., (2012) - Essential tremor and tremor in PD are associated with distinct tremor clusters in ventral thalamus_annotated_ann.json"}, {"pattern": {"sp_index": 7, "sub": ["we"], "pred": ["used"], "nes": {"Pearson": 1}, "cds": {}}, "sp": 8, "ne": 0, "cd": 0, "sid": "103", "total": 8, "doc_id": "./anns_v2/Pedrosa et al., (2012) - Essential tremor and tremor in PD are associated with distinct tremor clusters in ventral thalamus_annotated_ann.json"}, {"pattern": {"sp_index": -1, "sub": ["we"], "pred": ["rejected"], "nes": {}, "cds": {}}, "sp": 0, "ne": 0, "cd": 0, "sid": "104", "total": 0, "doc_id": "./anns_v2/Pedrosa et al., (2012) - Essential tremor and tremor in PD are associated with distinct tremor clusters in ventral thalamus_annotated_ann.json"}, {"pattern": {"sp_index": -1, "sub": ["Equal"], "pred": ["distributed"], "nes": {"Equal": 1}, "cds": {}}, "sp": 0, "ne": 0, "cd": 0, "sid": "105", "total": 0, "doc_id": "./anns_v2/Pedrosa et al., (2012) - Essential tremor and tremor in PD are associated with distinct tremor clusters in ventral thalamus_annotated_ann.json"}, {"pattern": {"sp_index": -1, "sub": ["tremor", "cluster"], "pred": ["was", "assumed"], "nes": {}, "cds": {"height": 1}}, "sp": 0, "ne": 0, "cd": 0, "sid": "106", "total": 0, "doc_id": "./anns_v2/Pedrosa et al., (2012) - Essential tremor and tremor in PD are associated with distinct tremor clusters in ventral thalamus_annotated_ann.json"}, {"pattern": {"sp_index": -1, "sub": ["groups"], "pred": ["were", "analyzed"], "nes": {}, "cds": {}}, "sp": 0, "ne": 0, "cd": 0, "sid": "107", "total": 0, "doc_id": "./anns_v2/Pedrosa et al., (2012) - Essential tremor and tremor in PD are associated with distinct tremor clusters in ventral thalamus_annotated_ann.json"}, {"pattern": {"sp_index": -1, "sub": ["heights"], "pred": ["were", "normalized"], "nes": {}, "cds": {}}, "sp": 0, "ne": 0, "cd": 0, "sid": "108", "total": 0, "doc_id": "./anns_v2/Pedrosa et al., (2012) - Essential tremor and tremor in PD are associated with distinct tremor clusters in ventral thalamus_annotated_ann.json"}, {"pattern": {"sp_index": -1, "sub": ["results"], "pred": ["were", "summed"], "nes": {}, "cds": {"height": 1}}, "sp": 0, "ne": 0, "cd": 0, "sid": "109", "total": 0, "doc_id": "./anns_v2/Pedrosa et al., (2012) - Essential tremor and tremor in PD are associated with distinct tremor clusters in ventral thalamus_annotated_ann.json"}, {"pattern": {"sp_index": -1, "sub": ["test"], "pred": ["was", "described"], "nes": {}, "cds": {}}, "sp": 0, "ne": 0, "cd": 0, "sid": "110", "total": 0, "doc_id": "./anns_v2/Pedrosa et al., (2012) - Essential tremor and tremor in PD are associated with distinct tremor clusters in ventral thalamus_annotated_ann.json"}, {"pattern": {"sp_index": 673, "sub": ["analyses"], "pred": ["were", "performed"], "nes": {"Chicago": 1, "SPSS": 2}, "cds": {}}, "sp": 1, "ne": 0, "cd": 0, "sid": "111", "total": 1, "doc_id": "./anns_v2/Pedrosa et al., (2012) - Essential tremor and tremor in PD are associated with distinct tremor clusters in ventral thalamus_annotated_ann.json"}, {"pattern": {"nes": {}, "cds": {}}, "sp": 0, "ne": 0, "cd": 0, "sid": "112", "total": 0, "doc_id": "./anns_v2/Pedrosa et al., (2012) - Essential tremor and tremor in PD are associated with distinct tremor clusters in ventral thalamus_annotated_ann.json"}, {"pattern": {"nes": {}, "cds": {}}, "sp": 0, "ne": 0, "cd": 0, "sid": "113", "total": 0, "doc_id": "./anns_v2/Pedrosa et al., (2012) - Essential tremor and tremor in PD are associated with distinct tremor clusters in ventral thalamus_annotated_ann.json"}, {"pattern": {"nes": {}, "cds": {}}, "sp": 0, "ne": 0, "cd": 0, "sid": "114", "total": 0, "doc_id": "./anns_v2/Pedrosa et al., (2012) - Essential tremor and tremor in PD are associated with distinct tremor clusters in ventral thalamus_annotated_ann.json"}, {"pattern": {"nes": {}, "cds": {}}, "sp": 0, "ne": 0, "cd": 0, "sid": "115", "total": 0, "doc_id": "./anns_v2/Pedrosa et al., (2012) - Essential tremor and tremor in PD are associated with distinct tremor clusters in ventral thalamus_annotated_ann.json"}, {"pattern": {"sp_index": -1, "sub": ["we"], "pred": ["registered"], "nes": {}, "cds": {"patients": 2, "LFPs": 2, "heights": 1}}, "sp": 0, "ne": 0, "cd": 126, "sid": "116", "total": 126, "doc_id": "./anns_v2/Pedrosa et al., (2012) - Essential tremor and tremor in PD are associated with distinct tremor clusters in ventral thalamus_annotated_ann.json"}, {"pattern": {"sp_index": -1, "sub": ["duration"], "pred": ["was"], "nes": {}, "cds": {"\u00b1": 1, "s": 3}}, "sp": 0, "ne": 0, "cd": 3, "sid": "117", "total": 3, "doc_id": "./anns_v2/Pedrosa et al., (2012) - Essential tremor and tremor in PD are associated with distinct tremor clusters in ventral thalamus_annotated_ann.json"}, {"pattern": {"sp_index": -1, "sub": ["groups"], "pred": ["had"], "nes": {}, "cds": {"Hz": 2}}, "sp": 0, "ne": 0, "cd": 0, "sid": "118", "total": 0, "doc_id": "./anns_v2/Pedrosa et al., (2012) - Essential tremor and tremor in PD are associated with distinct tremor clusters in ventral thalamus_annotated_ann.json"}, {"pattern": {"sp_index": 38, "sub": ["PD", "patients"], "pred": ["had"], "nes": {}, "cds": {"Hz": 1}}, "sp": 3, "ne": 0, "cd": 0, "sid": "119", "total": 3, "doc_id": "./anns_v2/Pedrosa et al., (2012) - Essential tremor and tremor in PD are associated with distinct tremor clusters in ventral thalamus_annotated_ann.json"}, {"pattern": {"sp_index": -1, "sub": ["ET", "patients"], "pred": ["had", "focused"], "nes": {}, "cds": {}}, "sp": 0, "ne": 0, "cd": 0, "sid": "120", "total": 0, "doc_id": "./anns_v2/Pedrosa et al., (2012) - Essential tremor and tremor in PD are associated with distinct tremor clusters in ventral thalamus_annotated_ann.json"}, {"pattern": {"sp_index": -1, "sub": ["target"], "pred": ["coordinates"], "nes": {"VLp": 1}, "cds": {"mm": 6, "\u00b1": 1}}, "sp": 0, "ne": 8, "cd": 1, "sid": "121", "total": 9, "doc_id": "./anns_v2/Pedrosa et al., (2012) - Essential tremor and tremor in PD are associated with distinct tremor clusters in ventral thalamus_annotated_ann.json"}, {"pattern": {"sp_index": -1, "sub": ["view"], "pred": ["is", "provided"], "nes": {"Fig": 1}, "cds": {}}, "sp": 0, "ne": 1, "cd": 0, "sid": "122", "total": 1, "doc_id": "./anns_v2/Pedrosa et al., (2012) - Essential tremor and tremor in PD are associated with distinct tremor clusters in ventral thalamus_annotated_ann.json"}, {"pattern": {"sp_index": -1, "sub": ["We"], "pred": ["analyzed"], "nes": {"EDC": 1, "EMGs": 1, "LFPs": 1, "FDL": 1}, "cds": {"combinations": 1, "hemispheres": 1}}, "sp": 0, "ne": 1, "cd": 0, "sid": "123", "total": 1, "doc_id": "./anns_v2/Pedrosa et al., (2012) - Essential tremor and tremor in PD are associated with distinct tremor clusters in ventral thalamus_annotated_ann.json"}, {"pattern": {"sp_index": 100, "sub": ["we"], "pred": ["studied"], "nes": {"EMG": 1, "LFP": 1}, "cds": {"combinations": 1, "hemispheres": 1}}, "sp": 2, "ne": 6, "cd": 0, "sid": "124", "total": 8, "doc_id": "./anns_v2/Pedrosa et al., (2012) - Essential tremor and tremor in PD are associated with distinct tremor clusters in ventral thalamus_annotated_ann.json"}, {"pattern": {"sp_index": -1, "sub": ["paradigms"], "pred": ["were", "performed"], "nes": {}, "cds": {}}, "sp": 0, "ne": 0, "cd": 0, "sid": "125", "total": 0, "doc_id": "./anns_v2/Pedrosa et al., (2012) - Essential tremor and tremor in PD are associated with distinct tremor clusters in ventral thalamus_annotated_ann.json"}, {"pattern": {"sp_index": -1, "sub": ["Coherence"], "pred": ["occurred"], "nes": {"EMG": 1, "Coherence": 1, "LFPs": 1}, "cds": {"frequency": 1}}, "sp": 0, "ne": 5, "cd": 0, "sid": "126", "total": 5, "doc_id": "./anns_v2/Pedrosa et al., (2012) - Essential tremor and tremor in PD are associated with distinct tremor clusters in ventral thalamus_annotated_ann.json"}, {"pattern": {"sp_index": 104, "sub": ["we"], "pred": ["identified"], "nes": {}, "cds": {"combinations": 3, "%": 3}}, "sp": 2, "ne": 0, "cd": 0, "sid": "127", "total": 2, "doc_id": "./anns_v2/Pedrosa et al., (2012) - Essential tremor and tremor in PD are associated with distinct tremor clusters in ventral thalamus_annotated_ann.json"}, {"pattern": {"sp_index": -1, "sub": ["coherence"], "pred": ["was", "found"], "nes": {}, "cds": {"combinations": 1, "%": 1}}, "sp": 0, "ne": 0, "cd": 0, "sid": "128", "total": 0, "doc_id": "./anns_v2/Pedrosa et al., (2012) - Essential tremor and tremor in PD are associated with distinct tremor clusters in ventral thalamus_annotated_ann.json"}, {"pattern": {"sp_index": -1, "sub": ["coherence"], "pred": ["was", "observed"], "nes": {}, "cds": {"combinations": 2, "%": 2}}, "sp": 0, "ne": 0, "cd": 0, "sid": "129", "total": 0, "doc_id": "./anns_v2/Pedrosa et al., (2012) - Essential tremor and tremor in PD are associated with distinct tremor clusters in ventral thalamus_annotated_ann.json"}, {"pattern": {"sp_index": -1, "sub": ["coherence"], "pred": ["occurred"], "nes": {}, "cds": {"combinations": 1, "%": 1}}, "sp": 0, "ne": 0, "cd": 0, "sid": "130", "total": 0, "doc_id": "./anns_v2/Pedrosa et al., (2012) - Essential tremor and tremor in PD are associated with distinct tremor clusters in ventral thalamus_annotated_ann.json"}, {"pattern": {"sp_index": 104, "sub": ["we"], "pred": ["identified"], "nes": {}, "cds": {"combinations": 1, "%": 1}}, "sp": 2, "ne": 0, "cd": 0, "sid": "131", "total": 2, "doc_id": "./anns_v2/Pedrosa et al., (2012) - Essential tremor and tremor in PD are associated with distinct tremor clusters in ventral thalamus_annotated_ann.json"}, {"pattern": {"sp_index": -1, "sub": ["we"], "pred": ["detected"], "nes": {}, "cds": {"combinations": 2, "%": 2}}, "sp": 0, "ne": 0, "cd": 0, "sid": "132", "total": 0, "doc_id": "./anns_v2/Pedrosa et al., (2012) - Essential tremor and tremor in PD are associated with distinct tremor clusters in ventral thalamus_annotated_ann.json"}, {"pattern": {"sp_index": -1, "sub": ["coherence"], "pred": ["occurred"], "nes": {}, "cds": {"combinations": 1, "%": 1}}, "sp": 0, "ne": 0, "cd": 0, "sid": "133", "total": 0, "doc_id": "./anns_v2/Pedrosa et al., (2012) - Essential tremor and tremor in PD are associated with distinct tremor clusters in ventral thalamus_annotated_ann.json"}, {"pattern": {"sp_index": 104, "sub": ["we"], "pred": ["identified"], "nes": {}, "cds": {"combinations": 1, "%": 1}}, "sp": 2, "ne": 0, "cd": 0, "sid": "134", "total": 2, "doc_id": "./anns_v2/Pedrosa et al., (2012) - Essential tremor and tremor in PD are associated with distinct tremor clusters in ventral thalamus_annotated_ann.json"}, {"pattern": {"sp_index": -1, "sub": ["overview"], "pred": ["is", "given"], "nes": {"Fig": 2}, "cds": {}}, "sp": 0, "ne": 1, "cd": 0, "sid": "135", "total": 1, "doc_id": "./anns_v2/Pedrosa et al., (2012) - Essential tremor and tremor in PD are associated with distinct tremor clusters in ventral thalamus_annotated_ann.json"}, {"pattern": {"sp_index": 115, "sub": ["patients"], "pred": ["showed"], "nes": {}, "cds": {}}, "sp": 2, "ne": 0, "cd": 0, "sid": "136", "total": 2, "doc_id": "./anns_v2/Pedrosa et al., (2012) - Essential tremor and tremor in PD are associated with distinct tremor clusters in ventral thalamus_annotated_ann.json"}, {"pattern": {"sp_index": -1, "sub": ["Chi", "Square", "Test"], "pred": ["did", "reject"], "nes": {"EDC": 1, "Chi Square Test": 1, "Pearson": 1, "LFP": 1}, "cds": {"patient": 1}}, "sp": 0, "ne": 2, "cd": 4, "sid": "137", "total": 6, "doc_id": "./anns_v2/Pedrosa et al., (2012) - Essential tremor and tremor in PD are associated with distinct tremor clusters in ventral thalamus_annotated_ann.json"}, {"pattern": {"sp_index": -1, "sub": null, "pred": ["see"], "nes": {}, "cds": {}}, "sp": 0, "ne": 0, "cd": 0, "sid": "138", "total": 0, "doc_id": "./anns_v2/Pedrosa et al., (2012) - Essential tremor and tremor in PD are associated with distinct tremor clusters in ventral thalamus_annotated_ann.json"}, {"pattern": {"sp_index": -1, "sub": ["coherence"], "pred": ["was", "taken"], "nes": {"Hence": 1, "EDC": 1}, "cds": {}}, "sp": 0, "ne": 0, "cd": 0, "sid": "139", "total": 0, "doc_id": "./anns_v2/Pedrosa et al., (2012) - Essential tremor and tremor in PD are associated with distinct tremor clusters in ventral thalamus_annotated_ann.json"}, {"pattern": {"sp_index": -1, "sub": ["We"], "pred": ["registered"], "nes": {}, "cds": {"patients": 1}}, "sp": 0, "ne": 0, "cd": 126, "sid": "140", "total": 126, "doc_id": "./anns_v2/Pedrosa et al., (2012) - Essential tremor and tremor in PD are associated with distinct tremor clusters in ventral thalamus_annotated_ann.json"}, {"pattern": {"sp_index": 32, "sub": null, "pred": ["were"], "nes": {}, "cds": {"clusters\u2019": 1}}, "sp": 4, "ne": 0, "cd": 0, "sid": "141", "total": 4, "doc_id": "./anns_v2/Pedrosa et al., (2012) - Essential tremor and tremor in PD are associated with distinct tremor clusters in ventral thalamus_annotated_ann.json"}, {"pattern": {"sp_index": -1, "sub": ["tremor", "clusters"], "pred": ["appeared"], "nes": {"Chi Square Test": 1, "Pearson": 1}, "cds": {}}, "sp": 0, "ne": 0, "cd": 0, "sid": "142", "total": 0, "doc_id": "./anns_v2/Pedrosa et al., (2012) - Essential tremor and tremor in PD are associated with distinct tremor clusters in ventral thalamus_annotated_ann.json"}, {"pattern": {"sp_index": -1, "sub": ["majority"], "pred": ["was", "found"], "nes": {}, "cds": {}}, "sp": 0, "ne": 0, "cd": 0, "sid": "143", "total": 0, "doc_id": "./anns_v2/Pedrosa et al., (2012) - Essential tremor and tremor in PD are associated with distinct tremor clusters in ventral thalamus_annotated_ann.json"}, {"pattern": {"sp_index": -1, "sub": ["distribution"], "pred": ["deviated"], "nes": {}, "cds": {}}, "sp": 0, "ne": 0, "cd": 0, "sid": "144", "total": 0, "doc_id": "./anns_v2/Pedrosa et al., (2012) - Essential tremor and tremor in PD are associated with distinct tremor clusters in ventral thalamus_annotated_ann.json"}, {"pattern": {"nes": {}, "cds": {"clusters": 1}}, "sp": 0, "ne": 0, "cd": 5, "sid": "145", "total": 5, "doc_id": "./anns_v2/Pedrosa et al., (2012) - Essential tremor and tremor in PD are associated with distinct tremor clusters in ventral thalamus_annotated_ann.json"}, {"pattern": {"sp_index": 170, "sub": ["results"], "pred": ["were"], "nes": {}, "cds": {"clusters": 1, "clusters\u2019": 1}}, "sp": 2, "ne": 0, "cd": 5, "sid": "146", "total": 7, "doc_id": "./anns_v2/Pedrosa et al., (2012) - Essential tremor and tremor in PD are associated with distinct tremor clusters in ventral thalamus_annotated_ann.json"}, {"pattern": {"sp_index": -1, "sub": ["total"], "pred": ["be", "found"], "nes": {}, "cds": {"clusters\u2019": 1}}, "sp": 0, "ne": 0, "cd": 0, "sid": "147", "total": 0, "doc_id": "./anns_v2/Pedrosa et al., (2012) - Essential tremor and tremor in PD are associated with distinct tremor clusters in ventral thalamus_annotated_ann.json"}, {"pattern": {"sp_index": -1, "sub": ["number"], "pred": ["ate"], "nes": {}, "cds": {}}, "sp": 0, "ne": 0, "cd": 0, "sid": "148", "total": 0, "doc_id": "./anns_v2/Pedrosa et al., (2012) - Essential tremor and tremor in PD are associated with distinct tremor clusters in ventral thalamus_annotated_ann.json"}, {"pattern": {"sp_index": -1, "sub": ["EDC-coherence"], "pred": ["was", "located"], "nes": {}, "cds": {}}, "sp": 0, "ne": 0, "cd": 0, "sid": "149", "total": 0, "doc_id": "./anns_v2/Pedrosa et al., (2012) - Essential tremor and tremor in PD are associated with distinct tremor clusters in ventral thalamus_annotated_ann.json"}, {"pattern": {"nes": {"MDN": 1, "ILN": 1, "IML": 1, "LDN": 1, "Fig": 1, "VPM": 1, "VLp": 1, "VIM": 1}, "cds": {}}, "sp": 0, "ne": 0, "cd": 0, "sid": "150", "total": 0, "doc_id": "./anns_v2/Pedrosa et al., (2012) - Essential tremor and tremor in PD are associated with distinct tremor clusters in ventral thalamus_annotated_ann.json"}, {"pattern": {"nes": {}, "cds": {}}, "sp": 0, "ne": 0, "cd": 0, "sid": "151", "total": 0, "doc_id": "./anns_v2/Pedrosa et al., (2012) - Essential tremor and tremor in PD are associated with distinct tremor clusters in ventral thalamus_annotated_ann.json"}, {"pattern": {"nes": {"EMG": 2, "Fig": 1, "LFP": 1, "LFPs": 1}, "cds": {"combinations": 3, "patterns": 1, "b": 1, "hemispheres": 3, "/Hz": 1}}, "sp": 0, "ne": 0, "cd": 0, "sid": "152", "total": 0, "doc_id": "./anns_v2/Pedrosa et al., (2012) - Essential tremor and tremor in PD are associated with distinct tremor clusters in ventral thalamus_annotated_ann.json"}, {"pattern": {"nes": {}, "cds": {}}, "sp": 0, "ne": 0, "cd": 0, "sid": "153", "total": 0, "doc_id": "./anns_v2/Pedrosa et al., (2012) - Essential tremor and tremor in PD are associated with distinct tremor clusters in ventral thalamus_annotated_ann.json"}, {"pattern": {"nes": {}, "cds": {}}, "sp": 0, "ne": 0, "cd": 0, "sid": "154", "total": 0, "doc_id": "./anns_v2/Pedrosa et al., (2012) - Essential tremor and tremor in PD are associated with distinct tremor clusters in ventral thalamus_annotated_ann.json"}, {"pattern": {"nes": {}, "cds": {}}, "sp": 0, "ne": 0, "cd": 0, "sid": "155", "total": 0, "doc_id": "./anns_v2/Pedrosa et al., (2012) - Essential tremor and tremor in PD are associated with distinct tremor clusters in ventral thalamus_annotated_ann.json"}, {"pattern": {"sp_index": -1, "sub": ["tremor", "clusters"], "pred": ["found"], "nes": {"EDC": 1, "Fig": 1, "FDL": 1}, "cds": {"patients/hemispheres": 1}}, "sp": 0, "ne": 1, "cd": 0, "sid": "156", "total": 1, "doc_id": "./anns_v2/Pedrosa et al., (2012) - Essential tremor and tremor in PD are associated with distinct tremor clusters in ventral thalamus_annotated_ann.json"}, {"pattern": {"sp_index": 391, "sub": ["We"], "pred": ["recorded"], "nes": {"VLp": 1, "DBS": 1, "LFPs": 1, "ET": 1}, "cds": {}}, "sp": 1, "ne": 22, "cd": 0, "sid": "157", "total": 23, "doc_id": "./anns_v2/Pedrosa et al., (2012) - Essential tremor and tremor in PD are associated with distinct tremor clusters in ventral thalamus_annotated_ann.json"}, {"pattern": {"sp_index": 1363, "sub": ["Our", "data"], "pred": ["show"], "nes": {"VLp": 1, "LFP": 1}, "cds": {}}, "sp": 1, "ne": 10, "cd": 0, "sid": "158", "total": 11, "doc_id": "./anns_v2/Pedrosa et al., (2012) - Essential tremor and tremor in PD are associated with distinct tremor clusters in ventral thalamus_annotated_ann.json"}, {"pattern": {"sp_index": 37, "sub": ["finding"], "pred": ["is"], "nes": {"EDC": 1, "FDL": 1}, "cds": {}}, "sp": 3, "ne": 0, "cd": 0, "sid": "159", "total": 3, "doc_id": "./anns_v2/Pedrosa et al., (2012) - Essential tremor and tremor in PD are associated with distinct tremor clusters in ventral thalamus_annotated_ann.json"}, {"pattern": {"sp_index": -1, "sub": ["findings"], "pred": ["are", "suggest"], "nes": {"STN": 1, "Clinically": 1}, "cds": {}}, "sp": 0, "ne": 32, "cd": 0, "sid": "160", "total": 32, "doc_id": "./anns_v2/Pedrosa et al., (2012) - Essential tremor and tremor in PD are associated with distinct tremor clusters in ventral thalamus_annotated_ann.json"}, {"pattern": {"sp_index": -1, "sub": ["we"], "pred": ["considered"], "nes": {"EMG": 1}, "cds": {"patients": 1}}, "sp": 0, "ne": 4, "cd": 126, "sid": "161", "total": 130, "doc_id": "./anns_v2/Pedrosa et al., (2012) - Essential tremor and tremor in PD are associated with distinct tremor clusters in ventral thalamus_annotated_ann.json"}, {"pattern": {"sp_index": -1, "sub": ["procedure"], "pred": ["is"], "nes": {"VLp": 1, "EMG": 1, "Tasker": 1, "Marsden": 1}, "cds": {}}, "sp": 0, "ne": 12, "cd": 0, "sid": "162", "total": 12, "doc_id": "./anns_v2/Pedrosa et al., (2012) - Essential tremor and tremor in PD are associated with distinct tremor clusters in ventral thalamus_annotated_ann.json"}, {"pattern": {"sp_index": -1, "sub": ["We"], "pred": ["did", "rectify"], "nes": {}, "cds": {}}, "sp": 0, "ne": 0, "cd": 0, "sid": "163", "total": 0, "doc_id": "./anns_v2/Pedrosa et al., (2012) - Essential tremor and tremor in PD are associated with distinct tremor clusters in ventral thalamus_annotated_ann.json"}, {"pattern": {"sp_index": -1, "sub": ["Rectification"], "pred": ["is"], "nes": {"Rectification": 1}, "cds": {"Hz": 1}}, "sp": 0, "ne": 0, "cd": 0, "sid": "164", "total": 0, "doc_id": "./anns_v2/Pedrosa et al., (2012) - Essential tremor and tremor in PD are associated with distinct tremor clusters in ventral thalamus_annotated_ann.json"}, {"pattern": {"sp_index": -1, "sub": ["data"], "pred": ["suggest"], "nes": {"Neto": 1, "McClelland": 1, "Christou": 1}, "cds": {}}, "sp": 0, "ne": 0, "cd": 0, "sid": "165", "total": 0, "doc_id": "./anns_v2/Pedrosa et al., (2012) - Essential tremor and tremor in PD are associated with distinct tremor clusters in ventral thalamus_annotated_ann.json"}, {"pattern": {"sp_index": -1, "sub": ["we"], "pred": ["refrained"], "nes": {}, "cds": {}}, "sp": 0, "ne": 0, "cd": 0, "sid": "166", "total": 0, "doc_id": "./anns_v2/Pedrosa et al., (2012) - Essential tremor and tremor in PD are associated with distinct tremor clusters in ventral thalamus_annotated_ann.json"}, {"pattern": {"sp_index": -1, "sub": ["ment"], "pred": ["showed"], "nes": {"Brodkey": 1}, "cds": {}}, "sp": 0, "ne": 0, "cd": 0, "sid": "167", "total": 0, "doc_id": "./anns_v2/Pedrosa et al., (2012) - Essential tremor and tremor in PD are associated with distinct tremor clusters in ventral thalamus_annotated_ann.json"}, {"pattern": {"sp_index": -1, "sub": ["sample", "size"], "pred": ["be", "mentioned"], "nes": {}, "cds": {}}, "sp": 0, "ne": 0, "cd": 0, "sid": "168", "total": 0, "doc_id": "./anns_v2/Pedrosa et al., (2012) - Essential tremor and tremor in PD are associated with distinct tremor clusters in ventral thalamus_annotated_ann.json"}, {"pattern": {"sp_index": -1, "sub": ["implantation"], "pred": ["do", "represent"], "nes": {}, "cds": {}}, "sp": 0, "ne": 0, "cd": 0, "sid": "169", "total": 0, "doc_id": "./anns_v2/Pedrosa et al., (2012) - Essential tremor and tremor in PD are associated with distinct tremor clusters in ventral thalamus_annotated_ann.json"}, {"pattern": {"sp_index": 19, "sub": null, "pred": ["is"], "nes": {"Parkinsonian": 1}, "cds": {}}, "sp": 5, "ne": 0, "cd": 0, "sid": "170", "total": 5, "doc_id": "./anns_v2/Pedrosa et al., (2012) - Essential tremor and tremor in PD are associated with distinct tremor clusters in ventral thalamus_annotated_ann.json"}, {"pattern": {"sp_index": -1, "sub": ["patients"], "pred": ["are", "considered"], "nes": {"VLp": 1}, "cds": {}}, "sp": 0, "ne": 8, "cd": 0, "sid": "171", "total": 8, "doc_id": "./anns_v2/Pedrosa et al., (2012) - Essential tremor and tremor in PD are associated with distinct tremor clusters in ventral thalamus_annotated_ann.json"}, {"pattern": {"sp_index": -1, "sub": null, "pred": ["leads", "is"], "nes": {"Hilker": 1, "German Deep Brain Stimulation Association": 1, "Ondo": 1}, "cds": {}}, "sp": 0, "ne": 0, "cd": 0, "sid": "172", "total": 0, "doc_id": "./anns_v2/Pedrosa et al., (2012) - Essential tremor and tremor in PD are associated with distinct tremor clusters in ventral thalamus_annotated_ann.json"}, {"pattern": {"sp_index": -1, "sub": ["fact"], "pred": ["explains"], "nes": {}, "cds": {}}, "sp": 0, "ne": 0, "cd": 0, "sid": "173", "total": 0, "doc_id": "./anns_v2/Pedrosa et al., (2012) - Essential tremor and tremor in PD are associated with distinct tremor clusters in ventral thalamus_annotated_ann.json"}, {"pattern": {"sp_index": -1, "sub": ["number"], "pred": ["is"], "nes": {"Kane": 1, "Marsden": 1}, "cds": {}}, "sp": 0, "ne": 0, "cd": 0, "sid": "174", "total": 0, "doc_id": "./anns_v2/Pedrosa et al., (2012) - Essential tremor and tremor in PD are associated with distinct tremor clusters in ventral thalamus_annotated_ann.json"}, {"pattern": {"sp_index": -1, "sub": ["we"], "pred": ["do", "believe"], "nes": {}, "cds": {}}, "sp": 0, "ne": 0, "cd": 0, "sid": "175", "total": 0, "doc_id": "./anns_v2/Pedrosa et al., (2012) - Essential tremor and tremor in PD are associated with distinct tremor clusters in ventral thalamus_annotated_ann.json"}, {"pattern": {"nes": {"Methodological": 1}, "cds": {}}, "sp": 0, "ne": 0, "cd": 0, "sid": "176", "total": 0, "doc_id": "./anns_v2/Pedrosa et al., (2012) - Essential tremor and tremor in PD are associated with distinct tremor clusters in ventral thalamus_annotated_ann.json"}, {"pattern": {"sp_index": -1, "sub": ["size"], "pred": ["found"], "nes": {"EDC": 1, "Fig": 1, "FDL": 1}, "cds": {"patients": 1, "patients/hemispheres": 1}}, "sp": 0, "ne": 1, "cd": 126, "sid": "177", "total": 127, "doc_id": "./anns_v2/Pedrosa et al., (2012) - Essential tremor and tremor in PD are associated with distinct tremor clusters in ventral thalamus_annotated_ann.json"}, {"pattern": {"nes": {"FDL": 2, "Double": 2, "Single": 4, "LFP": 2, "EDC": 4}, "cds": {"Yes": 2, "cluster\u2019": 1, "Sum": 2}}, "sp": 0, "ne": 0, "cd": 0, "sid": "178", "total": 0, "doc_id": "./anns_v2/Pedrosa et al., (2012) - Essential tremor and tremor in PD are associated with distinct tremor clusters in ventral thalamus_annotated_ann.json"}, {"pattern": {"nes": {"VLp": 1}, "cds": {}}, "sp": 0, "ne": 8, "cd": 0, "sid": "179", "total": 8, "doc_id": "./anns_v2/Pedrosa et al., (2012) - Essential tremor and tremor in PD are associated with distinct tremor clusters in ventral thalamus_annotated_ann.json"}, {"pattern": {"sp_index": -1, "sub": ["tremor", "activity"], "pred": ["is"], "nes": {"Reck": 1, "STN": 1, "Parkinsonian": 1, "VLp": 1}, "cds": {}}, "sp": 0, "ne": 40, "cd": 0, "sid": "180", "total": 40, "doc_id": "./anns_v2/Pedrosa et al., (2012) - Essential tremor and tremor in PD are associated with distinct tremor clusters in ventral thalamus_annotated_ann.json"}, {"pattern": {"sp_index": -1, "sub": ["results"], "pred": ["apply", "are"], "nes": {}, "cds": {}}, "sp": 0, "ne": 0, "cd": 0, "sid": "181", "total": 0, "doc_id": "./anns_v2/Pedrosa et al., (2012) - Essential tremor and tremor in PD are associated with distinct tremor clusters in ventral thalamus_annotated_ann.json"}, {"pattern": {"sp_index": -1, "sub": ["characterization"], "pred": ["revealed"], "nes": {"Lenz": 1}, "cds": {}}, "sp": 0, "ne": 0, "cd": 0, "sid": "182", "total": 0, "doc_id": "./anns_v2/Pedrosa et al., (2012) - Essential tremor and tremor in PD are associated with distinct tremor clusters in ventral thalamus_annotated_ann.json"}, {"pattern": {"sp_index": -1, "sub": ["animal", "studies"], "pred": ["suggest"], "nes": {"Mason": 1}, "cds": {"joint": 1}}, "sp": 0, "ne": 0, "cd": 0, "sid": "183", "total": 0, "doc_id": "./anns_v2/Pedrosa et al., (2012) - Essential tremor and tremor in PD are associated with distinct tremor clusters in ventral thalamus_annotated_ann.json"}, {"pattern": {"sp_index": 19, "sub": null, "pred": ["is"], "nes": {"Lenz": 1}, "cds": {}}, "sp": 5, "ne": 0, "cd": 0, "sid": "184", "total": 5, "doc_id": "./anns_v2/Pedrosa et al., (2012) - Essential tremor and tremor in PD are associated with distinct tremor clusters in ventral thalamus_annotated_ann.json"}, {"pattern": {"sp_index": 1190, "sub": ["it"], "pred": ["is"], "nes": {}, "cds": {}}, "sp": 1, "ne": 0, "cd": 0, "sid": "185", "total": 1, "doc_id": "./anns_v2/Pedrosa et al., (2012) - Essential tremor and tremor in PD are associated with distinct tremor clusters in ventral thalamus_annotated_ann.json"}, {"pattern": {"sp_index": -1, "sub": ["studies"], "pred": ["tried"], "nes": {}, "cds": {}}, "sp": 0, "ne": 0, "cd": 0, "sid": "186", "total": 0, "doc_id": "./anns_v2/Pedrosa et al., (2012) - Essential tremor and tremor in PD are associated with distinct tremor clusters in ventral thalamus_annotated_ann.json"}, {"pattern": {"sp_index": -1, "sub": ["one"], "pred": ["PD"], "nes": {"VLp": 1, "Krack": 1, "Marsden": 1}, "cds": {"patients": 2, "patient": 1}}, "sp": 0, "ne": 8, "cd": 130, "sid": "187", "total": 138, "doc_id": "./anns_v2/Pedrosa et al., (2012) - Essential tremor and tremor in PD are associated with distinct tremor clusters in ventral thalamus_annotated_ann.json"}, {"pattern": {"sp_index": -1, "sub": ["They"], "pred": ["found"], "nes": {"Marsden": 1}, "cds": {"Hz": 1, "groups": 1}}, "sp": 0, "ne": 0, "cd": 9, "sid": "188", "total": 9, "doc_id": "./anns_v2/Pedrosa et al., (2012) - Essential tremor and tremor in PD are associated with distinct tremor clusters in ventral thalamus_annotated_ann.json"}, {"pattern": {"sp_index": -1, "sub": ["Kane", "al."], "pred": ["analyzed"], "nes": {"Kane": 1}, "cds": {}}, "sp": 0, "ne": 0, "cd": 0, "sid": "189", "total": 0, "doc_id": "./anns_v2/Pedrosa et al., (2012) - Essential tremor and tremor in PD are associated with distinct tremor clusters in ventral thalamus_annotated_ann.json"}, {"pattern": {"sp_index": -1, "sub": ["They"], "pred": ["showed"], "nes": {"Jones": 1, "Kane": 1, "Vim": 1, "Nucleus": 1, "VLp": 1, "Krack": 1}, "cds": {"Hz": 1}}, "sp": 0, "ne": 8, "cd": 0, "sid": "190", "total": 8, "doc_id": "./anns_v2/Pedrosa et al., (2012) - Essential tremor and tremor in PD are associated with distinct tremor clusters in ventral thalamus_annotated_ann.json"}, {"pattern": {"sp_index": -1, "sub": ["groups"], "pred": ["were"], "nes": {}, "cds": {}}, "sp": 0, "ne": 0, "cd": 0, "sid": "191", "total": 0, "doc_id": "./anns_v2/Pedrosa et al., (2012) - Essential tremor and tremor in PD are associated with distinct tremor clusters in ventral thalamus_annotated_ann.json"}, {"pattern": {"sp_index": -1, "sub": ["we"], "pred": ["like"], "nes": {"PSA": 1, "Barbe": 1}, "cds": {}}, "sp": 0, "ne": 0, "cd": 0, "sid": "192", "total": 0, "doc_id": "./anns_v2/Pedrosa et al., (2012) - Essential tremor and tremor in PD are associated with distinct tremor clusters in ventral thalamus_annotated_ann.json"}, {"pattern": {"sp_index": -1, "sub": ["Our", "results"], "pred": ["revealed"], "nes": {"Figs": 1}, "cds": {}}, "sp": 0, "ne": 1, "cd": 0, "sid": "193", "total": 1, "doc_id": "./anns_v2/Pedrosa et al., (2012) - Essential tremor and tremor in PD are associated with distinct tremor clusters in ventral thalamus_annotated_ann.json"}, {"pattern": {"sp_index": -1, "sub": ["explanation"], "pred": ["be", "diversify"], "nes": {}, "cds": {"explanation": 1}}, "sp": 0, "ne": 0, "cd": 0, "sid": "194", "total": 0, "doc_id": "./anns_v2/Pedrosa et al., (2012) - Essential tremor and tremor in PD are associated with distinct tremor clusters in ventral thalamus_annotated_ann.json"}, {"pattern": {"sp_index": -1, "sub": null, "pred": ["explain"], "nes": {"VLp": 2, "PSA": 1}, "cds": {}}, "sp": 0, "ne": 8, "cd": 0, "sid": "195", "total": 8, "doc_id": "./anns_v2/Pedrosa et al., (2012) - Essential tremor and tremor in PD are associated with distinct tremor clusters in ventral thalamus_annotated_ann.json"}, {"pattern": {"sp_index": 104, "sub": ["we"], "pred": ["identified"], "nes": {}, "cds": {"patterns": 1}}, "sp": 2, "ne": 0, "cd": 0, "sid": "196", "total": 2, "doc_id": "./anns_v2/Pedrosa et al., (2012) - Essential tremor and tremor in PD are associated with distinct tremor clusters in ventral thalamus_annotated_ann.json"}, {"pattern": {"sp_index": -1, "sub": ["Our", "recordings"], "pred": ["have", "separated"], "nes": {}, "cds": {"mm": 2, "macroelectrodes": 1}}, "sp": 0, "ne": 0, "cd": 1, "sid": "197", "total": 1, "doc_id": "./anns_v2/Pedrosa et al., (2012) - Essential tremor and tremor in PD are associated with distinct tremor clusters in ventral thalamus_annotated_ann.json"}, {"pattern": {"sp_index": -1, "sub": ["We"], "pred": ["identified", "detected"], "nes": {}, "cds": {}}, "sp": 0, "ne": 0, "cd": 0, "sid": "198", "total": 0, "doc_id": "./anns_v2/Pedrosa et al., (2012) - Essential tremor and tremor in PD are associated with distinct tremor clusters in ventral thalamus_annotated_ann.json"}, {"pattern": {"sp_index": -1, "sub": ["we"], "pred": ["focused", "evaluated"], "nes": {"EMG": 1, "Kane": 1}, "cds": {}}, "sp": 0, "ne": 4, "cd": 0, "sid": "199", "total": 4, "doc_id": "./anns_v2/Pedrosa et al., (2012) - Essential tremor and tremor in PD are associated with distinct tremor clusters in ventral thalamus_annotated_ann.json"}, {"pattern": {"sp_index": -1, "sub": ["pathophysiology"], "pred": ["be", "expected"], "nes": {"PD": 1}, "cds": {}}, "sp": 0, "ne": 12, "cd": 0, "sid": "200", "total": 12, "doc_id": "./anns_v2/Pedrosa et al., (2012) - Essential tremor and tremor in PD are associated with distinct tremor clusters in ventral thalamus_annotated_ann.json"}, {"pattern": {"sp_index": 48, "sub": null, "pred": ["are"], "nes": {}, "cds": {}}, "sp": 3, "ne": 0, "cd": 0, "sid": "201", "total": 3, "doc_id": "./anns_v2/Pedrosa et al., (2012) - Essential tremor and tremor in PD are associated with distinct tremor clusters in ventral thalamus_annotated_ann.json"}, {"pattern": {"sp_index": -1, "sub": ["ET", "patients"], "pred": ["have"], "nes": {"Tan": 1}, "cds": {}}, "sp": 0, "ne": 0, "cd": 0, "sid": "202", "total": 0, "doc_id": "./anns_v2/Pedrosa et al., (2012) - Essential tremor and tremor in PD are associated with distinct tremor clusters in ventral thalamus_annotated_ann.json"}, {"pattern": {"sp_index": -1, "sub": null, "pred": ["be", "detected"], "nes": {}, "cds": {}}, "sp": 0, "ne": 0, "cd": 0, "sid": "203", "total": 0, "doc_id": "./anns_v2/Pedrosa et al., (2012) - Essential tremor and tremor in PD are associated with distinct tremor clusters in ventral thalamus_annotated_ann.json"}, {"pattern": {"sp_index": -1, "sub": ["features"], "pred": ["have", "been", "found"], "nes": {}, "cds": {}}, "sp": 0, "ne": 0, "cd": 0, "sid": "204", "total": 0, "doc_id": "./anns_v2/Pedrosa et al., (2012) - Essential tremor and tremor in PD are associated with distinct tremor clusters in ventral thalamus_annotated_ann.json"}, {"pattern": {"sp_index": -1, "sub": ["tremor"], "pred": ["is", "supposed"], "nes": {}, "cds": {}}, "sp": 0, "ne": 0, "cd": 0, "sid": "205", "total": 0, "doc_id": "./anns_v2/Pedrosa et al., (2012) - Essential tremor and tremor in PD are associated with distinct tremor clusters in ventral thalamus_annotated_ann.json"}, {"pattern": {"sp_index": -1, "sub": ["brain", "areas"], "pred": ["act", "entrain", "being", "entrained"], "nes": {"Deuschl": 1, "Different": 1, "Raethjen": 1}, "cds": {}}, "sp": 0, "ne": 0, "cd": 0, "sid": "206", "total": 0, "doc_id": "./anns_v2/Pedrosa et al., (2012) - Essential tremor and tremor in PD are associated with distinct tremor clusters in ventral thalamus_annotated_ann.json"}, {"pattern": {"sp_index": -1, "sub": ["motor", "cortex"], "pred": ["is", "assumed"], "nes": {"Raethjen": 1}, "cds": {}}, "sp": 0, "ne": 0, "cd": 0, "sid": "207", "total": 0, "doc_id": "./anns_v2/Pedrosa et al., (2012) - Essential tremor and tremor in PD are associated with distinct tremor clusters in ventral thalamus_annotated_ann.json"}, {"pattern": {"sp_index": -1, "sub": ["interaction"], "pred": ["seems"], "nes": {}, "cds": {}}, "sp": 0, "ne": 0, "cd": 0, "sid": "208", "total": 0, "doc_id": "./anns_v2/Pedrosa et al., (2012) - Essential tremor and tremor in PD are associated with distinct tremor clusters in ventral thalamus_annotated_ann.json"}, {"pattern": {"sp_index": -1, "sub": ["Our", "results"], "pred": ["support"], "nes": {"VLp": 1}, "cds": {}}, "sp": 0, "ne": 8, "cd": 0, "sid": "209", "total": 8, "doc_id": "./anns_v2/Pedrosa et al., (2012) - Essential tremor and tremor in PD are associated with distinct tremor clusters in ventral thalamus_annotated_ann.json"}, {"pattern": {"sp_index": -1, "sub": ["recording"], "pred": ["was", "performed"], "nes": {}, "cds": {}}, "sp": 0, "ne": 0, "cd": 0, "sid": "210", "total": 0, "doc_id": "./anns_v2/Pedrosa et al., (2012) - Essential tremor and tremor in PD are associated with distinct tremor clusters in ventral thalamus_annotated_ann.json"}, {"pattern": {"sp_index": -1, "sub": ["Tremor"], "pred": ["results"], "nes": {"Tremor": 1, "Parkinson": 1}, "cds": {}}, "sp": 0, "ne": 5, "cd": 0, "sid": "211", "total": 5, "doc_id": "./anns_v2/Pedrosa et al., (2012) - Essential tremor and tremor in PD are associated with distinct tremor clusters in ventral thalamus_annotated_ann.json"}, {"pattern": {"sp_index": -1, "sub": ["patients"], "pred": ["reveal"], "nes": {}, "cds": {}}, "sp": 0, "ne": 0, "cd": 0, "sid": "212", "total": 0, "doc_id": "./anns_v2/Pedrosa et al., (2012) - Essential tremor and tremor in PD are associated with distinct tremor clusters in ventral thalamus_annotated_ann.json"}, {"pattern": {"nes": {}, "cds": {}}, "sp": 0, "ne": 0, "cd": 0, "sid": "213", "total": 0, "doc_id": "./anns_v2/Pedrosa et al., (2012) - Essential tremor and tremor in PD are associated with distinct tremor clusters in ventral thalamus_annotated_ann.json"}, {"pattern": {"sp_index": -1, "sub": ["switch"], "pred": ["causes"], "nes": {"Helmich": 1}, "cds": {}}, "sp": 0, "ne": 0, "cd": 0, "sid": "214", "total": 0, "doc_id": "./anns_v2/Pedrosa et al., (2012) - Essential tremor and tremor in PD are associated with distinct tremor clusters in ventral thalamus_annotated_ann.json"}, {"pattern": {"sp_index": -1, "sub": ["loops"], "pred": ["need"], "nes": {"Parkinsonian": 1}, "cds": {}}, "sp": 0, "ne": 0, "cd": 0, "sid": "215", "total": 0, "doc_id": "./anns_v2/Pedrosa et al., (2012) - Essential tremor and tremor in PD are associated with distinct tremor clusters in ventral thalamus_annotated_ann.json"}, {"pattern": {"sp_index": -1, "sub": ["activity"], "pred": ["is"], "nes": {}, "cds": {}}, "sp": 0, "ne": 0, "cd": 0, "sid": "216", "total": 0, "doc_id": "./anns_v2/Pedrosa et al., (2012) - Essential tremor and tremor in PD are associated with distinct tremor clusters in ventral thalamus_annotated_ann.json"}, {"pattern": {"sp_index": -1, "sub": ["segregation"], "pred": ["be", "transmitted"], "nes": {"Reck": 1, "STN": 1, "VLp": 1}, "cds": {}}, "sp": 0, "ne": 40, "cd": 0, "sid": "217", "total": 40, "doc_id": "./anns_v2/Pedrosa et al., (2012) - Essential tremor and tremor in PD are associated with distinct tremor clusters in ventral thalamus_annotated_ann.json"}, {"pattern": {"sp_index": -1, "sub": ["findings"], "pred": ["were"], "nes": {"VLp": 1}, "cds": {}}, "sp": 0, "ne": 8, "cd": 0, "sid": "218", "total": 8, "doc_id": "./anns_v2/Pedrosa et al., (2012) - Essential tremor and tremor in PD are associated with distinct tremor clusters in ventral thalamus_annotated_ann.json"}, {"pattern": {"sp_index": -1, "sub": null, "pred": ["result"], "nes": {}, "cds": {}}, "sp": 0, "ne": 0, "cd": 0, "sid": "219", "total": 0, "doc_id": "./anns_v2/Pedrosa et al., (2012) - Essential tremor and tremor in PD are associated with distinct tremor clusters in ventral thalamus_annotated_ann.json"}, {"pattern": {"sp_index": -1, "sub": ["analysis"], "pred": ["need"], "nes": {"LFP": 1}, "cds": {}}, "sp": 0, "ne": 2, "cd": 0, "sid": "220", "total": 2, "doc_id": "./anns_v2/Pedrosa et al., (2012) - Essential tremor and tremor in PD are associated with distinct tremor clusters in ventral thalamus_annotated_ann.json"}, {"pattern": {"sp_index": -1, "sub": ["analysis"], "pred": ["result"], "nes": {}, "cds": {}}, "sp": 0, "ne": 0, "cd": 0, "sid": "221", "total": 0, "doc_id": "./anns_v2/Pedrosa et al., (2012) - Essential tremor and tremor in PD are associated with distinct tremor clusters in ventral thalamus_annotated_ann.json"}, {"pattern": {"nes": {}, "cds": {}}, "sp": 0, "ne": 0, "cd": 0, "sid": "222", "total": 0, "doc_id": "./anns_v2/Pedrosa et al., (2012) - Essential tremor and tremor in PD are associated with distinct tremor clusters in ventral thalamus_annotated_ann.json"}, {"pattern": {"sp_index": -1, "sub": ["Patient", "number", "Disease", "Significant", "coherence", "LFP-EMG", "Single"], "pred": ["tremor"], "nes": {"Double": 1, "Single": 1, "Disease Significant": 1}, "cds": {}}, "sp": 0, "ne": 2, "cd": 0, "sid": "223", "total": 2, "doc_id": "./anns_v2/Pedrosa et al., (2012) - Essential tremor and tremor in PD are associated with distinct tremor clusters in ventral thalamus_annotated_ann.json"}, {"pattern": {"nes": {}, "cds": {}}, "sp": 0, "ne": 0, "cd": 0, "sid": "224", "total": 0, "doc_id": "./anns_v2/Pedrosa et al., (2012) - Essential tremor and tremor in PD are associated with distinct tremor clusters in ventral thalamus_annotated_ann.json"}, {"pattern": {"sp_index": -1, "sub": null, "pred": ["PD"], "nes": {}, "cds": {}}, "sp": 0, "ne": 0, "cd": 0, "sid": "225", "total": 0, "doc_id": "./anns_v2/Pedrosa et al., (2012) - Essential tremor and tremor in PD are associated with distinct tremor clusters in ventral thalamus_annotated_ann.json"}, {"pattern": {"nes": {}, "cds": {}}, "sp": 0, "ne": 0, "cd": 0, "sid": "226", "total": 0, "doc_id": "./anns_v2/Pedrosa et al., (2012) - Essential tremor and tremor in PD are associated with distinct tremor clusters in ventral thalamus_annotated_ann.json"}, {"pattern": {"nes": {}, "cds": {}}, "sp": 0, "ne": 0, "cd": 0, "sid": "227", "total": 0, "doc_id": "./anns_v2/Pedrosa et al., (2012) - Essential tremor and tremor in PD are associated with distinct tremor clusters in ventral thalamus_annotated_ann.json"}, {"pattern": {"nes": {}, "cds": {"Sum": 1}}, "sp": 0, "ne": 0, "cd": 0, "sid": "228", "total": 0, "doc_id": "./anns_v2/Pedrosa et al., (2012) - Essential tremor and tremor in PD are associated with distinct tremor clusters in ventral thalamus_annotated_ann.json"}, {"pattern": {"sp_index": -1, "sub": ["distribution"], "pred": ["Unequal"], "nes": {"EDC": 1, "Unequal": 1}, "cds": {}}, "sp": 0, "ne": 0, "cd": 0, "sid": "229", "total": 0, "doc_id": "./anns_v2/Pedrosa et al., (2012) - Essential tremor and tremor in PD are associated with distinct tremor clusters in ventral thalamus_annotated_ann.json"}, {"pattern": {"nes": {"Double": 2, "Single": 4, "FDL": 2, "EDC": 2}, "cds": {"Distribution": 2, "distribution": 1, "Sum": 2}}, "sp": 0, "ne": 0, "cd": 0, "sid": "230", "total": 0, "doc_id": "./anns_v2/Pedrosa et al., (2012) - Essential tremor and tremor in PD are associated with distinct tremor clusters in ventral thalamus_annotated_ann.json"}, {"pattern": {"sp_index": -1, "sub": ["clusters"], "pred": ["Tremor"], "nes": {}, "cds": {}}, "sp": 0, "ne": 0, "cd": 0, "sid": "231", "total": 0, "doc_id": "./anns_v2/Pedrosa et al., (2012) - Essential tremor and tremor in PD are associated with distinct tremor clusters in ventral thalamus_annotated_ann.json"}, {"pattern": {"nes": {"EDC": 1, "Unequal": 1}, "cds": {}}, "sp": 0, "ne": 0, "cd": 0, "sid": "232", "total": 0, "doc_id": "./anns_v2/Pedrosa et al., (2012) - Essential tremor and tremor in PD are associated with distinct tremor clusters in ventral thalamus_annotated_ann.json"}, {"pattern": {"nes": {"Tremor": 1}, "cds": {}}, "sp": 0, "ne": 0, "cd": 0, "sid": "233", "total": 0, "doc_id": "./anns_v2/Pedrosa et al., (2012) - Essential tremor and tremor in PD are associated with distinct tremor clusters in ventral thalamus_annotated_ann.json"}, {"pattern": {"nes": {"Double": 1}, "cds": {}}, "sp": 0, "ne": 0, "cd": 0, "sid": "234", "total": 0, "doc_id": "./anns_v2/Pedrosa et al., (2012) - Essential tremor and tremor in PD are associated with distinct tremor clusters in ventral thalamus_annotated_ann.json"}, {"pattern": {"sp_index": -1, "sub": ["study"], "pred": ["showed"], "nes": {"STN": 1, "PD": 1}, "cds": {}}, "sp": 0, "ne": 44, "cd": 0, "sid": "235", "total": 44, "doc_id": "./anns_v2/Pedrosa et al., (2012) - Essential tremor and tremor in PD are associated with distinct tremor clusters in ventral thalamus_annotated_ann.json"}, {"pattern": {"sp_index": -1, "sub": ["our", "data"], "pred": ["suggest"], "nes": {"ET": 1, "VLp": 1}, "cds": {}}, "sp": 0, "ne": 10, "cd": 0, "sid": "236", "total": 10, "doc_id": "./anns_v2/Pedrosa et al., (2012) - Essential tremor and tremor in PD are associated with distinct tremor clusters in ventral thalamus_annotated_ann.json"}, {"pattern": {"sp_index": -1, "sub": ["D.P.", "M.M", "L.W.", "V.S.", "A.S.", "L.T"], "pred": ["received"], "nes": {"Medtronic": 1}, "cds": {}}, "sp": 0, "ne": 0, "cd": 0, "sid": "237", "total": 0, "doc_id": "./anns_v2/Pedrosa et al., (2012) - Essential tremor and tremor in PD are associated with distinct tremor clusters in ventral thalamus_annotated_ann.json"}, {"pattern": {"sp_index": -1, "sub": ["Christiane", "Reck"], "pred": ["works", "reports"], "nes": {"Christiane Reck": 1}, "cds": {}}, "sp": 0, "ne": 0, "cd": 0, "sid": "238", "total": 0, "doc_id": "./anns_v2/Pedrosa et al., (2012) - Essential tremor and tremor in PD are associated with distinct tremor clusters in ventral thalamus_annotated_ann.json"}, {"pattern": {"sp_index": -1, "sub": ["study"], "pred": ["was", "supported"], "nes": {"Ursula M\u00fcller": 1}, "cds": {}}, "sp": 0, "ne": 0, "cd": 0, "sid": "239", "total": 0, "doc_id": "./anns_v2/Pedrosa et al., (2012) - Essential tremor and tremor in PD are associated with distinct tremor clusters in ventral thalamus_annotated_ann.json"}, {"pattern": {"nes": {}, "cds": {}}, "sp": 0, "ne": 0, "cd": 0, "sid": "240", "total": 0, "doc_id": "./anns_v2/Pedrosa et al., (2012) - Essential tremor and tremor in PD are associated with distinct tremor clusters in ventral thalamus_annotated_ann.json"}, {"pattern": {"sp_index": -1, "sub": ["T."], "pred": ["acknowledges"], "nes": {}, "cds": {}}, "sp": 0, "ne": 0, "cd": 0, "sid": "241", "total": 0, "doc_id": "./anns_v2/Pedrosa et al., (2012) - Essential tremor and tremor in PD are associated with distinct tremor clusters in ventral thalamus_annotated_ann.json"}, {"pattern": {"nes": {"German Research Foundation": 1, "BMBF": 1, "Klinische Forschergruppe": 1, "German Ministry": 1, "DFG": 1, "Education": 1}, "cds": {}}, "sp": 0, "ne": 0, "cd": 0, "sid": "242", "total": 0, "doc_id": "./anns_v2/Pedrosa et al., (2012) - Essential tremor and tremor in PD are associated with distinct tremor clusters in ventral thalamus_annotated_ann.json"}, {"pattern": {"sp_index": -1, "sub": ["authors"], "pred": ["report", "do", "have"], "nes": {}, "cds": {}}, "sp": 0, "ne": 0, "cd": 0, "sid": "243", "total": 0, "doc_id": "./anns_v2/Pedrosa et al., (2012) - Essential tremor and tremor in PD are associated with distinct tremor clusters in ventral thalamus_annotated_ann.json"}, {"pattern": {"sp_index": -1, "sub": ["data"], "pred": ["be", "found"], "nes": {}, "cds": {}}, "sp": 0, "ne": 0, "cd": 0, "sid": "244", "total": 0, "doc_id": "./anns_v2/Pedrosa et al., (2012) - Essential tremor and tremor in PD are associated with distinct tremor clusters in ventral thalamus_annotated_ann.json"}, {"pattern": {"nes": {}, "cds": {}}, "sp": 0, "ne": 0, "cd": 0, "sid": "245", "total": 0, "doc_id": "./anns_v2/Pedrosa et al., (2012) - Essential tremor and tremor in PD are associated with distinct tremor clusters in ventral thalamus_annotated_ann.json"}, {"pattern": {"nes": {"Kwan": 3, "Christou": 1, "Srinivasan": 1, "Schnitzler": 8, "Hariz": 3, "Deyng": 1, "Wilkinson": 2, "Reck": 1, "Schelter": 1, "Gay": 2, "Groiss": 2, "Kopper": 1, "Bloem": 1, "Gervason": 1, "Gao": 2, "Part": 1, "Book Medical Publishers": 1, "Tremor": 1, "Ilinsky": 2, "Perret": 1, "MEG": 2, "Marsden": 1, "Grieszbach": 1, "Ohara": 1, "Clin": 3, "Harley": 1, "Breeze": 2, "Reich": 1, "Benabid": 2, "Neto": 1, "Heneghan": 1, "Garonzik": 1, "Schwartz": 1, "Asanuma": 1, "Koller": 2, "Tucker": 1, "Toni": 1, "Fink": 3, "Voges": 2, "Bain": 1, "Brain Res": 3, "EMG": 4, "Benazzouz": 1, "Koskinen": 1, "Mills": 1, "Mason": 1, "Kahraman": 1, "Farmer": 1, "Kircheis": 1, "EEG": 2, "Hutchison": 1, "Yamashiro": 1, "Hoffmann": 2, "German Deep Brain Stimulation Association": 1, "Tasker": 4, "Schrader": 1, "Haussinger": 1, "Lange": 1, "Schmidt": 1, "Cvetkovic": 1, "Helmich": 1, "Butz": 1, "Brillinger": 1, "Parkinsonian": 5, "Hilker": 1, "Barbe": 1, "Brown": 2, "Hamani": 1, "Ashby": 1, "Stuttgart": 1, "PubMed": 3, "Volkmann": 2, "Fogel": 1, "Limousin": 2, "Hellwig": 1, "Maarouf": 3, "Silberstein": 1, "Lyons": 1, "LINGO1": 2, "Rosenberg": 2, "Parkinson": 6, "Vim": 1, "Maldonado": 1, "Rothwell": 1, "McAndrews": 1, "Macaca": 1, "Vesper": 1, "Vaughan": 1, "Florin": 4, "Rehncrona": 1, "Cadusch": 1, "Martin": 1, "Widner": 1, "Deuschl": 4, "Amjad": 2, "Hassler": 1, "Wojtecki": 3, "Hua": 1, "Yue": 1, "Chicago": 1, "Jankovic": 1, "Govindan": 1, "Lenz": 5, "Sydow": 1, "Muthuraman": 1, "Wijesinghe": 1, "Janssen": 1, "Allert": 1, "Lozano": 3, "Pahwa": 2, "Pallidal": 1, "Payen": 1, "Henschel": 1, "Oyen": 1, "Sreenivasan": 1, "Sturm": 4, "Conway": 1, "Timmer": 1, "Dougherty": 1, "Lowery": 1, "Schmaljohann": 1, "Thach": 1, "Brin": 1, "Dostrovsky": 6, "Pollak": 2, "Pfister": 1, "Salenius": 1, "Vitek": 1, "Gross": 4, "Hommel": 1, "Macchi": 1, "Wenzelburger": 1, "Himmel": 1, "IEEE Trans": 1, "Hodaie": 1, "Liu": 1, "Runge": 1, "Stereotaxy": 1, "McClelland": 1, "Kupsch": 1, "Freund": 1, "Tornqvist": 1, "Murphy": 2, "Laplacians": 1, "Krause": 2, "Human Brain": 1, "Lucking": 1, "Zirh": 1, "Nowak": 1, "Jones": 3, "Dirks": 1, "Westdorp": 1, "Timmermann": 8, "Liebhart": 1, "Schaltenbrand": 1, "Activity": 1, "Fourier": 1, "Simpson": 1, "Munks": 1, "Lindemann": 1, "Brodkey": 1, "Almaguer": 1, "Single": 2, "Benecke": 1, "Wahren": 1, "Johnels": 1}, "cds": {"Mar": 1}}, "sp": 0, "ne": 0, "cd": 0, "sid": "246", "total": 0, "doc_id": "./anns_v2/Pedrosa et al., (2012) - Essential tremor and tremor in PD are associated with distinct tremor clusters in ventral thalamus_annotated_ann.json"}]