[{"ncbo": [{"uri": "http://purl.obolibrary.org/obo/PATO_0000618", "annotation": {"to": 20, "matchType": "PREF", "from": 12, "text": "BILATERAL"}}, {"uri": "http://purl.obolibrary.org/obo/HP_0012832", "annotation": {"to": 20, "matchType": "PREF", "from": 12, "text": "BILATERAL"}}, {"uri": "http://purl.org/sig/ont/fma/fma62035", "annotation": {"to": 59, "matchType": "PREF", "from": 41, "text": "SUBTHALAMIC NUCLEUS"}}, {"uri": "http://purl.obolibrary.org/obo/GO_0005634", "annotation": {"to": 59, "matchType": "PREF", "from": 53, "text": "NUCLEUS"}}, {"uri": "http://purl.obolibrary.org/obo/HP_0012828", "annotation": {"to": 83, "matchType": "PREF", "from": 78, "text": "SEVERE"}}], "end": 128, "struct": "DoCO:Title", "text": "", "start": 0, "sid": "1"}, {"ncbo": [{"uri": "http://purl.obolibrary.org/obo/PATO_0000618", "annotation": {"to": 192, "matchType": "PREF", "from": 184, "text": "BILATERAL"}}, {"uri": "http://purl.obolibrary.org/obo/HP_0012832", "annotation": {"to": 192, "matchType": "PREF", "from": 184, "text": "BILATERAL"}}, {"uri": "http://purl.obolibrary.org/obo/PATO_0000456", "annotation": {"to": 137, "matchType": "PREF", "from": 130, "text": "ABSTRACT"}}, {"uri": "http://purl.obolibrary.org/obo/PATO_0000467", "annotation": {"to": 149, "matchType": "PREF", "from": 143, "text": "PRESENT"}}, {"uri": "http://purl.obolibrary.org/obo/PATO_0001596", "annotation": {"to": 197, "matchType": "SYN", "from": 194, "text": "DEEP"}}, {"uri": "http://purl.org/sig/ont/fma/fma50801", "annotation": {"to": 203, "matchType": "PREF", "from": 199, "text": "BRAIN"}}], "end": 345, "struct": "DoCO:Abstract", "CoreSc": "Bac", "text": "", "marked": ["subthalamic nuclei (STN)"], "start": 129, "sid": "2"}, {"ncbo": [{"uri": "http://purl.obolibrary.org/obo/PATO_0000694", "annotation": {"to": 396, "matchType": "SYN", "from": 389, "text": "ADVANCED"}}, {"uri": "http://purl.obolibrary.org/obo/PATO_0000487", "annotation": {"to": 420, "matchType": "SYN", "from": 411, "text": "RESPONSIVE"}}, {"uri": "http://purl.obolibrary.org/obo/HP_0100660", "annotation": {"to": 639, "matchType": "SYN", "from": 629, "text": "DYSKINESIAS"}}], "end": 640, "struct": "DoCO:Abstract", "CoreSc": "Bac", "text": "", "marked": ["26 patients"], "start": 346, "sid": "3"}, {"ncbo": [{"uri": "http://purl.obolibrary.org/obo/PATO_0001177", "annotation": {"to": 737, "matchType": "PREF", "from": 733, "text": "BLIND"}}], "end": 792, "struct": "DoCO:Abstract", "CoreSc": "Bac", "text": "", "start": 641, "sid": "4"}, {"end": 901, "struct": "DoCO:Abstract", "start": 793, "text": "", "CoreSc": "Bac", "sid": "5"}, {"ncbo": [{"uri": "http://purl.obolibrary.org/obo/HP_0100660", "annotation": {"to": 1109, "matchType": "SYN", "from": 1099, "text": "DYSKINESIAS"}}, {"uri": "http://purl.obolibrary.org/obo/PATO_0000011", "annotation": {"to": 1031, "matchType": "PREF", "from": 1029, "text": "AGE"}}, {"uri": "http://purl.org/sig/ont/fma/fma0328408", "annotation": {"to": 1031, "matchType": "PREF", "from": 1029, "text": "AGE"}}], "end": 1110, "struct": "DoCO:BodyMatter", "CoreSc": "Bac", "text": "", "marked": ["develop complications in the form of motor fluctuations", "motor fluctuations"], "start": 902, "sid": "6", "page": "1"}, {"ncbo": [{"uri": "http://purl.org/sig/ont/fma/fma67238", "annotation": {"to": 1149, "matchType": "PREF", "from": 1142, "text": "DOPAMINE"}}, {"uri": "http://purl.obolibrary.org/obo/GO_0032502", "annotation": {"to": 1202, "matchType": "SYN", "from": 1192, "text": "DEVELOPMENT"}}], "end": 1253, "struct": "DoCO:BodyMatter", "CoreSc": "Bac", "text": "", "start": 1111, "sid": "7", "page": "1"}, {"ncbo": [{"uri": "http://purl.obolibrary.org/obo/PATO_0000694", "annotation": {"to": 1332, "matchType": "SYN", "from": 1328, "text": "EARLY"}}, {"uri": "http://purl.org/sig/ont/fma/fma67238", "annotation": {"to": 1267, "matchType": "PREF", "from": 1260, "text": "DOPAMINE"}}, {"uri": "http://purl.obolibrary.org/obo/PATO_0001678", "annotation": {"to": 1418, "matchType": "PREF", "from": 1410, "text": "EFFICIENT"}}], "end": 1429, "struct": "DoCO:BodyMatter", "CoreSc": "Bac", "text": "", "start": 1254, "sid": "8", "page": "1"}, {"end": 1552, "struct": "DoCO:BodyMatter", "start": 1430, "text": "", "CoreSc": "Bac", "sid": "9", "page": "1"}, {"ncbo": [{"uri": "http://purl.obolibrary.org/obo/PATO_0000694", "annotation": {"to": 1565, "matchType": "SYN", "from": 1558, "text": "ADVANCED"}}], "end": 1570, "struct": "DoCO:BodyMatter", "CoreSc": "Bac", "text": "", "start": 1553, "sid": "10", "page": "1"}, {"ncbo": [{"uri": "http://purl.obolibrary.org/obo/PATO_0000456", "annotation": {"to": 1664, "matchType": "PREF", "from": 1657, "text": "ABSTRACT"}}, {"uri": "http://purl.obolibrary.org/obo/HP_0001300", "annotation": {"to": 1764, "matchType": "PREF", "from": 1753, "text": "PARKINSONISM"}}], "end": 1991, "struct": "DoCO:BodyMatter", "CoreSc": "Bac", "text": "", "marked": ["II"], "start": 1571, "sid": "11", "page": "1"}, {"end": 2189, "struct": "DoCO:BodyMatter", "start": 1992, "text": "", "CoreSc": "Bac", "sid": "12", "page": "1"}, {"end": 2207, "struct": "DoCO:BodyMatter", "start": 2190, "text": "", "CoreSc": "Bac", "sid": "13", "page": "1"}, {"end": 2213, "struct": "DoCO:BodyMatter", "start": 2208, "text": "", "CoreSc": "Bac", "sid": "14", "page": "1"}, {"ncbo": [{"uri": "http://purl.obolibrary.org/obo/HP_0100660", "annotation": {"to": 2329, "matchType": "SYN", "from": 2319, "text": "DYSKINESIAS"}}, {"uri": "http://purl.obolibrary.org/obo/PATO_0001309", "annotation": {"to": 2314, "matchType": "PREF", "from": 2307, "text": "DURATION"}}, {"uri": "http://purl.obolibrary.org/obo/PATO_0001309", "annotation": {"to": 2349, "matchType": "PREF", "from": 2342, "text": "DURATION"}}], "end": 2365, "struct": "DoCO:BodyMatter", "CoreSc": "Bac", "text": "", "start": 2214, "sid": "15", "page": "1"}, {"end": 2495, "struct": "DoCO:BodyMatter", "start": 2366, "text": "", "CoreSc": "Bac", "sid": "16", "page": "1"}, {"end": 2538, "struct": "DoCO:BodyMatter", "start": 2496, "text": "", "CoreSc": "Bac", "sid": "17", "page": "1"}, {"ncbo": [{"uri": "http://purl.obolibrary.org/obo/PATO_0000618", "annotation": {"to": 2607, "matchType": "PREF", "from": 2599, "text": "BILATERAL"}}, {"uri": "http://purl.obolibrary.org/obo/HP_0012832", "annotation": {"to": 2607, "matchType": "PREF", "from": 2599, "text": "BILATERAL"}}, {"uri": "http://purl.obolibrary.org/obo/GO_0005634", "annotation": {"to": 2921, "matchType": "PREF", "from": 2915, "text": "NUCLEUS"}}, {"uri": "http://purl.obolibrary.org/obo/PATO_0001596", "annotation": {"to": 2894, "matchType": "SYN", "from": 2891, "text": "DEEP"}}, {"uri": "http://purl.org/sig/ont/fma/fma50801", "annotation": {"to": 2900, "matchType": "PREF", "from": 2896, "text": "BRAIN"}}, {"uri": "http://purl.obolibrary.org/obo/PATO_0000694", "annotation": {"to": 2669, "matchType": "SYN", "from": 2662, "text": "ADVANCED"}}, {"uri": "http://purl.obolibrary.org/obo/HP_0100022", "annotation": {"to": 2768, "matchType": "SYN", "from": 2752, "text": "MOVEMENT DISORDER"}}], "end": 2935, "struct": "DoCO:BodyMatter", "CoreSc": "Bac", "text": "", "start": 2539, "sid": "18", "page": "1"}, {"ncbo": [{"uri": "http://purl.obolibrary.org/obo/HP_0100660", "annotation": {"to": 3018, "matchType": "SYN", "from": 3008, "text": "DYSKINESIAS"}}], "end": 3019, "struct": "DoCO:BodyMatter", "CoreSc": "Bac", "text": "", "start": 2936, "sid": "19", "page": "1"}, {"ncbo": [{"uri": "http://purl.obolibrary.org/obo/HP_0012828", "annotation": {"to": 3161, "matchType": "PREF", "from": 3156, "text": "SEVERE"}}, {"uri": "http://purl.obolibrary.org/obo/PATO_0001596", "annotation": {"to": 3054, "matchType": "SYN", "from": 3051, "text": "DEEP"}}, {"uri": "http://purl.org/sig/ont/fma/fma50801", "annotation": {"to": 3060, "matchType": "PREF", "from": 3056, "text": "BRAIN"}}], "end": 3184, "struct": "DoCO:BodyMatter", "CoreSc": "Bac", "text": "", "start": 3020, "sid": "20", "page": "1"}, {"ncbo": [{"uri": "http://purl.obolibrary.org/obo/PATO_0000694", "annotation": {"to": 3342, "matchType": "SYN", "from": 3335, "text": "ADVANCED"}}, {"uri": "http://purl.org/sig/ont/fma/fma74549", "annotation": {"to": 3236, "matchType": "PREF", "from": 3229, "text": "INTERNAL"}}, {"uri": "http://purl.org/sig/ont/fma/fma61835", "annotation": {"to": 3264, "matchType": "PREF", "from": 3250, "text": "GLOBUS PALLIDUS"}}], "end": 3346, "struct": "DoCO:BodyMatter", "CoreSc": "Bac", "text": "", "marked": ["globus pallidus (GPi)"], "start": 3185, "sid": "21", "page": "1"}, {"ncbo": [{"uri": "http://purl.obolibrary.org/obo/PATO_0001627", "annotation": {"to": 3558, "matchType": "PREF", "from": 3549, "text": "SUFFICIENT"}}], "end": 3620, "struct": "DoCO:BodyMatter", "CoreSc": "Bac", "text": "", "start": 3347, "sid": "22", "page": "1"}, {"end": 3697, "struct": "DoCO:BodyMatter", "start": 3621, "text": "", "CoreSc": "Bac", "sid": "23", "page": "1"}, {"ncbo": [{"uri": "http://purl.obolibrary.org/obo/PATO_0000618", "annotation": {"to": 3751, "matchType": "PREF", "from": 3743, "text": "BILATERAL"}}, {"uri": "http://purl.obolibrary.org/obo/PATO_0000618", "annotation": {"to": 3816, "matchType": "PREF", "from": 3808, "text": "BILATERAL"}}, {"uri": "http://purl.obolibrary.org/obo/HP_0012832", "annotation": {"to": 3751, "matchType": "PREF", "from": 3743, "text": "BILATERAL"}}, {"uri": "http://purl.obolibrary.org/obo/HP_0012832", "annotation": {"to": 3816, "matchType": "PREF", "from": 3808, "text": "BILATERAL"}}], "end": 3829, "struct": "DoCO:BodyMatter", "CoreSc": "Bac", "text": "", "start": 3698, "sid": "24", "page": "1"}, {"ncbo": [{"uri": "http://purl.org/sig/ont/fma/fma50801", "annotation": {"to": 3931, "matchType": "PREF", "from": 3927, "text": "BRAIN"}}, {"uri": "http://purl.obolibrary.org/obo/PATO_0001863", "annotation": {"to": 3883, "matchType": "PREF", "from": 3877, "text": "CHRONIC"}}, {"uri": "http://purl.obolibrary.org/obo/PATO_0000498", "annotation": {"to": 3883, "matchType": "SYN", "from": 3877, "text": "CHRONIC"}}, {"uri": "http://purl.obolibrary.org/obo/HP_0011010", "annotation": {"to": 3883, "matchType": "PREF", "from": 3877, "text": "CHRONIC"}}, {"uri": "http://purl.obolibrary.org/obo/PATO_0001020", "annotation": {"to": 3913, "matchType": "PREF", "from": 3908, "text": "DAMAGE"}}, {"uri": "http://purl.org/sig/ont/fma/fma9637", "annotation": {"to": 3938, "matchType": "SYN", "from": 3933, "text": "TISSUE"}}], "end": 3939, "struct": "DoCO:BodyMatter", "CoreSc": "Bac", "text": "", "start": 3830, "sid": "25", "page": "1"}, {"ncbo": [{"uri": "http://purl.obolibrary.org/obo/HP_0012828", "annotation": {"to": 4085, "matchType": "PREF", "from": 4080, "text": "SEVERE"}}, {"uri": "http://purl.obolibrary.org/obo/PATO_0000467", "annotation": {"to": 3958, "matchType": "PREF", "from": 3952, "text": "PRESENT"}}, {"uri": "http://purl.obolibrary.org/obo/PATO_0000694", "annotation": {"to": 4044, "matchType": "SYN", "from": 4037, "text": "ADVANCED"}}, {"uri": "http://purl.obolibrary.org/obo/GO_0043336", "annotation": {"to": 4090, "matchType": "SYN", "from": 4087, "text": "REST"}}, {"uri": "http://purl.obolibrary.org/obo/HP_0001337", "annotation": {"to": 4097, "matchType": "PREF", "from": 4092, "text": "TREMOR"}}, {"uri": "http://purl.obolibrary.org/obo/PATO_0000469", "annotation": {"to": 4131, "matchType": "PREF", "from": 4128, "text": "HIGH"}}, {"uri": "http://purl.obolibrary.org/obo/PATO_0000044", "annotation": {"to": 4141, "matchType": "PREF", "from": 4133, "text": "FREQUENCY"}}, {"uri": "http://purl.obolibrary.org/obo/PATO_0001504", "annotation": {"to": 4175, "matchType": "PREF", "from": 4169, "text": "COMPLEX"}}], "end": 4277, "struct": "DoCO:BodyMatter", "CoreSc": "Bac", "text": "", "start": 3940, "sid": "26", "page": "1"}, {"ncbo": [{"uri": "http://purl.org/sig/ont/fma/fma67238", "annotation": {"to": 4682, "matchType": "PREF", "from": 4675, "text": "DOPAMINE"}}, {"uri": "http://purl.org/sig/ont/fma/fma61835", "annotation": {"to": 4786, "matchType": "PREF", "from": 4772, "text": "GLOBUS PALLIDUS"}}, {"uri": "http://purl.obolibrary.org/obo/PATO_0001997", "annotation": {"to": 4477, "matchType": "SYN", "from": 4469, "text": "DECREASED"}}, {"uri": "http://purl.obolibrary.org/obo/PATO_0001997", "annotation": {"to": 4824, "matchType": "SYN", "from": 4816, "text": "DECREASED"}}, {"uri": "http://purl.obolibrary.org/obo/GO_0005793", "annotation": {"to": 4524, "matchType": "SYN", "from": 4520, "text": "ERGIC"}}, {"uri": "http://purl.org/sig/ont/fma/fma67947", "annotation": {"to": 4578, "matchType": "PREF", "from": 4563, "text": "SUBSTANTIA NIGRA"}}, {"uri": "http://purl.org/sig/ont/fma/fma67947", "annotation": {"to": 4669, "matchType": "PREF", "from": 4654, "text": "SUBSTANTIA NIGRA"}}, {"uri": "http://purl.obolibrary.org/obo/PATO_0000470", "annotation": {"to": 4624, "matchType": "SYN", "from": 4616, "text": "INCREASED"}}, {"uri": "http://purl.obolibrary.org/obo/PATO_0000470", "annotation": {"to": 4716, "matchType": "SYN", "from": 4708, "text": "INCREASED"}}, {"uri": "http://purl.org/sig/ont/fma/fma77618", "annotation": {"to": 4694, "matchType": "PREF", "from": 4687, "text": "STRIATUM"}}, {"uri": "http://purl.org/sig/ont/fma/fma74548", "annotation": {"to": 4762, "matchType": "PREF", "from": 4755, "text": "EXTERNAL"}}], "end": 4892, "struct": "DoCO:BodyMatter", "CoreSc": "Bac", "text": "", "start": 4278, "sid": "27", "page": "1"}, {"ncbo": [{"uri": "http://purl.obolibrary.org/obo/PATO_0000618", "annotation": {"to": 4950, "matchType": "PREF", "from": 4942, "text": "BILATERAL"}}, {"uri": "http://purl.obolibrary.org/obo/HP_0012832", "annotation": {"to": 4950, "matchType": "PREF", "from": 4942, "text": "BILATERAL"}}, {"uri": "http://purl.obolibrary.org/obo/PATO_0000467", "annotation": {"to": 4907, "matchType": "PREF", "from": 4901, "text": "PRESENT"}}, {"uri": "http://purl.obolibrary.org/obo/PATO_0000694", "annotation": {"to": 5006, "matchType": "SYN", "from": 4999, "text": "ADVANCED"}}], "end": 5165, "struct": "DoCO:BodyMatter", "CoreSc": "Bac", "text": "", "marked": ["the efficacy and side effects of bilateral DBS of the STN in 26 consecutive patients with advanced PD and motor complications", "bilateral DBS of the STN"], "start": 4893, "sid": "28", "page": "1"}, {"end": 5169, "struct": "DoCO:BodyMatter", "start": 5166, "text": "", "CoreSc": "Bac", "sid": "29", "page": "1"}, {"ncbo": [{"uri": "http://purl.obolibrary.org/obo/PATO_0000618", "annotation": {"to": 5241, "matchType": "PREF", "from": 5233, "text": "BILATERAL"}}, {"uri": "http://purl.obolibrary.org/obo/HP_0012832", "annotation": {"to": 5241, "matchType": "PREF", "from": 5233, "text": "BILATERAL"}}, {"uri": "http://purl.obolibrary.org/obo/HP_0100660", "annotation": {"to": 5394, "matchType": "SYN", "from": 5384, "text": "DYSKINESIAS"}}], "end": 5465, "struct": "deo:Methods", "CoreSc": "Bac", "text": "", "marked": ["33 parkinsonian patients"], "start": 5170, "sid": "30", "page": "2"}, {"ncbo": [{"uri": "http://purl.obolibrary.org/obo/PATO_0000011", "annotation": {"to": 5532, "matchType": "PREF", "from": 5530, "text": "AGE"}}, {"uri": "http://purl.org/sig/ont/fma/fma0328408", "annotation": {"to": 5532, "matchType": "PREF", "from": 5530, "text": "AGE"}}, {"uri": "http://purl.obolibrary.org/obo/PATO_0001309", "annotation": {"to": 5565, "matchType": "SYN", "from": 5562, "text": "TIME"}}, {"uri": "http://purl.obolibrary.org/obo/PATO_0001309", "annotation": {"to": 5593, "matchType": "PREF", "from": 5586, "text": "DURATION"}}, {"uri": "http://purl.obolibrary.org/obo/PATO_0000165", "annotation": {"to": 5565, "matchType": "PREF", "from": 5562, "text": "TIME"}}, {"uri": "http://purl.obolibrary.org/obo/PATO_0001990", "annotation": {"to": 5604, "matchType": "PREF", "from": 5586, "text": "DURATION OF DISEASE"}}], "end": 5648, "struct": "deo:Methods", "CoreSc": "Bac", "text": "", "marked": ["Twenty-six patients"], "start": 5466, "sid": "31", "page": "2"}, {"ncbo": [{"uri": "http://purl.obolibrary.org/obo/HP_0012828", "annotation": {"to": 5832, "matchType": "PREF", "from": 5827, "text": "SEVERE"}}, {"uri": "http://purl.obolibrary.org/obo/HP_0012828", "annotation": {"to": 5903, "matchType": "PREF", "from": 5898, "text": "SEVERE"}}, {"uri": "http://purl.obolibrary.org/obo/HP_0100660", "annotation": {"to": 5915, "matchType": "SYN", "from": 5905, "text": "DYSKINESIAS"}}, {"uri": "http://purl.obolibrary.org/obo/HP_0002304", "annotation": {"to": 5841, "matchType": "PREF", "from": 5834, "text": "AKINESIA"}}, {"uri": "http://purl.obolibrary.org/obo/HP_0004372", "annotation": {"to": 5867, "matchType": "SYN", "from": 5847, "text": "LOWERED CONSCIOUSNESS"}}], "end": 5916, "struct": "deo:Methods", "CoreSc": "Bac", "text": "", "marked": ["seven patients"], "start": 5649, "sid": "32", "page": "2"}, {"ncbo": [{"uri": "http://purl.obolibrary.org/obo/HP_0012828", "annotation": {"to": 5951, "matchType": "PREF", "from": 5946, "text": "SEVERE"}}, {"uri": "http://purl.obolibrary.org/obo/HP_0100660", "annotation": {"to": 5963, "matchType": "SYN", "from": 5953, "text": "DYSKINESIAS"}}, {"uri": "http://purl.obolibrary.org/obo/HP_0100660", "annotation": {"to": 6052, "matchType": "SYN", "from": 6042, "text": "DYSKINESIAS"}}], "end": 6100, "struct": "deo:Methods", "CoreSc": "Bac", "text": "", "start": 5917, "sid": "33", "page": "2"}, {"end": 6181, "struct": "deo:Methods", "start": 6101, "text": "", "CoreSc": "Bac", "sid": "34", "page": "2"}, {"ncbo": [{"uri": "http://purl.obolibrary.org/obo/PATO_0000011", "annotation": {"to": 6219, "matchType": "PREF", "from": 6217, "text": "AGE"}}, {"uri": "http://purl.obolibrary.org/obo/PATO_0000011", "annotation": {"to": 6267, "matchType": "PREF", "from": 6265, "text": "AGE"}}, {"uri": "http://purl.org/sig/ont/fma/fma0328408", "annotation": {"to": 6219, "matchType": "PREF", "from": 6217, "text": "AGE"}}, {"uri": "http://purl.org/sig/ont/fma/fma0328408", "annotation": {"to": 6267, "matchType": "PREF", "from": 6265, "text": "AGE"}}, {"uri": "http://purl.obolibrary.org/obo/HP_0001337", "annotation": {"to": 6256, "matchType": "PREF", "from": 6251, "text": "TREMOR"}}, {"uri": "http://purl.obolibrary.org/obo/HP_0001337", "annotation": {"to": 6294, "matchType": "PREF", "from": 6289, "text": "TREMOR"}}, {"uri": "http://purl.obolibrary.org/obo/HP_0030186", "annotation": {"to": 6256, "matchType": "SYN", "from": 6241, "text": "ESSENTIAL TREMOR"}}], "end": 6320, "struct": "deo:Methods", "CoreSc": "Met", "text": "", "start": 6182, "sid": "35", "page": "2"}, {"ncbo": [{"uri": "http://purl.obolibrary.org/obo/HP_0100660", "annotation": {"to": 6365, "matchType": "SYN", "from": 6355, "text": "DYSKINESIAS"}}], "end": 6366, "struct": "deo:Methods", "CoreSc": "Met", "text": "", "start": 6321, "sid": "36", "page": "2"}, {"ncbo": [{"uri": "http://purl.obolibrary.org/obo/PATO_0000438", "annotation": {"to": 6491, "matchType": "SYN", "from": 6484, "text": "CONSTANT"}}], "end": 6513, "struct": "deo:Methods", "CoreSc": "Met", "text": "", "start": 6367, "sid": "37", "page": "2"}, {"ncbo": [{"uri": "http://purl.obolibrary.org/obo/HP_0100660", "annotation": {"to": 6603, "matchType": "SYN", "from": 6593, "text": "DYSKINESIAS"}}, {"uri": "http://purl.obolibrary.org/obo/PATO_0001309", "annotation": {"to": 6588, "matchType": "PREF", "from": 6581, "text": "DURATION"}}, {"uri": "http://purl.obolibrary.org/obo/PATO_0000224", "annotation": {"to": 6573, "matchType": "PREF", "from": 6560, "text": "MOTOR FUNCTION"}}, {"uri": "http://purl.obolibrary.org/obo/PATO_0000173", "annotation": {"to": 6573, "matchType": "PREF", "from": 6566, "text": "FUNCTION"}}], "end": 6702, "struct": "deo:Methods", "CoreSc": "Met", "text": "", "start": 6514, "sid": "38", "page": "2"}, {"ncbo": [{"uri": "http://purl.obolibrary.org/obo/PATO_0000487", "annotation": {"to": 6780, "matchType": "SYN", "from": 6771, "text": "RESPONSIVE"}}, {"uri": "http://purl.obolibrary.org/obo/HP_0100660", "annotation": {"to": 6870, "matchType": "SYN", "from": 6860, "text": "DYSKINESIAS"}}, {"uri": "http://purl.obolibrary.org/obo/PATO_0000011", "annotation": {"to": 6751, "matchType": "PREF", "from": 6749, "text": "AGE"}}, {"uri": "http://purl.org/sig/ont/fma/fma0328408", "annotation": {"to": 6751, "matchType": "PREF", "from": 6749, "text": "AGE"}}], "end": 6881, "struct": "deo:Methods", "CoreSc": "Met", "text": "", "marked": ["levodopa-responsive idiopathic PD"], "start": 6703, "sid": "39", "page": "2"}, {"ncbo": [{"uri": "http://purl.obolibrary.org/obo/PATO_0000438", "annotation": {"to": 6918, "matchType": "SYN", "from": 6911, "text": "CONSTANT"}}], "end": 7161, "struct": "deo:Methods", "CoreSc": "Met", "text": "", "marked": ["part III", "Hoehn and Yahr staging", "Unified Parkinson\u2019s Disease Rating Scale part III (UPDRS, motor examination"], "start": 6882, "sid": "40", "page": "2"}, {"ncbo": [{"uri": "http://purl.obolibrary.org/obo/PATO_0002107", "annotation": {"to": 7223, "matchType": "PREF", "from": 7214, "text": "PERIPHERAL"}}, {"uri": "http://purl.obolibrary.org/obo/HP_0030646", "annotation": {"to": 7223, "matchType": "PREF", "from": 7214, "text": "PERIPHERAL"}}], "end": 7248, "struct": "deo:Methods", "CoreSc": "Met", "text": "", "start": 7162, "sid": "41", "page": "2"}, {"ncbo": [{"uri": "http://purl.org/sig/ont/fma/fma67238", "annotation": {"to": 7287, "matchType": "PREF", "from": 7280, "text": "DOPAMINE"}}, {"uri": "http://purl.obolibrary.org/obo/PATO_0002438", "annotation": {"to": 7319, "matchType": "SYN", "from": 7308, "text": "SUBCUTANEOUS"}}], "end": 7332, "struct": "deo:Methods", "CoreSc": "Met", "text": "", "start": 7249, "sid": "42", "page": "2"}, {"ncbo": [{"uri": "http://purl.obolibrary.org/obo/PATO_0001685", "annotation": {"to": 7355, "matchType": "PREF", "from": 7348, "text": "MAGNETIC"}}, {"uri": "http://purl.obolibrary.org/obo/PATO_0000461", "annotation": {"to": 7390, "matchType": "PREF", "from": 7385, "text": "NORMAL"}}], "end": 7391, "struct": "deo:Methods", "CoreSc": "Met", "text": "", "start": 7333, "sid": "43", "page": "2"}, {"ncbo": [{"uri": "http://purl.obolibrary.org/obo/HP_0000726", "annotation": {"to": 7438, "matchType": "PREF", "from": 7431, "text": "DEMENTIA"}}, {"uri": "http://purl.obolibrary.org/obo/HP_0000716", "annotation": {"to": 7450, "matchType": "PREF", "from": 7441, "text": "DEPRESSION"}}], "end": 7487, "struct": "deo:Methods", "CoreSc": "Met", "text": "", "start": 7392, "sid": "44", "page": "2"}, {"end": 7580, "struct": "deo:Methods", "start": 7488, "text": "", "CoreSc": "Met", "sid": "45", "page": "2"}, {"ncbo": [{"uri": "http://purl.obolibrary.org/obo/GO_0005634", "annotation": {"to": 7770, "matchType": "PREF", "from": 7764, "text": "NUCLEUS"}}, {"uri": "http://purl.obolibrary.org/obo/HP_0012828", "annotation": {"to": 7794, "matchType": "PREF", "from": 7789, "text": "SEVERE"}}, {"uri": "http://purl.obolibrary.org/obo/HP_0001337", "annotation": {"to": 7801, "matchType": "PREF", "from": 7796, "text": "TREMOR"}}, {"uri": "http://purl.obolibrary.org/obo/PATO_0000634", "annotation": {"to": 7618, "matchType": "PREF", "from": 7609, "text": "UNILATERAL"}}, {"uri": "http://purl.obolibrary.org/obo/PATO_0000634", "annotation": {"to": 7700, "matchType": "PREF", "from": 7691, "text": "UNILATERAL"}}, {"uri": "http://purl.obolibrary.org/obo/HP_0012833", "annotation": {"to": 7618, "matchType": "PREF", "from": 7609, "text": "UNILATERAL"}}, {"uri": "http://purl.obolibrary.org/obo/HP_0012833", "annotation": {"to": 7700, "matchType": "PREF", "from": 7691, "text": "UNILATERAL"}}, {"uri": "http://purl.org/sig/ont/fma/fma256693", "annotation": {"to": 7770, "matchType": "SYN", "from": 7755, "text": "THALAMIC NUCLEUS"}}], "end": 7802, "struct": "deo:Methods", "CoreSc": "Met", "text": "", "start": 7581, "sid": "46", "page": "2"}, {"ncbo": [{"uri": "http://purl.obolibrary.org/obo/GO_0005634", "annotation": {"to": 7843, "matchType": "PREF", "from": 7837, "text": "NUCLEUS"}}], "end": 7871, "struct": "deo:Methods", "CoreSc": "Met", "text": "", "start": 7803, "sid": "47", "page": "2"}, {"end": 7986, "struct": "deo:Methods", "start": 7872, "text": "", "CoreSc": "Met", "sid": "48", "page": "2"}, {"ncbo": [{"uri": "http://purl.obolibrary.org/obo/PATO_0000618", "annotation": {"to": 8039, "matchType": "PREF", "from": 8031, "text": "BILATERAL"}}, {"uri": "http://purl.obolibrary.org/obo/HP_0012832", "annotation": {"to": 8039, "matchType": "PREF", "from": 8031, "text": "BILATERAL"}}, {"uri": "http://purl.obolibrary.org/obo/GO_0019013", "annotation": {"to": 8082, "matchType": "SYN", "from": 8079, "text": "CORE"}}], "end": 8175, "struct": "deo:Methods", "CoreSc": "Met", "text": "", "start": 7987, "sid": "49", "page": "2"}, {"end": 8330, "struct": "deo:Methods", "start": 8176, "text": "", "marked": ["Evaluation was, however, performed only once 1 month before surgery and at 1, 3, 6, and 12 months after surgery"], "CoreSc": "Met", "sid": "50", "page": "2"}, {"ncbo": [{"uri": "http://purl.obolibrary.org/obo/HP_0100660", "annotation": {"to": 8597, "matchType": "SYN", "from": 8587, "text": "DYSKINESIAS"}}, {"uri": "http://purl.obolibrary.org/obo/PATO_0001309", "annotation": {"to": 8438, "matchType": "SYN", "from": 8435, "text": "TIME"}}, {"uri": "http://purl.obolibrary.org/obo/PATO_0000165", "annotation": {"to": 8438, "matchType": "PREF", "from": 8435, "text": "TIME"}}, {"uri": "http://purl.obolibrary.org/obo/PATO_0001555", "annotation": {"to": 8470, "matchType": "SYN", "from": 8462, "text": "NUMBER OF"}}, {"uri": "http://purl.obolibrary.org/obo/PATO_0001555", "annotation": {"to": 8467, "matchType": "SYN", "from": 8462, "text": "NUMBER"}}, {"uri": "http://purl.obolibrary.org/obo/PATO_0001056", "annotation": {"to": 8467, "matchType": "PREF", "from": 8462, "text": "NUMBER"}}, {"uri": "http://purl.obolibrary.org/obo/PATO_0000070", "annotation": {"to": 8467, "matchType": "SYN", "from": 8462, "text": "NUMBER"}}, {"uri": "http://purl.org/sig/ont/fma/fma11343", "annotation": {"to": 8500, "matchType": "PREF", "from": 8491, "text": "RIGHT FOOT"}}, {"uri": "http://purl.obolibrary.org/obo/PATO_0000367", "annotation": {"to": 8495, "matchType": "PREF", "from": 8491, "text": "RIGHT"}}, {"uri": "http://purl.obolibrary.org/obo/HP_0012834", "annotation": {"to": 8495, "matchType": "PREF", "from": 8491, "text": "RIGHT"}}, {"uri": "http://purl.org/sig/ont/fma/fma9664", "annotation": {"to": 8500, "matchType": "PREF", "from": 8497, "text": "FOOT"}}, {"uri": "http://purl.org/sig/ont/fma/fma0328527", "annotation": {"to": 8520, "matchType": "PREF", "from": 8517, "text": "TEST"}}], "end": 8598, "struct": "deo:Methods", "CoreSc": "Met", "text": "", "marked": ["UPDRS part I, II, III, IV, V, and VI"], "start": 8331, "sid": "51", "page": "2"}, {"end": 8993, "struct": "deo:Methods", "start": 8599, "text": "", "CoreSc": "Met", "sid": "52", "page": "2"}, {"end": 9064, "struct": "deo:Methods", "start": 8994, "text": "", "CoreSc": "Met", "sid": "53", "page": "2"}, {"end": 9132, "struct": "deo:Methods", "start": 9065, "text": "", "CoreSc": "Met", "sid": "54", "page": "2"}, {"end": 9327, "struct": "deo:Methods", "start": 9133, "text": "", "CoreSc": "Met", "sid": "55", "page": "2"}, {"end": 9421, "struct": "deo:Methods", "start": 9328, "text": "", "CoreSc": "Met", "sid": "56", "page": "2"}, {"end": 9565, "struct": "deo:Methods", "start": 9422, "text": "", "CoreSc": "Met", "sid": "57", "page": "3"}, {"ncbo": [{"uri": "http://purl.obolibrary.org/obo/PATO_0001685", "annotation": {"to": 9698, "matchType": "PREF", "from": 9691, "text": "MAGNETIC"}}, {"uri": "http://purl.obolibrary.org/obo/PATO_0001667", "annotation": {"to": 9660, "matchType": "PREF", "from": 9650, "text": "ATTACHED TO"}}, {"uri": "http://purl.obolibrary.org/obo/PATO_0001667", "annotation": {"to": 9657, "matchType": "SYN", "from": 9650, "text": "ATTACHED"}}, {"uri": "http://purl.org/sig/ont/fma/fma46565", "annotation": {"to": 9670, "matchType": "PREF", "from": 9666, "text": "SKULL"}}], "end": 9755, "struct": "deo:Methods", "CoreSc": "Met", "text": "", "start": 9566, "sid": "58", "page": "3"}, {"end": 9925, "struct": "deo:Methods", "start": 9756, "text": "", "CoreSc": "Met", "sid": "59", "page": "3"}, {"ncbo": [{"uri": "http://purl.org/sig/ont/fma/fma74530", "annotation": {"to": 9942, "matchType": "PREF", "from": 9935, "text": "SAGITTAL"}}, {"uri": "http://purl.obolibrary.org/obo/PATO_0000627", "annotation": {"to": 9985, "matchType": "PREF", "from": 9977, "text": "LOCALIZED"}}, {"uri": "http://purl.obolibrary.org/obo/HP_0012838", "annotation": {"to": 9985, "matchType": "PREF", "from": 9977, "text": "LOCALIZED"}}, {"uri": "http://purl.obolibrary.org/obo/PATO_0001193", "annotation": {"to": 10013, "matchType": "SYN", "from": 10007, "text": "LATERAL"}}, {"uri": "http://purl.org/sig/ont/fma/fma74544", "annotation": {"to": 10045, "matchType": "PREF", "from": 10040, "text": "MIDDLE"}}, {"uri": "http://purl.org/sig/ont/fma/fma62072", "annotation": {"to": 10092, "matchType": "PREF", "from": 10073, "text": "POSTERIOR COMMISSURE"}}, {"uri": "http://purl.org/sig/ont/fma/fma76741", "annotation": {"to": 10092, "matchType": "PREF", "from": 10083, "text": "COMMISSURE"}}], "end": 10106, "struct": "deo:Methods", "CoreSc": "Met", "text": "", "start": 9926, "sid": "60", "page": "3"}, {"ncbo": [{"uri": "http://purl.obolibrary.org/obo/GO_0051179", "annotation": {"to": 10124, "matchType": "PREF", "from": 10113, "text": "LOCALIZATION"}}], "end": 10202, "struct": "deo:Methods", "CoreSc": "Met", "text": "", "start": 10107, "sid": "61", "page": "3"}, {"end": 10269, "struct": "deo:Methods", "start": 10203, "text": "", "CoreSc": "Met", "sid": "62", "page": "3"}, {"ncbo": [{"uri": "http://purl.obolibrary.org/obo/PATO_0000140", "annotation": {"to": 10329, "matchType": "SYN", "from": 10321, "text": "PLACEMENT"}}, {"uri": "http://purl.org/sig/ont/fma/fma74536", "annotation": {"to": 10415, "matchType": "PREF", "from": 10409, "text": "FRONTAL"}}], "end": 10427, "struct": "deo:Methods", "CoreSc": "Met", "text": "", "start": 10270, "sid": "63", "page": "3"}, {"end": 10503, "struct": "deo:Methods", "start": 10428, "text": "", "CoreSc": "Met", "sid": "64", "page": "3"}, {"ncbo": [{"uri": "http://purl.obolibrary.org/obo/HP_0001337", "annotation": {"to": 10631, "matchType": "PREF", "from": 10626, "text": "TREMOR"}}, {"uri": "http://purl.obolibrary.org/obo/HP_0002304", "annotation": {"to": 10623, "matchType": "PREF", "from": 10616, "text": "AKINESIA"}}, {"uri": "http://purl.org/sig/ont/fma/fma0328527", "annotation": {"to": 10531, "matchType": "PREF", "from": 10528, "text": "TEST"}}, {"uri": "http://purl.obolibrary.org/obo/HP_0002063", "annotation": {"to": 10613, "matchType": "PREF", "from": 10606, "text": "RIGIDITY"}}], "end": 10653, "struct": "deo:Methods", "CoreSc": "Met", "text": "", "start": 10504, "sid": "65", "page": "3"}, {"ncbo": [{"uri": "http://purl.org/sig/ont/fma/fma50801", "annotation": {"to": 10767, "matchType": "PREF", "from": 10763, "text": "BRAIN"}}], "end": 10780, "struct": "deo:Methods", "CoreSc": "Met", "text": "", "start": 10654, "sid": "66", "page": "3"}, {"ncbo": [{"uri": "http://purl.org/sig/ont/fma/fma76739", "annotation": {"to": 10886, "matchType": "PREF", "from": 10882, "text": "TRACT"}}], "end": 10922, "struct": "deo:Methods", "CoreSc": "Met", "text": "", "start": 10781, "sid": "67", "page": "3"}, {"ncbo": [{"uri": "http://purl.obolibrary.org/obo/GO_0051179", "annotation": {"to": 10956, "matchType": "PREF", "from": 10945, "text": "LOCALIZATION"}}], "end": 11048, "struct": "deo:Methods", "CoreSc": "Met", "text": "", "start": 10923, "sid": "68", "page": "3"}, {"ncbo": [{"uri": "http://purl.org/sig/ont/fma/fma74549", "annotation": {"to": 11132, "matchType": "PREF", "from": 11125, "text": "INTERNAL"}}, {"uri": "http://purl.org/sig/ont/fma/fma13321", "annotation": {"to": 11243, "matchType": "PREF", "from": 11236, "text": "CLAVICLE"}}], "end": 11244, "struct": "deo:Methods", "CoreSc": "Met", "text": "", "start": 11049, "sid": "69", "page": "3"}, {"ncbo": [{"uri": "http://purl.obolibrary.org/obo/PATO_0002438", "annotation": {"to": 11368, "matchType": "SYN", "from": 11357, "text": "SUBCUTANEOUS"}}], "end": 11406, "struct": "deo:Methods", "CoreSc": "Met", "text": "", "start": 11245, "sid": "70", "page": "3"}, {"ncbo": [{"uri": "http://purl.obolibrary.org/obo/PATO_0001309", "annotation": {"to": 11447, "matchType": "SYN", "from": 11444, "text": "TIME"}}, {"uri": "http://purl.obolibrary.org/obo/PATO_0000165", "annotation": {"to": 11447, "matchType": "PREF", "from": 11444, "text": "TIME"}}], "end": 11462, "struct": "deo:Methods", "CoreSc": "Met", "text": "", "start": 11407, "sid": "71", "page": "3"}, {"end": 11641, "struct": "deo:Methods", "start": 11463, "text": "", "CoreSc": "Met", "sid": "72", "page": "3"}, {"end": 11708, "struct": "deo:Methods", "start": 11642, "text": "", "CoreSc": "Met", "sid": "73", "page": "3"}, {"ncbo": [{"uri": "http://purl.obolibrary.org/obo/PATO_0001470", "annotation": {"to": 11779, "matchType": "SYN", "from": 11776, "text": "RATE"}}, {"uri": "http://purl.obolibrary.org/obo/PATO_0000161", "annotation": {"to": 11779, "matchType": "PREF", "from": 11776, "text": "RATE"}}, {"uri": "http://purl.obolibrary.org/obo/PATO_0000921", "annotation": {"to": 11801, "matchType": "PREF", "from": 11797, "text": "WIDTH"}}], "end": 11809, "struct": "deo:Methods", "CoreSc": "Met", "text": "", "start": 11709, "sid": "74", "page": "3"}, {"end": 11957, "struct": "deo:Methods", "start": 11810, "text": "", "CoreSc": "Met", "sid": "75", "page": "3"}, {"ncbo": [{"uri": "http://purl.obolibrary.org/obo/PATO_0001997", "annotation": {"to": 12031, "matchType": "SYN", "from": 12025, "text": "REDUCED"}}, {"uri": "http://purl.obolibrary.org/obo/PATO_0000470", "annotation": {"to": 11991, "matchType": "SYN", "from": 11983, "text": "INCREASED"}}], "end": 12032, "struct": "deo:Methods", "CoreSc": "Met", "text": "", "start": 11958, "sid": "76", "page": "3"}, {"end": 12133, "struct": "deo:Methods", "start": 12033, "text": "", "CoreSc": "Met", "sid": "77", "page": "3"}, {"ncbo": [{"uri": "http://purl.obolibrary.org/obo/HP_0100660", "annotation": {"to": 12309, "matchType": "SYN", "from": 12299, "text": "DYSKINESIAS"}}, {"uri": "http://purl.obolibrary.org/obo/PATO_0001309", "annotation": {"to": 12294, "matchType": "PREF", "from": 12287, "text": "DURATION"}}], "end": 12327, "struct": "deo:Methods", "CoreSc": "Met", "text": "", "marked": ["parts II", "and IV"], "start": 12134, "sid": "78", "page": "3"}, {"ncbo": [{"uri": "http://purl.obolibrary.org/obo/PATO_0001309", "annotation": {"to": 12517, "matchType": "SYN", "from": 12514, "text": "TIME"}}, {"uri": "http://purl.obolibrary.org/obo/HP_0001337", "annotation": {"to": 12406, "matchType": "PREF", "from": 12401, "text": "TREMOR"}}, {"uri": "http://purl.obolibrary.org/obo/PATO_0000165", "annotation": {"to": 12517, "matchType": "PREF", "from": 12514, "text": "TIME"}}, {"uri": "http://purl.obolibrary.org/obo/HP_0002304", "annotation": {"to": 12398, "matchType": "PREF", "from": 12391, "text": "AKINESIA"}}, {"uri": "http://purl.obolibrary.org/obo/PATO_0001555", "annotation": {"to": 12550, "matchType": "SYN", "from": 12542, "text": "NUMBER OF"}}, {"uri": "http://purl.obolibrary.org/obo/PATO_0001555", "annotation": {"to": 12547, "matchType": "SYN", "from": 12542, "text": "NUMBER"}}, {"uri": "http://purl.obolibrary.org/obo/PATO_0001056", "annotation": {"to": 12547, "matchType": "PREF", "from": 12542, "text": "NUMBER"}}, {"uri": "http://purl.obolibrary.org/obo/PATO_0000070", "annotation": {"to": 12547, "matchType": "SYN", "from": 12542, "text": "NUMBER"}}, {"uri": "http://purl.org/sig/ont/fma/fma11343", "annotation": {"to": 12580, "matchType": "PREF", "from": 12571, "text": "RIGHT FOOT"}}, {"uri": "http://purl.obolibrary.org/obo/PATO_0000367", "annotation": {"to": 12575, "matchType": "PREF", "from": 12571, "text": "RIGHT"}}, {"uri": "http://purl.obolibrary.org/obo/HP_0012834", "annotation": {"to": 12575, "matchType": "PREF", "from": 12571, "text": "RIGHT"}}, {"uri": "http://purl.org/sig/ont/fma/fma9664", "annotation": {"to": 12580, "matchType": "PREF", "from": 12577, "text": "FOOT"}}, {"uri": "http://purl.org/sig/ont/fma/fma0328527", "annotation": {"to": 12600, "matchType": "PREF", "from": 12597, "text": "TEST"}}, {"uri": "http://purl.org/sig/ont/fma/fma0328527", "annotation": {"to": 12632, "matchType": "PREF", "from": 12629, "text": "TEST"}}, {"uri": "http://purl.obolibrary.org/obo/HP_0002063", "annotation": {"to": 12388, "matchType": "PREF", "from": 12381, "text": "RIGIDITY"}}, {"uri": "http://purl.obolibrary.org/obo/PATO_0002532", "annotation": {"to": 12342, "matchType": "PREF", "from": 12334, "text": "SECONDARY"}}, {"uri": "http://purl.obolibrary.org/obo/PATO_0000190", "annotation": {"to": 12412, "matchType": "PREF", "from": 12409, "text": "GAIT"}}], "end": 12633, "struct": "deo:Methods", "CoreSc": "Met", "text": "", "marked": ["Hoehn and Yahr staging, Schwab and England ADL, timed tests including time to walk 4.5 m,"], "start": 12328, "sid": "79", "page": "3"}, {"ncbo": [{"uri": "http://purl.obolibrary.org/obo/PATO_0001309", "annotation": {"to": 12783, "matchType": "SYN", "from": 12780, "text": "TIME"}}, {"uri": "http://purl.obolibrary.org/obo/PATO_0000165", "annotation": {"to": 12783, "matchType": "PREF", "from": 12780, "text": "TIME"}}], "end": 12784, "struct": "deo:Methods", "CoreSc": "Met", "text": "", "start": 12634, "sid": "80", "page": "3"}, {"ncbo": [{"uri": "http://purl.org/sig/ont/fma/fma0328527", "annotation": {"to": 12817, "matchType": "PREF", "from": 12814, "text": "TEST"}}], "end": 12945, "struct": "deo:Methods", "CoreSc": "Met", "text": "", "start": 12785, "sid": "81", "page": "3"}, {"ncbo": [{"uri": "http://purl.obolibrary.org/obo/HP_0100660", "annotation": {"to": 12969, "matchType": "SYN", "from": 12959, "text": "DYSKINESIAS"}}, {"uri": "http://purl.org/sig/ont/fma/fma0328527", "annotation": {"to": 13024, "matchType": "PREF", "from": 13021, "text": "TEST"}}], "end": 13034, "struct": "deo:Methods", "CoreSc": "Met", "text": "", "start": 12946, "sid": "82", "page": "3"}, {"ncbo": [{"uri": "http://purl.obolibrary.org/obo/PATO_0000002", "annotation": {"to": 13070, "matchType": "PREF", "from": 13066, "text": "VALUE"}}], "end": 13121, "struct": "deo:Methods", "CoreSc": "Met", "text": "", "start": 13035, "sid": "83", "page": "3"}, {"end": 13210, "struct": "deo:Results", "start": 13122, "text": "", "CoreSc": "Met", "sid": "84", "page": "3"}, {"ncbo": [{"uri": "http://purl.obolibrary.org/obo/HP_0100660", "annotation": {"to": 13238, "matchType": "SYN", "from": 13228, "text": "DYSKINESIAS"}}, {"uri": "http://purl.obolibrary.org/obo/PATO_0001309", "annotation": {"to": 13223, "matchType": "PREF", "from": 13216, "text": "DURATION"}}, {"uri": "http://purl.obolibrary.org/obo/PATO_0001997", "annotation": {"to": 13334, "matchType": "SYN", "from": 13328, "text": "REDUCED"}}], "end": 13460, "struct": "deo:Results", "CoreSc": "Met", "text": "", "marked": ["The duration of dyskinesias (improvement of 86%) and off-periods (improvement of 83%) were highly and significantly reduced, meaning that the patients motor condition when on medication and on stimulation was stabilized throughout the day"], "start": 13211, "sid": "85", "page": "3"}, {"end": 13577, "struct": "deo:Results", "start": 13461, "text": "", "CoreSc": "Met", "sid": "86", "page": "3"}, {"end": 13654, "struct": "deo:Results", "start": 13578, "text": "", "CoreSc": "Met", "sid": "87", "page": "3"}, {"ncbo": [{"uri": "http://purl.obolibrary.org/obo/PATO_0000224", "annotation": {"to": 13708, "matchType": "PREF", "from": 13695, "text": "MOTOR FUNCTION"}}, {"uri": "http://purl.obolibrary.org/obo/PATO_0000173", "annotation": {"to": 13708, "matchType": "PREF", "from": 13701, "text": "FUNCTION"}}], "end": 13877, "struct": "deo:Results", "CoreSc": "Met", "text": "", "start": 13655, "sid": "88", "page": "3"}, {"end": 13981, "struct": "deo:Results", "start": 13878, "text": "", "CoreSc": "Met", "sid": "89", "page": "3"}, {"end": 14098, "struct": "deo:Results", "start": 13982, "text": "", "CoreSc": "Met", "sid": "90", "page": "3"}, {"ncbo": [{"uri": "http://purl.obolibrary.org/obo/HP_0100660", "annotation": {"to": 14119, "matchType": "SYN", "from": 14109, "text": "DYSKINESIAS"}}, {"uri": "http://purl.obolibrary.org/obo/HP_0100660", "annotation": {"to": 14549, "matchType": "SYN", "from": 14539, "text": "DYSKINESIAS"}}, {"uri": "http://purl.obolibrary.org/obo/PATO_0000002", "annotation": {"to": 14444, "matchType": "PREF", "from": 14440, "text": "VALUE"}}], "end": 14899, "struct": "DoCO:TableBox", "CoreSc": "Met", "text": "", "start": 14099, "sid": "91"}, {"ncbo": [{"uri": "http://purl.obolibrary.org/obo/HP_0001337", "annotation": {"to": 15014, "matchType": "PREF", "from": 15009, "text": "TREMOR"}}, {"uri": "http://purl.obolibrary.org/obo/HP_0002304", "annotation": {"to": 15006, "matchType": "PREF", "from": 14999, "text": "AKINESIA"}}, {"uri": "http://purl.obolibrary.org/obo/HP_0002063", "annotation": {"to": 14996, "matchType": "PREF", "from": 14989, "text": "RIGIDITY"}}, {"uri": "http://purl.obolibrary.org/obo/PATO_0000190", "annotation": {"to": 15020, "matchType": "PREF", "from": 15017, "text": "GAIT"}}, {"uri": "http://purl.obolibrary.org/obo/PATO_0000573", "annotation": {"to": 14933, "matchType": "SYN", "from": 14930, "text": "LONG"}}], "end": 15156, "struct": "deo:Results", "CoreSc": "Met", "text": "", "start": 14900, "sid": "92", "page": "4"}, {"ncbo": [{"uri": "http://purl.obolibrary.org/obo/HP_0002304", "annotation": {"to": 15222, "matchType": "PREF", "from": 15215, "text": "AKINESIA"}}, {"uri": "http://purl.obolibrary.org/obo/PATO_0000190", "annotation": {"to": 15231, "matchType": "PREF", "from": 15228, "text": "GAIT"}}], "end": 15242, "struct": "deo:Results", "CoreSc": "Met", "text": "", "start": 15157, "sid": "93", "page": "4"}, {"ncbo": [{"uri": "http://purl.obolibrary.org/obo/PATO_0000224", "annotation": {"to": 15390, "matchType": "PREF", "from": 15377, "text": "MOTOR FUNCTION"}}, {"uri": "http://purl.obolibrary.org/obo/PATO_0000173", "annotation": {"to": 15390, "matchType": "PREF", "from": 15383, "text": "FUNCTION"}}], "end": 15416, "struct": "deo:Results", "CoreSc": "Met", "text": "", "start": 15243, "sid": "94", "page": "4"}, {"ncbo": [{"uri": "http://purl.obolibrary.org/obo/HP_0002304", "annotation": {"to": 15521, "matchType": "PREF", "from": 15514, "text": "AKINESIA"}}, {"uri": "http://purl.obolibrary.org/obo/HP_0002063", "annotation": {"to": 15511, "matchType": "PREF", "from": 15504, "text": "RIGIDITY"}}], "end": 15556, "struct": "deo:Results", "CoreSc": "Met", "text": "", "start": 15417, "sid": "95", "page": "4"}, {"ncbo": [{"uri": "http://purl.obolibrary.org/obo/PATO_0001309", "annotation": {"to": 15561, "matchType": "SYN", "from": 15558, "text": "TIME"}}, {"uri": "http://purl.obolibrary.org/obo/PATO_0000165", "annotation": {"to": 15561, "matchType": "PREF", "from": 15558, "text": "TIME"}}, {"uri": "http://purl.obolibrary.org/obo/PATO_0001555", "annotation": {"to": 15575, "matchType": "SYN", "from": 15567, "text": "NUMBER OF"}}, {"uri": "http://purl.obolibrary.org/obo/PATO_0001555", "annotation": {"to": 15572, "matchType": "SYN", "from": 15567, "text": "NUMBER"}}, {"uri": "http://purl.obolibrary.org/obo/PATO_0001056", "annotation": {"to": 15572, "matchType": "PREF", "from": 15567, "text": "NUMBER"}}, {"uri": "http://purl.obolibrary.org/obo/PATO_0000070", "annotation": {"to": 15572, "matchType": "SYN", "from": 15567, "text": "NUMBER"}}], "end": 15667, "struct": "deo:Results", "CoreSc": "Met", "text": "", "start": 15557, "sid": "96", "page": "4"}, {"ncbo": [{"uri": "http://purl.obolibrary.org/obo/PATO_0001555", "annotation": {"to": 15678, "matchType": "SYN", "from": 15670, "text": "NUMBER OF"}}, {"uri": "http://purl.obolibrary.org/obo/PATO_0001555", "annotation": {"to": 15675, "matchType": "SYN", "from": 15670, "text": "NUMBER"}}, {"uri": "http://purl.obolibrary.org/obo/PATO_0001056", "annotation": {"to": 15675, "matchType": "PREF", "from": 15670, "text": "NUMBER"}}, {"uri": "http://purl.obolibrary.org/obo/PATO_0000070", "annotation": {"to": 15675, "matchType": "SYN", "from": 15670, "text": "NUMBER"}}, {"uri": "http://purl.org/sig/ont/fma/fma9666", "annotation": {"to": 15685, "matchType": "PREF", "from": 15680, "text": "FINGER"}}], "end": 15770, "struct": "deo:Results", "CoreSc": "Met", "text": "", "start": 15668, "sid": "97", "page": "4"}, {"ncbo": [{"uri": "http://purl.obolibrary.org/obo/PATO_0000618", "annotation": {"to": 15843, "matchType": "PREF", "from": 15835, "text": "BILATERAL"}}, {"uri": "http://purl.obolibrary.org/obo/HP_0012832", "annotation": {"to": 15843, "matchType": "PREF", "from": 15835, "text": "BILATERAL"}}, {"uri": "http://purl.org/sig/ont/fma/fma62035", "annotation": {"to": 22107, "matchType": "PREF", "from": 22089, "text": "SUBTHALAMIC NUCLEUS"}}, {"uri": "http://purl.obolibrary.org/obo/GO_0005634", "annotation": {"to": 20276, "matchType": "PREF", "from": 20270, "text": "NUCLEUS"}}, {"uri": "http://purl.obolibrary.org/obo/GO_0005634", "annotation": {"to": 22107, "matchType": "PREF", "from": 22101, "text": "NUCLEUS"}}, {"uri": "http://purl.obolibrary.org/obo/PATO_0001678", "annotation": {"to": 19225, "matchType": "PREF", "from": 19217, "text": "EFFICIENT"}}, {"uri": "http://purl.obolibrary.org/obo/PATO_0001678", "annotation": {"to": 21655, "matchType": "PREF", "from": 21647, "text": "EFFICIENT"}}, {"uri": "http://purl.obolibrary.org/obo/PATO_0000469", "annotation": {"to": 18709, "matchType": "PREF", "from": 18706, "text": "HIGH"}}, {"uri": "http://purl.obolibrary.org/obo/PATO_0000469", "annotation": {"to": 21490, "matchType": "PREF", "from": 21487, "text": "HIGH"}}, {"uri": "http://purl.obolibrary.org/obo/PATO_0001997", "annotation": {"to": 18962, "matchType": "SYN", "from": 18956, "text": "REDUCED"}}, {"uri": "http://purl.obolibrary.org/obo/PATO_0001997", "annotation": {"to": 21583, "matchType": "SYN", "from": 21577, "text": "REDUCED"}}, {"uri": "http://purl.org/sig/ont/fma/fma0328527", "annotation": {"to": 20099, "matchType": "PREF", "from": 20096, "text": "TEST"}}, {"uri": "http://purl.org/sig/ont/fma/fma0328527", "annotation": {"to": 20401, "matchType": "PREF", "from": 20398, "text": "TEST"}}, {"uri": "http://purl.org/sig/ont/fma/fma0328527", "annotation": {"to": 22169, "matchType": "PREF", "from": 22166, "text": "TEST"}}, {"uri": "http://purl.org/sig/ont/fma/fma0328527", "annotation": {"to": 22202, "matchType": "PREF", "from": 22199, "text": "TEST"}}, {"uri": "http://purl.obolibrary.org/obo/PATO_0000002", "annotation": {"to": 16063, "matchType": "PREF", "from": 16059, "text": "VALUE"}}, {"uri": "http://purl.obolibrary.org/obo/PATO_0000002", "annotation": {"to": 20601, "matchType": "PREF", "from": 20597, "text": "VALUE"}}, {"uri": "http://purl.obolibrary.org/obo/PATO_0001668", "annotation": {"to": 18121, "matchType": "PREF", "from": 18107, "text": "ASSOCIATED WITH"}}, {"uri": "http://purl.obolibrary.org/obo/PATO_0001668", "annotation": {"to": 18116, "matchType": "SYN", "from": 18107, "text": "ASSOCIATED"}}, {"uri": "http://purl.obolibrary.org/obo/PATO_0001668", "annotation": {"to": 21335, "matchType": "PREF", "from": 21321, "text": "ASSOCIATED WITH"}}, {"uri": "http://purl.obolibrary.org/obo/PATO_0001668", "annotation": {"to": 21330, "matchType": "SYN", "from": 21321, "text": "ASSOCIATED"}}], "end": 22259, "struct": "DoCO:TableBox", "CoreSc": "Met", "text": "", "start": 15771, "sid": "98"}, {"ncbo": [{"uri": "http://purl.org/sig/ont/fma/fma0328527", "annotation": {"to": 22276, "matchType": "PREF", "from": 22273, "text": "TEST"}}], "end": 22580, "struct": "deo:Results", "CoreSc": "Met", "text": "", "start": 22260, "sid": "99", "page": "4"}, {"ncbo": [{"uri": "http://purl.obolibrary.org/obo/PATO_0001997", "annotation": {"to": 22645, "matchType": "SYN", "from": 22639, "text": "REDUCED"}}], "end": 22663, "struct": "deo:Results", "CoreSc": "Met", "text": "", "start": 22581, "sid": "100", "page": "4"}, {"ncbo": [{"uri": "http://purl.org/sig/ont/fma/fma67238", "annotation": {"to": 22698, "matchType": "PREF", "from": 22691, "text": "DOPAMINE"}}, {"uri": "http://purl.obolibrary.org/obo/PATO_0002269", "annotation": {"to": 22755, "matchType": "SYN", "from": 22750, "text": "POOLED"}}], "end": 22819, "struct": "deo:Results", "CoreSc": "Met", "text": "", "start": 22664, "sid": "101", "page": "4"}, {"ncbo": [{"uri": "http://purl.obolibrary.org/obo/PATO_0000618", "annotation": {"to": 22882, "matchType": "PREF", "from": 22874, "text": "BILATERAL"}}, {"uri": "http://purl.obolibrary.org/obo/PATO_0000618", "annotation": {"to": 22950, "matchType": "PREF", "from": 22942, "text": "BILATERAL"}}, {"uri": "http://purl.obolibrary.org/obo/HP_0012832", "annotation": {"to": 22882, "matchType": "PREF", "from": 22874, "text": "BILATERAL"}}, {"uri": "http://purl.obolibrary.org/obo/HP_0012832", "annotation": {"to": 22950, "matchType": "PREF", "from": 22942, "text": "BILATERAL"}}, {"uri": "http://purl.obolibrary.org/obo/PATO_0000689", "annotation": {"to": 22872, "matchType": "PREF", "from": 22863, "text": "CONTINUOUS"}}, {"uri": "http://purl.obolibrary.org/obo/PATO_0000689", "annotation": {"to": 22940, "matchType": "PREF", "from": 22931, "text": "CONTINUOUS"}}], "end": 22971, "struct": "deo:Results", "CoreSc": "Met", "text": "", "start": 22820, "sid": "102", "page": "4"}, {"end": 23015, "struct": "deo:Results", "start": 22972, "text": "", "CoreSc": "Met", "sid": "103", "page": "4"}, {"ncbo": [{"uri": "http://purl.obolibrary.org/obo/PATO_0000044", "annotation": {"to": 23026, "matchType": "PREF", "from": 23018, "text": "FREQUENCY"}}], "end": 23057, "struct": "deo:Results", "CoreSc": "Met", "text": "", "start": 23016, "sid": "104", "page": "4"}, {"ncbo": [{"uri": "http://purl.obolibrary.org/obo/PATO_0000921", "annotation": {"to": 23070, "matchType": "PREF", "from": 23066, "text": "WIDTH"}}], "end": 23097, "struct": "deo:Results", "CoreSc": "Met", "text": "", "start": 23058, "sid": "105", "page": "4"}, {"ncbo": [{"uri": "http://purl.obolibrary.org/obo/PATO_0000618", "annotation": {"to": 23170, "matchType": "PREF", "from": 23162, "text": "BILATERAL"}}, {"uri": "http://purl.obolibrary.org/obo/HP_0012832", "annotation": {"to": 23170, "matchType": "PREF", "from": 23162, "text": "BILATERAL"}}, {"uri": "http://purl.org/sig/ont/fma/fma62035", "annotation": {"to": 27652, "matchType": "PREF", "from": 27634, "text": "SUBTHALAMIC NUCLEUS"}}, {"uri": "http://purl.obolibrary.org/obo/GO_0005634", "annotation": {"to": 26373, "matchType": "PREF", "from": 26367, "text": "NUCLEUS"}}, {"uri": "http://purl.obolibrary.org/obo/GO_0005634", "annotation": {"to": 27652, "matchType": "PREF", "from": 27646, "text": "NUCLEUS"}}, {"uri": "http://purl.obolibrary.org/obo/HP_0001337", "annotation": {"to": 24255, "matchType": "PREF", "from": 24250, "text": "TREMOR"}}, {"uri": "http://purl.obolibrary.org/obo/HP_0001337", "annotation": {"to": 26905, "matchType": "PREF", "from": 26900, "text": "TREMOR"}}, {"uri": "http://purl.obolibrary.org/obo/HP_0002304", "annotation": {"to": 24248, "matchType": "PREF", "from": 24241, "text": "AKINESIA"}}, {"uri": "http://purl.obolibrary.org/obo/HP_0002304", "annotation": {"to": 26828, "matchType": "PREF", "from": 26821, "text": "AKINESIA"}}, {"uri": "http://purl.obolibrary.org/obo/HP_0002063", "annotation": {"to": 23949, "matchType": "PREF", "from": 23942, "text": "RIGIDITY"}}, {"uri": "http://purl.obolibrary.org/obo/HP_0002063", "annotation": {"to": 26754, "matchType": "PREF", "from": 26747, "text": "RIGIDITY"}}, {"uri": "http://purl.obolibrary.org/obo/PATO_0000190", "annotation": {"to": 24260, "matchType": "PREF", "from": 24257, "text": "GAIT"}}, {"uri": "http://purl.obolibrary.org/obo/PATO_0000190", "annotation": {"to": 26977, "matchType": "PREF", "from": 26974, "text": "GAIT"}}, {"uri": "http://purl.obolibrary.org/obo/PATO_0000002", "annotation": {"to": 23723, "matchType": "PREF", "from": 23719, "text": "VALUE"}}, {"uri": "http://purl.obolibrary.org/obo/PATO_0000002", "annotation": {"to": 26692, "matchType": "PREF", "from": 26688, "text": "VALUE"}}], "end": 27695, "struct": "DoCO:TableBox", "CoreSc": "Met", "text": "", "start": 23098, "sid": "106"}, {"end": 27814, "struct": "deo:Results", "start": 27696, "text": "", "CoreSc": "Met", "sid": "107", "page": "5"}, {"end": 27869, "struct": "deo:Results", "start": 27815, "text": "", "CoreSc": "Met", "sid": "108", "page": "5"}, {"ncbo": [{"uri": "http://purl.obolibrary.org/obo/HP_0000252", "annotation": {"to": 27899, "matchType": "SYN", "from": 27890, "text": "SMALL HEAD"}}, {"uri": "http://purl.obolibrary.org/obo/PATO_0000587", "annotation": {"to": 27894, "matchType": "SYN", "from": 27890, "text": "SMALL"}}, {"uri": "http://purl.org/sig/ont/fma/fma7154", "annotation": {"to": 27899, "matchType": "PREF", "from": 27896, "text": "HEAD"}}, {"uri": "http://purl.org/sig/ont/fma/fma46494", "annotation": {"to": 27918, "matchType": "PREF", "from": 27914, "text": "SCALP"}}], "end": 27977, "struct": "deo:Results", "CoreSc": "Met", "text": "", "start": 27870, "sid": "109", "page": "5"}, {"ncbo": [{"uri": "http://purl.obolibrary.org/obo/HP_0001287", "annotation": {"to": 28058, "matchType": "PREF", "from": 28049, "text": "MENINGITIS"}}], "end": 28118, "struct": "deo:Results", "CoreSc": "Met", "text": "", "start": 27978, "sid": "110", "page": "5"}, {"end": 28222, "struct": "deo:Results", "start": 28119, "text": "", "CoreSc": "Met", "sid": "111", "page": "5"}, {"ncbo": [{"uri": "http://purl.obolibrary.org/obo/HP_0002197", "annotation": {"to": 28266, "matchType": "PREF", "from": 28247, "text": "GENERALIZED SEIZURES"}}, {"uri": "http://purl.obolibrary.org/obo/HP_0012837", "annotation": {"to": 28257, "matchType": "PREF", "from": 28247, "text": "GENERALIZED"}}, {"uri": "http://purl.obolibrary.org/obo/PATO_0002403", "annotation": {"to": 28257, "matchType": "PREF", "from": 28247, "text": "GENERALIZED"}}, {"uri": "http://purl.obolibrary.org/obo/HP_0001250", "annotation": {"to": 28266, "matchType": "PREF", "from": 28259, "text": "SEIZURES"}}], "end": 28337, "struct": "deo:Results", "CoreSc": "Met", "text": "", "start": 28223, "sid": "112", "page": "5"}, {"ncbo": [{"uri": "http://purl.obolibrary.org/obo/HP_0001250", "annotation": {"to": 28374, "matchType": "PREF", "from": 28367, "text": "SEIZURES"}}], "end": 28375, "struct": "deo:Results", "CoreSc": "Met", "text": "", "start": 28338, "sid": "113", "page": "5"}, {"ncbo": [{"uri": "http://purl.obolibrary.org/obo/PATO_0002292", "annotation": {"to": 28408, "matchType": "PREF", "from": 28400, "text": "TRANSIENT"}}, {"uri": "http://purl.obolibrary.org/obo/HP_0000738", "annotation": {"to": 28423, "matchType": "PREF", "from": 28410, "text": "HALLUCINATIONS"}}, {"uri": "http://purl.obolibrary.org/obo/HP_0001289", "annotation": {"to": 28481, "matchType": "PREF", "from": 28473, "text": "CONFUSION"}}, {"uri": "http://purl.obolibrary.org/obo/HP_0001289", "annotation": {"to": 28521, "matchType": "PREF", "from": 28513, "text": "CONFUSION"}}, {"uri": "http://purl.obolibrary.org/obo/GO_0030431", "annotation": {"to": 28545, "matchType": "PREF", "from": 28541, "text": "SLEEP"}}], "end": 28585, "struct": "deo:Results", "CoreSc": "Met", "text": "", "start": 28376, "sid": "114", "page": "5"}, {"end": 28625, "struct": "deo:Results", "start": 28586, "text": "", "CoreSc": "Met", "sid": "115", "page": "5"}, {"ncbo": [{"uri": "http://purl.obolibrary.org/obo/HP_0000716", "annotation": {"to": 28669, "matchType": "PREF", "from": 28660, "text": "DEPRESSION"}}, {"uri": "http://purl.obolibrary.org/obo/PATO_0000397", "annotation": {"to": 28658, "matchType": "PREF", "from": 28653, "text": "SLIGHT"}}], "end": 28700, "struct": "deo:Results", "CoreSc": "Met", "text": "", "start": 28626, "sid": "116", "page": "5"}, {"end": 28754, "struct": "deo:Results", "start": 28701, "text": "", "CoreSc": "Bac", "sid": "117", "page": "5"}, {"ncbo": [{"uri": "http://purl.obolibrary.org/obo/HP_0000716", "annotation": {"to": 28770, "matchType": "PREF", "from": 28761, "text": "DEPRESSION"}}], "end": 28781, "struct": "deo:Results", "CoreSc": "Bac", "text": "", "start": 28755, "sid": "118", "page": "5"}, {"ncbo": [{"uri": "http://purl.obolibrary.org/obo/PATO_0000201", "annotation": {"to": 28829, "matchType": "PREF", "from": 28824, "text": "MEMORY"}}, {"uri": "http://purl.obolibrary.org/obo/GO_0007613", "annotation": {"to": 28829, "matchType": "PREF", "from": 28824, "text": "MEMORY"}}, {"uri": "http://purl.obolibrary.org/obo/HP_0100543", "annotation": {"to": 28874, "matchType": "SYN", "from": 28852, "text": "INTELLECTUAL IMPAIRMENT"}}], "end": 28952, "struct": "deo:Results", "CoreSc": "Bac", "text": "", "start": 28782, "sid": "119", "page": "5"}, {"ncbo": [{"uri": "http://purl.obolibrary.org/obo/HP_0001260", "annotation": {"to": 29020, "matchType": "PREF", "from": 29011, "text": "DYSARTHRIA"}}], "end": 29146, "struct": "deo:Results", "CoreSc": "Bac", "text": "", "start": 28953, "sid": "120", "page": "5"}, {"ncbo": [{"uri": "http://purl.obolibrary.org/obo/HP_0002015", "annotation": {"to": 29183, "matchType": "PREF", "from": 29175, "text": "DYSPHAGIA"}}], "end": 29184, "struct": "deo:Results", "CoreSc": "Bac", "text": "", "start": 29147, "sid": "121", "page": "5"}, {"ncbo": [{"uri": "http://purl.obolibrary.org/obo/HP_0000658", "annotation": {"to": 29263, "matchType": "PREF", "from": 29250, "text": "EYELID APRAXIA"}}, {"uri": "http://purl.org/sig/ont/fma/fma54437", "annotation": {"to": 29255, "matchType": "PREF", "from": 29250, "text": "EYELID"}}, {"uri": "http://purl.obolibrary.org/obo/HP_0002186", "annotation": {"to": 29263, "matchType": "PREF", "from": 29257, "text": "APRAXIA"}}], "end": 29351, "struct": "deo:Results", "CoreSc": "Bac", "text": "", "start": 29185, "sid": "122", "page": "5"}, {"ncbo": [{"uri": "http://purl.obolibrary.org/obo/HP_0012835", "annotation": {"to": 29521, "matchType": "PREF", "from": 29518, "text": "LEFT"}}, {"uri": "http://purl.obolibrary.org/obo/PATO_0000366", "annotation": {"to": 29521, "matchType": "PREF", "from": 29518, "text": "LEFT"}}], "end": 29544, "struct": "deo:Results", "CoreSc": "Bac", "text": "", "start": 29352, "sid": "123", "page": "5"}, {"ncbo": [{"uri": "http://purl.obolibrary.org/obo/PATO_0000618", "annotation": {"to": 29619, "matchType": "PREF", "from": 29611, "text": "BILATERAL"}}, {"uri": "http://purl.obolibrary.org/obo/PATO_0000618", "annotation": {"to": 29738, "matchType": "PREF", "from": 29730, "text": "BILATERAL"}}, {"uri": "http://purl.obolibrary.org/obo/HP_0012832", "annotation": {"to": 29619, "matchType": "PREF", "from": 29611, "text": "BILATERAL"}}, {"uri": "http://purl.obolibrary.org/obo/HP_0012832", "annotation": {"to": 29738, "matchType": "PREF", "from": 29730, "text": "BILATERAL"}}, {"uri": "http://purl.obolibrary.org/obo/PATO_0001309", "annotation": {"to": 29805, "matchType": "SYN", "from": 29802, "text": "TIME"}}, {"uri": "http://purl.obolibrary.org/obo/PATO_0000165", "annotation": {"to": 29805, "matchType": "PREF", "from": 29802, "text": "TIME"}}, {"uri": "http://purl.obolibrary.org/obo/PATO_0001477", "annotation": {"to": 29652, "matchType": "SYN", "from": 29647, "text": "MOVED "}}], "end": 29829, "struct": "deo:Results", "CoreSc": "Bac", "text": "", "start": 29545, "sid": "124", "page": "5"}, {"ncbo": [{"uri": "http://purl.obolibrary.org/obo/PATO_0000190", "annotation": {"to": 29872, "matchType": "PREF", "from": 29869, "text": "GAIT"}}, {"uri": "http://purl.obolibrary.org/obo/PATO_0000185", "annotation": {"to": 29863, "matchType": "PREF", "from": 29857, "text": "BALANCE"}}], "end": 29928, "struct": "deo:Results", "CoreSc": "Bac", "text": "", "start": 29830, "sid": "125", "page": "5"}, {"ncbo": [{"uri": "http://purl.obolibrary.org/obo/PATO_0000618", "annotation": {"to": 30001, "matchType": "PREF", "from": 29993, "text": "BILATERAL"}}, {"uri": "http://purl.obolibrary.org/obo/HP_0012832", "annotation": {"to": 30001, "matchType": "PREF", "from": 29993, "text": "BILATERAL"}}, {"uri": "http://purl.org/sig/ont/fma/fma62035", "annotation": {"to": 32963, "matchType": "PREF", "from": 32945, "text": "SUBTHALAMIC NUCLEUS"}}, {"uri": "http://purl.org/sig/ont/fma/fma62035", "annotation": {"to": 34177, "matchType": "PREF", "from": 34159, "text": "SUBTHALAMIC NUCLEUS"}}, {"uri": "http://purl.obolibrary.org/obo/GO_0005634", "annotation": {"to": 32963, "matchType": "PREF", "from": 32957, "text": "NUCLEUS"}}, {"uri": "http://purl.obolibrary.org/obo/GO_0005634", "annotation": {"to": 34177, "matchType": "PREF", "from": 34171, "text": "NUCLEUS"}}, {"uri": "http://purl.obolibrary.org/obo/HP_0001337", "annotation": {"to": 30925, "matchType": "PREF", "from": 30920, "text": "TREMOR"}}, {"uri": "http://purl.obolibrary.org/obo/HP_0001337", "annotation": {"to": 33459, "matchType": "PREF", "from": 33454, "text": "TREMOR"}}, {"uri": "http://purl.obolibrary.org/obo/HP_0002304", "annotation": {"to": 30582, "matchType": "PREF", "from": 30575, "text": "AKINESIA"}}, {"uri": "http://purl.obolibrary.org/obo/HP_0002304", "annotation": {"to": 33382, "matchType": "PREF", "from": 33375, "text": "AKINESIA"}}, {"uri": "http://purl.obolibrary.org/obo/HP_0002063", "annotation": {"to": 30573, "matchType": "PREF", "from": 30566, "text": "RIGIDITY"}}, {"uri": "http://purl.obolibrary.org/obo/HP_0002063", "annotation": {"to": 33313, "matchType": "PREF", "from": 33306, "text": "RIGIDITY"}}, {"uri": "http://purl.obolibrary.org/obo/PATO_0000190", "annotation": {"to": 30930, "matchType": "PREF", "from": 30927, "text": "GAIT"}}, {"uri": "http://purl.obolibrary.org/obo/PATO_0000190", "annotation": {"to": 33523, "matchType": "PREF", "from": 33520, "text": "GAIT"}}, {"uri": "http://purl.obolibrary.org/obo/PATO_0000002", "annotation": {"to": 30192, "matchType": "PREF", "from": 30188, "text": "VALUE"}}, {"uri": "http://purl.obolibrary.org/obo/PATO_0000002", "annotation": {"to": 33222, "matchType": "PREF", "from": 33218, "text": "VALUE"}}], "end": 34189, "struct": "DoCO:TableBox", "CoreSc": "Bac", "text": "", "start": 29929, "sid": "126"}, {"ncbo": [{"uri": "http://purl.obolibrary.org/obo/PATO_0000618", "annotation": {"to": 34261, "matchType": "PREF", "from": 34253, "text": "BILATERAL"}}, {"uri": "http://purl.obolibrary.org/obo/HP_0012832", "annotation": {"to": 34261, "matchType": "PREF", "from": 34253, "text": "BILATERAL"}}, {"uri": "http://purl.org/sig/ont/fma/fma62035", "annotation": {"to": 37160, "matchType": "PREF", "from": 37142, "text": "SUBTHALAMIC NUCLEUS"}}, {"uri": "http://purl.org/sig/ont/fma/fma62035", "annotation": {"to": 38437, "matchType": "PREF", "from": 38419, "text": "SUBTHALAMIC NUCLEUS"}}, {"uri": "http://purl.obolibrary.org/obo/GO_0005634", "annotation": {"to": 37160, "matchType": "PREF", "from": 37154, "text": "NUCLEUS"}}, {"uri": "http://purl.obolibrary.org/obo/GO_0005634", "annotation": {"to": 38437, "matchType": "PREF", "from": 38431, "text": "NUCLEUS"}}, {"uri": "http://purl.obolibrary.org/obo/PATO_0001309", "annotation": {"to": 34739, "matchType": "SYN", "from": 34736, "text": "TIME"}}, {"uri": "http://purl.obolibrary.org/obo/PATO_0001309", "annotation": {"to": 35010, "matchType": "SYN", "from": 35007, "text": "TIME"}}, {"uri": "http://purl.obolibrary.org/obo/PATO_0001309", "annotation": {"to": 37492, "matchType": "SYN", "from": 37489, "text": "TIME"}}, {"uri": "http://purl.obolibrary.org/obo/PATO_0001309", "annotation": {"to": 37589, "matchType": "SYN", "from": 37586, "text": "TIME"}}, {"uri": "http://purl.obolibrary.org/obo/PATO_0000165", "annotation": {"to": 34739, "matchType": "PREF", "from": 34736, "text": "TIME"}}, {"uri": "http://purl.obolibrary.org/obo/PATO_0000165", "annotation": {"to": 35010, "matchType": "PREF", "from": 35007, "text": "TIME"}}, {"uri": "http://purl.obolibrary.org/obo/PATO_0000165", "annotation": {"to": 37492, "matchType": "PREF", "from": 37489, "text": "TIME"}}, {"uri": "http://purl.obolibrary.org/obo/PATO_0000165", "annotation": {"to": 37589, "matchType": "PREF", "from": 37586, "text": "TIME"}}, {"uri": "http://purl.obolibrary.org/obo/PATO_0001555", "annotation": {"to": 35691, "matchType": "SYN", "from": 35686, "text": "NUMBER"}}, {"uri": "http://purl.obolibrary.org/obo/PATO_0001555", "annotation": {"to": 37955, "matchType": "SYN", "from": 37947, "text": "NUMBER OF"}}, {"uri": "http://purl.obolibrary.org/obo/PATO_0001555", "annotation": {"to": 37952, "matchType": "SYN", "from": 37947, "text": "NUMBER"}}, {"uri": "http://purl.obolibrary.org/obo/PATO_0001056", "annotation": {"to": 35691, "matchType": "PREF", "from": 35686, "text": "NUMBER"}}, {"uri": "http://purl.obolibrary.org/obo/PATO_0001056", "annotation": {"to": 37952, "matchType": "PREF", "from": 37947, "text": "NUMBER"}}, {"uri": "http://purl.obolibrary.org/obo/PATO_0000070", "annotation": {"to": 35691, "matchType": "SYN", "from": 35686, "text": "NUMBER"}}, {"uri": "http://purl.obolibrary.org/obo/PATO_0000070", "annotation": {"to": 37952, "matchType": "SYN", "from": 37947, "text": "NUMBER"}}, {"uri": "http://purl.obolibrary.org/obo/PATO_0000367", "annotation": {"to": 35467, "matchType": "PREF", "from": 35463, "text": "RIGHT"}}, {"uri": "http://purl.obolibrary.org/obo/PATO_0000367", "annotation": {"to": 35697, "matchType": "PREF", "from": 35693, "text": "RIGHT"}}, {"uri": "http://purl.obolibrary.org/obo/PATO_0000367", "annotation": {"to": 37862, "matchType": "PREF", "from": 37858, "text": "RIGHT"}}, {"uri": "http://purl.obolibrary.org/obo/PATO_0000367", "annotation": {"to": 38035, "matchType": "PREF", "from": 38031, "text": "RIGHT"}}, {"uri": "http://purl.obolibrary.org/obo/HP_0012834", "annotation": {"to": 35467, "matchType": "PREF", "from": 35463, "text": "RIGHT"}}, {"uri": "http://purl.obolibrary.org/obo/HP_0012834", "annotation": {"to": 35697, "matchType": "PREF", "from": 35693, "text": "RIGHT"}}, {"uri": "http://purl.obolibrary.org/obo/HP_0012834", "annotation": {"to": 37862, "matchType": "PREF", "from": 37858, "text": "RIGHT"}}, {"uri": "http://purl.obolibrary.org/obo/HP_0012834", "annotation": {"to": 38035, "matchType": "PREF", "from": 38031, "text": "RIGHT"}}, {"uri": "http://purl.obolibrary.org/obo/HP_0012835", "annotation": {"to": 35417, "matchType": "PREF", "from": 35414, "text": "LEFT"}}, {"uri": "http://purl.obolibrary.org/obo/HP_0012835", "annotation": {"to": 35714, "matchType": "PREF", "from": 35711, "text": "LEFT"}}, {"uri": "http://purl.obolibrary.org/obo/HP_0012835", "annotation": {"to": 37924, "matchType": "PREF", "from": 37921, "text": "LEFT"}}, {"uri": "http://purl.obolibrary.org/obo/HP_0012835", "annotation": {"to": 38044, "matchType": "PREF", "from": 38041, "text": "LEFT"}}, {"uri": "http://purl.obolibrary.org/obo/PATO_0000366", "annotation": {"to": 35417, "matchType": "PREF", "from": 35414, "text": "LEFT"}}, {"uri": "http://purl.obolibrary.org/obo/PATO_0000366", "annotation": {"to": 35714, "matchType": "PREF", "from": 35711, "text": "LEFT"}}, {"uri": "http://purl.obolibrary.org/obo/PATO_0000366", "annotation": {"to": 37924, "matchType": "PREF", "from": 37921, "text": "LEFT"}}, {"uri": "http://purl.obolibrary.org/obo/PATO_0000366", "annotation": {"to": 38044, "matchType": "PREF", "from": 38041, "text": "LEFT"}}, {"uri": "http://purl.org/sig/ont/fma/fma9712", "annotation": {"to": 35427, "matchType": "PREF", "from": 35424, "text": "HAND"}}, {"uri": "http://purl.org/sig/ont/fma/fma9712", "annotation": {"to": 35719, "matchType": "PREF", "from": 35716, "text": "HAND"}}, {"uri": "http://purl.org/sig/ont/fma/fma9712", "annotation": {"to": 37929, "matchType": "PREF", "from": 37926, "text": "HAND"}}, {"uri": "http://purl.org/sig/ont/fma/fma9712", "annotation": {"to": 38049, "matchType": "PREF", "from": 38046, "text": "HAND"}}, {"uri": "http://purl.org/sig/ont/fma/fma9714", "annotation": {"to": 35719, "matchType": "PREF", "from": 35711, "text": "LEFT HAND"}}, {"uri": "http://purl.org/sig/ont/fma/fma9714", "annotation": {"to": 37929, "matchType": "PREF", "from": 37921, "text": "LEFT HAND"}}, {"uri": "http://purl.org/sig/ont/fma/fma9714", "annotation": {"to": 38049, "matchType": "PREF", "from": 38041, "text": "LEFT HAND"}}], "end": 38449, "struct": "DoCO:TableBox", "CoreSc": "Bac", "text": "", "start": 34190, "sid": "127"}, {"ncbo": [{"uri": "http://purl.obolibrary.org/obo/PATO_0000470", "annotation": {"to": 38466, "matchType": "SYN", "from": 38458, "text": "INCREASED"}}, {"uri": "http://purl.obolibrary.org/obo/PATO_0000128", "annotation": {"to": 38456, "matchType": "PREF", "from": 38451, "text": "WEIGHT"}}], "end": 38554, "struct": "deo:Results", "CoreSc": "Bac", "text": "", "start": 38450, "sid": "128", "page": "6"}, {"ncbo": [{"uri": "http://purl.obolibrary.org/obo/PATO_0000694", "annotation": {"to": 38623, "matchType": "SYN", "from": 38616, "text": "ADVANCED"}}], "end": 38733, "struct": "deo:Discussion", "CoreSc": "Bac", "text": "", "start": 38555, "sid": "129", "page": "6"}, {"ncbo": [{"uri": "http://purl.obolibrary.org/obo/PATO_0000224", "annotation": {"to": 38826, "matchType": "PREF", "from": 38813, "text": "MOTOR FUNCTION"}}, {"uri": "http://purl.obolibrary.org/obo/PATO_0000173", "annotation": {"to": 38826, "matchType": "PREF", "from": 38819, "text": "FUNCTION"}}], "end": 38835, "struct": "deo:Discussion", "CoreSc": "Bac", "text": "", "start": 38734, "sid": "130", "page": "6"}, {"ncbo": [{"uri": "http://purl.obolibrary.org/obo/HP_0100660", "annotation": {"to": 39010, "matchType": "SYN", "from": 39000, "text": "DYSKINESIAS"}}], "end": 39011, "struct": "deo:Discussion", "CoreSc": "Bac", "text": "", "start": 38836, "sid": "131", "page": "6"}, {"ncbo": [{"uri": "http://purl.obolibrary.org/obo/HP_0100660", "annotation": {"to": 39191, "matchType": "SYN", "from": 39181, "text": "DYSKINESIAS"}}, {"uri": "http://purl.obolibrary.org/obo/PATO_0001309", "annotation": {"to": 39176, "matchType": "PREF", "from": 39169, "text": "DURATION"}}, {"uri": "http://purl.obolibrary.org/obo/PATO_0001309", "annotation": {"to": 39211, "matchType": "PREF", "from": 39204, "text": "DURATION"}}], "end": 39241, "struct": "deo:Discussion", "CoreSc": "Bac", "text": "", "start": 39012, "sid": "132", "page": "6"}, {"ncbo": [{"uri": "http://purl.org/sig/ont/fma/fma0328527", "annotation": {"to": 39305, "matchType": "PREF", "from": 39302, "text": "TEST"}}], "end": 39347, "struct": "deo:Discussion", "CoreSc": "Bac", "text": "", "start": 39242, "sid": "133", "page": "6"}, {"ncbo": [{"uri": "http://purl.obolibrary.org/obo/PATO_0001997", "annotation": {"to": 39391, "matchType": "SYN", "from": 39385, "text": "REDUCED"}}], "end": 39418, "struct": "deo:Discussion", "CoreSc": "Bac", "text": "", "start": 39348, "sid": "134", "page": "6"}, {"ncbo": [{"uri": "http://purl.org/sig/ont/fma/fma67238", "annotation": {"to": 39496, "matchType": "PREF", "from": 39489, "text": "DOPAMINE"}}], "end": 40333, "struct": "DoCO:TableBox", "CoreSc": "Bac", "text": "", "start": 39419, "sid": "135"}, {"end": 40617, "struct": "deo:Discussion", "start": 40334, "text": "", "CoreSc": "Bac", "sid": "136", "page": "6"}, {"ncbo": [{"uri": "http://purl.obolibrary.org/obo/PATO_0001997", "annotation": {"to": 40664, "matchType": "SYN", "from": 40658, "text": "REDUCED"}}], "end": 40665, "struct": "deo:Discussion", "CoreSc": "Bac", "text": "", "start": 40618, "sid": "137", "page": "6"}, {"ncbo": [{"uri": "http://purl.obolibrary.org/obo/PATO_0001596", "annotation": {"to": 40756, "matchType": "SYN", "from": 40753, "text": "DEEP"}}, {"uri": "http://purl.org/sig/ont/fma/fma50801", "annotation": {"to": 40762, "matchType": "PREF", "from": 40758, "text": "BRAIN"}}], "end": 40877, "struct": "deo:Discussion", "CoreSc": "Bac", "text": "", "start": 40666, "sid": "138", "page": "6"}, {"end": 41003, "struct": "deo:Discussion", "start": 40878, "text": "", "CoreSc": "Bac", "sid": "139", "page": "6"}, {"ncbo": [{"uri": "http://purl.obolibrary.org/obo/PATO_0000467", "annotation": {"to": 41049, "matchType": "PREF", "from": 41043, "text": "PRESENT"}}], "end": 41231, "struct": "deo:Discussion", "CoreSc": "Bac", "text": "", "start": 41004, "sid": "140", "page": "6"}, {"ncbo": [{"uri": "http://purl.obolibrary.org/obo/PATO_0000467", "annotation": {"to": 41247, "matchType": "PREF", "from": 41241, "text": "PRESENT"}}, {"uri": "http://purl.obolibrary.org/obo/PATO_0001997", "annotation": {"to": 41299, "matchType": "SYN", "from": 41293, "text": "REDUCED"}}], "end": 41312, "struct": "deo:Discussion", "CoreSc": "Bac", "text": "", "start": 41232, "sid": "141", "page": "6"}, {"ncbo": [{"uri": "http://purl.org/sig/ont/fma/fma67238", "annotation": {"to": 41593, "matchType": "PREF", "from": 41586, "text": "DOPAMINE"}}, {"uri": "http://purl.obolibrary.org/obo/PATO_0000461", "annotation": {"to": 41451, "matchType": "SYN", "from": 41445, "text": "AVERAGE"}}], "end": 41603, "struct": "deo:Discussion", "CoreSc": "Bac", "text": "", "start": 41313, "sid": "142", "page": "6"}, {"ncbo": [{"uri": "http://purl.obolibrary.org/obo/PATO_0000467", "annotation": {"to": 41700, "matchType": "PREF", "from": 41694, "text": "PRESENT"}}], "end": 41742, "struct": "deo:Discussion", "CoreSc": "Bac", "text": "", "start": 41604, "sid": "143", "page": "6"}, {"end": 41960, "struct": "deo:Discussion", "start": 41743, "text": "", "CoreSc": "Bac", "sid": "144", "page": "6"}, {"ncbo": [{"uri": "http://purl.obolibrary.org/obo/HP_0100660", "annotation": {"to": 42044, "matchType": "SYN", "from": 42034, "text": "DYSKINESIAS"}}], "end": 42119, "struct": "deo:Discussion", "CoreSc": "Bac", "text": "", "start": 41961, "sid": "145", "page": "6"}, {"ncbo": [{"uri": "http://purl.obolibrary.org/obo/HP_0100660", "annotation": {"to": 42169, "matchType": "SYN", "from": 42159, "text": "DYSKINESIAS"}}, {"uri": "http://purl.obolibrary.org/obo/PATO_0001997", "annotation": {"to": 42208, "matchType": "SYN", "from": 42202, "text": "REDUCED"}}], "end": 42351, "struct": "deo:Discussion", "CoreSc": "Bac", "text": "", "start": 42120, "sid": "146", "page": "6"}, {"ncbo": [{"uri": "http://purl.obolibrary.org/obo/HP_0100660", "annotation": {"to": 42606, "matchType": "SYN", "from": 42596, "text": "DYSKINESIAS"}}, {"uri": "http://purl.obolibrary.org/obo/PATO_0001309", "annotation": {"to": 42638, "matchType": "SYN", "from": 42635, "text": "TIME"}}, {"uri": "http://purl.obolibrary.org/obo/PATO_0000165", "annotation": {"to": 42638, "matchType": "PREF", "from": 42635, "text": "TIME"}}, {"uri": "http://purl.obolibrary.org/obo/PATO_0000224", "annotation": {"to": 42564, "matchType": "PREF", "from": 42551, "text": "MOTOR FUNCTION"}}, {"uri": "http://purl.obolibrary.org/obo/PATO_0000173", "annotation": {"to": 42564, "matchType": "PREF", "from": 42557, "text": "FUNCTION"}}], "end": 42661, "struct": "deo:Discussion", "CoreSc": "Bac", "text": "", "start": 42352, "sid": "147", "page": "6"}, {"end": 42817, "struct": "deo:Discussion", "start": 42662, "text": "", "CoreSc": "Bac", "sid": "148", "page": "6"}, {"end": 42944, "struct": "deo:Discussion", "start": 42818, "text": "", "CoreSc": "Bac", "sid": "149", "page": "6"}, {"ncbo": [{"uri": "http://purl.obolibrary.org/obo/HP_0002170", "annotation": {"to": 42969, "matchType": "PREF", "from": 42947, "text": "INTRACRANIAL HEMORRHAGE"}}], "end": 43110, "struct": "deo:Discussion", "CoreSc": "Bac", "text": "", "start": 42945, "sid": "150", "page": "6"}, {"ncbo": [{"uri": "http://purl.obolibrary.org/obo/PATO_0000470", "annotation": {"to": 43146, "matchType": "SYN", "from": 43138, "text": "INCREASED"}}, {"uri": "http://purl.obolibrary.org/obo/PATO_0001668", "annotation": {"to": 43200, "matchType": "PREF", "from": 43186, "text": "ASSOCIATED WITH"}}, {"uri": "http://purl.obolibrary.org/obo/PATO_0001668", "annotation": {"to": 43195, "matchType": "SYN", "from": 43186, "text": "ASSOCIATED"}}, {"uri": "http://purl.obolibrary.org/obo/HP_0002170", "annotation": {"to": 43239, "matchType": "PREF", "from": 43217, "text": "INTRACRANIAL HEMORRHAGE"}}], "end": 43240, "struct": "deo:Discussion", "CoreSc": "Bac", "text": "", "start": 43111, "sid": "151", "page": "6"}, {"ncbo": [{"uri": "http://purl.obolibrary.org/obo/PATO_0000467", "annotation": {"to": 43360, "matchType": "PREF", "from": 43354, "text": "PRESENT"}}, {"uri": "http://purl.obolibrary.org/obo/PATO_0000470", "annotation": {"to": 43456, "matchType": "SYN", "from": 43448, "text": "INCREASED"}}], "end": 43487, "struct": "deo:Discussion", "CoreSc": "Bac", "text": "", "start": 43241, "sid": "152", "page": "6"}, {"ncbo": [{"uri": "http://purl.obolibrary.org/obo/HP_0001260", "annotation": {"to": 43586, "matchType": "PREF", "from": 43577, "text": "DYSARTHRIA"}}, {"uri": "http://purl.obolibrary.org/obo/PATO_0002293", "annotation": {"to": 43612, "matchType": "PREF", "from": 43604, "text": "PERMANENT"}}], "end": 43706, "struct": "deo:Discussion", "CoreSc": "Bac", "text": "", "start": 43488, "sid": "153", "page": "6"}, {"ncbo": [{"uri": "http://purl.obolibrary.org/obo/PATO_0000201", "annotation": {"to": 43800, "matchType": "PREF", "from": 43795, "text": "MEMORY"}}, {"uri": "http://purl.obolibrary.org/obo/GO_0007613", "annotation": {"to": 43800, "matchType": "PREF", "from": 43795, "text": "MEMORY"}}, {"uri": "http://purl.obolibrary.org/obo/GO_0007614", "annotation": {"to": 43800, "matchType": "PREF", "from": 43784, "text": "SHORT-TERM MEMORY"}}, {"uri": "http://purl.obolibrary.org/obo/PATO_0000574", "annotation": {"to": 43788, "matchType": "SYN", "from": 43784, "text": "SHORT"}}, {"uri": "http://purl.obolibrary.org/obo/PATO_0000569", "annotation": {"to": 43788, "matchType": "SYN", "from": 43784, "text": "SHORT"}}], "end": 43801, "struct": "deo:Discussion", "CoreSc": "Bac", "text": "", "start": 43707, "sid": "154", "page": "6"}, {"end": 43870, "struct": "deo:Discussion", "start": 43802, "text": "", "CoreSc": "Bac", "sid": "155", "page": "6"}, {"ncbo": [{"uri": "http://purl.obolibrary.org/obo/HP_0000726", "annotation": {"to": 44028, "matchType": "PREF", "from": 44021, "text": "DEMENTIA"}}, {"uri": "http://purl.obolibrary.org/obo/PATO_0000201", "annotation": {"to": 44006, "matchType": "PREF", "from": 44001, "text": "MEMORY"}}, {"uri": "http://purl.obolibrary.org/obo/GO_0007613", "annotation": {"to": 44006, "matchType": "PREF", "from": 44001, "text": "MEMORY"}}], "end": 44077, "struct": "deo:Discussion", "CoreSc": "Bac", "text": "", "start": 43871, "sid": "156", "page": "6"}, {"ncbo": [{"uri": "http://purl.obolibrary.org/obo/HP_0000726", "annotation": {"to": 44129, "matchType": "PREF", "from": 44122, "text": "DEMENTIA"}}, {"uri": "http://purl.obolibrary.org/obo/PATO_0000201", "annotation": {"to": 44107, "matchType": "PREF", "from": 44102, "text": "MEMORY"}}, {"uri": "http://purl.obolibrary.org/obo/GO_0007613", "annotation": {"to": 44107, "matchType": "PREF", "from": 44102, "text": "MEMORY"}}], "end": 44152, "struct": "deo:Discussion", "CoreSc": "Bac", "text": "", "start": 44078, "sid": "157", "page": "6"}, {"ncbo": [{"uri": "http://purl.obolibrary.org/obo/PATO_0000173", "annotation": {"to": 44260, "matchType": "PREF", "from": 44253, "text": "FUNCTION"}}, {"uri": "http://purl.obolibrary.org/obo/PATO_0000173", "annotation": {"to": 44293, "matchType": "PREF", "from": 44286, "text": "FUNCTION"}}, {"uri": "http://purl.obolibrary.org/obo/PATO_0000461", "annotation": {"to": 44303, "matchType": "PREF", "from": 44298, "text": "NORMAL"}}], "end": 44360, "struct": "deo:Discussion", "CoreSc": "Bac", "text": "", "start": 44153, "sid": "158", "page": "6"}, {"ncbo": [{"uri": "http://purl.obolibrary.org/obo/PATO_0000618", "annotation": {"to": 44374, "matchType": "PREF", "from": 44366, "text": "BILATERAL"}}, {"uri": "http://purl.obolibrary.org/obo/HP_0012832", "annotation": {"to": 44374, "matchType": "PREF", "from": 44366, "text": "BILATERAL"}}, {"uri": "http://purl.org/sig/ont/fma/fma74536", "annotation": {"to": 44439, "matchType": "PREF", "from": 44433, "text": "FRONTAL"}}], "end": 44503, "struct": "deo:Discussion", "CoreSc": "Bac", "text": "", "start": 44361, "sid": "159", "page": "6"}, {"ncbo": [{"uri": "http://purl.obolibrary.org/obo/PATO_0000573", "annotation": {"to": 44556, "matchType": "SYN", "from": 44553, "text": "LONG"}}], "end": 44589, "struct": "deo:Discussion", "CoreSc": "Bac", "text": "", "start": 44504, "sid": "160", "page": "6"}, {"ncbo": [{"uri": "http://purl.obolibrary.org/obo/PATO_0001470", "annotation": {"to": 44682, "matchType": "SYN", "from": 44679, "text": "RATE"}}, {"uri": "http://purl.obolibrary.org/obo/PATO_0000161", "annotation": {"to": 44682, "matchType": "PREF", "from": 44679, "text": "RATE"}}], "end": 44707, "struct": "deo:Discussion", "CoreSc": "Bac", "text": "", "start": 44590, "sid": "161", "page": "6"}, {"end": 44871, "struct": "deo:Discussion", "start": 44708, "text": "", "CoreSc": "Bac", "sid": "162", "page": "6"}, {"ncbo": [{"uri": "http://purl.obolibrary.org/obo/PATO_0000618", "annotation": {"to": 44900, "matchType": "PREF", "from": 44892, "text": "BILATERAL"}}, {"uri": "http://purl.obolibrary.org/obo/HP_0012832", "annotation": {"to": 44900, "matchType": "PREF", "from": 44892, "text": "BILATERAL"}}, {"uri": "http://purl.obolibrary.org/obo/PATO_0000694", "annotation": {"to": 44962, "matchType": "SYN", "from": 44955, "text": "ADVANCED"}}], "end": 45036, "struct": "deo:Discussion", "CoreSc": "Bac", "text": "", "start": 44872, "sid": "163", "page": "6"}, {"ncbo": [{"uri": "http://purl.obolibrary.org/obo/PATO_0001596", "annotation": {"to": 47332, "matchType": "SYN", "from": 47329, "text": "DEEP"}}, {"uri": "http://purl.obolibrary.org/obo/PATO_0001596", "annotation": {"to": 48291, "matchType": "SYN", "from": 48288, "text": "DEEP"}}, {"uri": "http://purl.org/sig/ont/fma/fma50801", "annotation": {"to": 47338, "matchType": "PREF", "from": 47334, "text": "BRAIN"}}, {"uri": "http://purl.org/sig/ont/fma/fma50801", "annotation": {"to": 48297, "matchType": "PREF", "from": 48293, "text": "BRAIN"}}, {"uri": "http://purl.obolibrary.org/obo/HP_0100660", "annotation": {"to": 45680, "matchType": "SYN", "from": 45670, "text": "DYSKINESIAS"}}, {"uri": "http://purl.obolibrary.org/obo/HP_0100660", "annotation": {"to": 47852, "matchType": "SYN", "from": 47842, "text": "DYSKINESIAS"}}], "end": 48437, "struct": "DoCO:TableBox", "CoreSc": "Bac", "text": "", "start": 45037, "sid": "164"}, {"end": 48600, "struct": "deo:Discussion", "start": 48438, "text": "", "CoreSc": "Bac", "sid": "165", "page": "7"}, {"ncbo": [{"uri": "http://purl.obolibrary.org/obo/PATO_0000618", "annotation": {"to": 53549, "matchType": "PREF", "from": 53541, "text": "BILATERAL"}}, {"uri": "http://purl.obolibrary.org/obo/PATO_0000618", "annotation": {"to": 54805, "matchType": "PREF", "from": 54797, "text": "BILATERAL"}}, {"uri": "http://purl.obolibrary.org/obo/PATO_0000618", "annotation": {"to": 55085, "matchType": "PREF", "from": 55077, "text": "BILATERAL"}}, {"uri": "http://purl.obolibrary.org/obo/PATO_0000618", "annotation": {"to": 55322, "matchType": "PREF", "from": 55314, "text": "BILATERAL"}}, {"uri": "http://purl.obolibrary.org/obo/HP_0012832", "annotation": {"to": 53549, "matchType": "PREF", "from": 53541, "text": "BILATERAL"}}, {"uri": "http://purl.obolibrary.org/obo/HP_0012832", "annotation": {"to": 54805, "matchType": "PREF", "from": 54797, "text": "BILATERAL"}}, {"uri": "http://purl.obolibrary.org/obo/HP_0012832", "annotation": {"to": 55085, "matchType": "PREF", "from": 55077, "text": "BILATERAL"}}, {"uri": "http://purl.obolibrary.org/obo/HP_0012832", "annotation": {"to": 55322, "matchType": "PREF", "from": 55314, "text": "BILATERAL"}}, {"uri": "http://purl.org/sig/ont/fma/fma62035", "annotation": {"to": 49769, "matchType": "PREF", "from": 49751, "text": "SUBTHALAMIC NUCLEUS"}}, {"uri": "http://purl.org/sig/ont/fma/fma62035", "annotation": {"to": 49972, "matchType": "PREF", "from": 49954, "text": "SUBTHALAMIC NUCLEUS"}}, {"uri": "http://purl.org/sig/ont/fma/fma62035", "annotation": {"to": 50284, "matchType": "PREF", "from": 50266, "text": "SUBTHALAMIC NUCLEUS"}}, {"uri": "http://purl.org/sig/ont/fma/fma62035", "annotation": {"to": 50500, "matchType": "PREF", "from": 50482, "text": "SUBTHALAMIC NUCLEUS"}}, {"uri": "http://purl.org/sig/ont/fma/fma62035", "annotation": {"to": 50687, "matchType": "PREF", "from": 50669, "text": "SUBTHALAMIC NUCLEUS"}}, {"uri": "http://purl.org/sig/ont/fma/fma62035", "annotation": {"to": 51239, "matchType": "PREF", "from": 51221, "text": "SUBTHALAMIC NUCLEUS"}}, {"uri": "http://purl.org/sig/ont/fma/fma62035", "annotation": {"to": 52221, "matchType": "PREF", "from": 52203, "text": "SUBTHALAMIC NUCLEUS"}}, {"uri": "http://purl.org/sig/ont/fma/fma62035", "annotation": {"to": 52830, "matchType": "PREF", "from": 52812, "text": "SUBTHALAMIC NUCLEUS"}}, {"uri": "http://purl.org/sig/ont/fma/fma62035", "annotation": {"to": 53050, "matchType": "PREF", "from": 53032, "text": "SUBTHALAMIC NUCLEUS"}}, {"uri": "http://purl.org/sig/ont/fma/fma62035", "annotation": {"to": 53801, "matchType": "PREF", "from": 53783, "text": "SUBTHALAMIC NUCLEUS"}}, {"uri": "http://purl.org/sig/ont/fma/fma62035", "annotation": {"to": 53994, "matchType": "PREF", "from": 53976, "text": "SUBTHALAMIC NUCLEUS"}}, {"uri": "http://purl.org/sig/ont/fma/fma62035", "annotation": {"to": 54634, "matchType": "PREF", "from": 54616, "text": "SUBTHALAMIC NUCLEUS"}}, {"uri": "http://purl.org/sig/ont/fma/fma62035", "annotation": {"to": 55124, "matchType": "PREF", "from": 55106, "text": "SUBTHALAMIC NUCLEUS"}}, {"uri": "http://purl.org/sig/ont/fma/fma62035", "annotation": {"to": 55361, "matchType": "PREF", "from": 55343, "text": "SUBTHALAMIC NUCLEUS"}}, {"uri": "http://purl.org/sig/ont/fma/fma62035", "annotation": {"to": 55625, "matchType": "PREF", "from": 55607, "text": "SUBTHALAMIC NUCLEUS"}}, {"uri": "http://purl.obolibrary.org/obo/GO_0005634", "annotation": {"to": 49769, "matchType": "PREF", "from": 49763, "text": "NUCLEUS"}}, {"uri": "http://purl.obolibrary.org/obo/GO_0005634", "annotation": {"to": 49972, "matchType": "PREF", "from": 49966, "text": "NUCLEUS"}}, {"uri": "http://purl.obolibrary.org/obo/GO_0005634", "annotation": {"to": 50284, "matchType": "PREF", "from": 50278, "text": "NUCLEUS"}}, {"uri": "http://purl.obolibrary.org/obo/GO_0005634", "annotation": {"to": 50500, "matchType": "PREF", "from": 50494, "text": "NUCLEUS"}}, {"uri": "http://purl.obolibrary.org/obo/GO_0005634", "annotation": {"to": 50687, "matchType": "PREF", "from": 50681, "text": "NUCLEUS"}}, {"uri": "http://purl.obolibrary.org/obo/GO_0005634", "annotation": {"to": 51239, "matchType": "PREF", "from": 51233, "text": "NUCLEUS"}}, {"uri": "http://purl.obolibrary.org/obo/GO_0005634", "annotation": {"to": 52050, "matchType": "PREF", "from": 52044, "text": "NUCLEUS"}}, {"uri": "http://purl.obolibrary.org/obo/GO_0005634", "annotation": {"to": 52221, "matchType": "PREF", "from": 52215, "text": "NUCLEUS"}}, {"uri": "http://purl.obolibrary.org/obo/GO_0005634", "annotation": {"to": 52410, "matchType": "PREF", "from": 52404, "text": "NUCLEUS"}}, {"uri": "http://purl.obolibrary.org/obo/GO_0005634", "annotation": {"to": 52830, "matchType": "PREF", "from": 52824, "text": "NUCLEUS"}}, {"uri": "http://purl.obolibrary.org/obo/GO_0005634", "annotation": {"to": 53050, "matchType": "PREF", "from": 53044, "text": "NUCLEUS"}}, {"uri": "http://purl.obolibrary.org/obo/GO_0005634", "annotation": {"to": 53571, "matchType": "PREF", "from": 53565, "text": "NUCLEUS"}}, {"uri": "http://purl.obolibrary.org/obo/GO_0005634", "annotation": {"to": 53801, "matchType": "PREF", "from": 53795, "text": "NUCLEUS"}}, {"uri": "http://purl.obolibrary.org/obo/GO_0005634", "annotation": {"to": 53994, "matchType": "PREF", "from": 53988, "text": "NUCLEUS"}}, {"uri": "http://purl.obolibrary.org/obo/GO_0005634", "annotation": {"to": 54634, "matchType": "PREF", "from": 54628, "text": "NUCLEUS"}}, {"uri": "http://purl.obolibrary.org/obo/GO_0005634", "annotation": {"to": 55124, "matchType": "PREF", "from": 55118, "text": "NUCLEUS"}}, {"uri": "http://purl.obolibrary.org/obo/GO_0005634", "annotation": {"to": 55361, "matchType": "PREF", "from": 55355, "text": "NUCLEUS"}}, {"uri": "http://purl.obolibrary.org/obo/GO_0005634", "annotation": {"to": 55625, "matchType": "PREF", "from": 55619, "text": "NUCLEUS"}}, {"uri": "http://purl.obolibrary.org/obo/PATO_0001596", "annotation": {"to": 49977, "matchType": "SYN", "from": 49974, "text": "DEEP"}}, {"uri": "http://purl.obolibrary.org/obo/PATO_0001596", "annotation": {"to": 50202, "matchType": "SYN", "from": 50199, "text": "DEEP"}}, {"uri": "http://purl.obolibrary.org/obo/PATO_0001596", "annotation": {"to": 50442, "matchType": "SYN", "from": 50439, "text": "DEEP"}}, {"uri": "http://purl.obolibrary.org/obo/PATO_0001596", "annotation": {"to": 50582, "matchType": "SYN", "from": 50579, "text": "DEEP"}}, {"uri": "http://purl.obolibrary.org/obo/PATO_0001596", "annotation": {"to": 50642, "matchType": "SYN", "from": 50639, "text": "DEEP"}}, {"uri": "http://purl.obolibrary.org/obo/PATO_0001596", "annotation": {"to": 50923, "matchType": "SYN", "from": 50920, "text": "DEEP"}}, {"uri": "http://purl.obolibrary.org/obo/PATO_0001596", "annotation": {"to": 51059, "matchType": "SYN", "from": 51056, "text": "DEEP"}}, {"uri": "http://purl.obolibrary.org/obo/PATO_0001596", "annotation": {"to": 51194, "matchType": "SYN", "from": 51191, "text": "DEEP"}}, {"uri": "http://purl.obolibrary.org/obo/PATO_0001596", "annotation": {"to": 52644, "matchType": "SYN", "from": 52641, "text": "DEEP"}}, {"uri": "http://purl.obolibrary.org/obo/PATO_0001596", "annotation": {"to": 53005, "matchType": "SYN", "from": 53002, "text": "DEEP"}}, {"uri": "http://purl.obolibrary.org/obo/PATO_0001596", "annotation": {"to": 53756, "matchType": "SYN", "from": 53753, "text": "DEEP"}}, {"uri": "http://purl.org/sig/ont/fma/fma50801", "annotation": {"to": 49844, "matchType": "PREF", "from": 49840, "text": "BRAIN"}}, {"uri": "http://purl.org/sig/ont/fma/fma50801", "annotation": {"to": 49983, "matchType": "PREF", "from": 49979, "text": "BRAIN"}}, {"uri": "http://purl.org/sig/ont/fma/fma50801", "annotation": {"to": 50208, "matchType": "PREF", "from": 50204, "text": "BRAIN"}}, {"uri": "http://purl.org/sig/ont/fma/fma50801", "annotation": {"to": 50448, "matchType": "PREF", "from": 50444, "text": "BRAIN"}}, {"uri": "http://purl.org/sig/ont/fma/fma50801", "annotation": {"to": 50588, "matchType": "PREF", "from": 50584, "text": "BRAIN"}}, {"uri": "http://purl.org/sig/ont/fma/fma50801", "annotation": {"to": 50648, "matchType": "PREF", "from": 50644, "text": "BRAIN"}}, {"uri": "http://purl.org/sig/ont/fma/fma50801", "annotation": {"to": 50929, "matchType": "PREF", "from": 50925, "text": "BRAIN"}}, {"uri": "http://purl.org/sig/ont/fma/fma50801", "annotation": {"to": 51065, "matchType": "PREF", "from": 51061, "text": "BRAIN"}}, {"uri": "http://purl.org/sig/ont/fma/fma50801", "annotation": {"to": 51200, "matchType": "PREF", "from": 51196, "text": "BRAIN"}}, {"uri": "http://purl.org/sig/ont/fma/fma50801", "annotation": {"to": 52650, "matchType": "PREF", "from": 52646, "text": "BRAIN"}}, {"uri": "http://purl.org/sig/ont/fma/fma50801", "annotation": {"to": 53011, "matchType": "PREF", "from": 53007, "text": "BRAIN"}}, {"uri": "http://purl.org/sig/ont/fma/fma50801", "annotation": {"to": 53762, "matchType": "PREF", "from": 53758, "text": "BRAIN"}}, {"uri": "http://purl.org/sig/ont/fma/fma50801", "annotation": {"to": 55391, "matchType": "PREF", "from": 55387, "text": "BRAIN"}}, {"uri": "http://purl.obolibrary.org/obo/PATO_0000694", "annotation": {"to": 49034, "matchType": "SYN", "from": 49030, "text": "EARLY"}}, {"uri": "http://purl.obolibrary.org/obo/PATO_0000694", "annotation": {"to": 49189, "matchType": "SYN", "from": 49185, "text": "EARLY"}}, {"uri": "http://purl.obolibrary.org/obo/PATO_0000694", "annotation": {"to": 50009, "matchType": "SYN", "from": 50002, "text": "ADVANCED"}}, {"uri": "http://purl.obolibrary.org/obo/PATO_0000694", "annotation": {"to": 50512, "matchType": "SYN", "from": 50505, "text": "ADVANCED"}}, {"uri": "http://purl.obolibrary.org/obo/PATO_0000694", "annotation": {"to": 52233, "matchType": "SYN", "from": 52226, "text": "ADVANCED"}}, {"uri": "http://purl.obolibrary.org/obo/PATO_0000694", "annotation": {"to": 52674, "matchType": "SYN", "from": 52667, "text": "ADVANCED"}}, {"uri": "http://purl.obolibrary.org/obo/PATO_0000694", "annotation": {"to": 53101, "matchType": "SYN", "from": 53094, "text": "ADVANCED"}}, {"uri": "http://purl.obolibrary.org/obo/PATO_0000694", "annotation": {"to": 53595, "matchType": "SYN", "from": 53588, "text": "ADVANCED"}}, {"uri": "http://purl.obolibrary.org/obo/PATO_0000694", "annotation": {"to": 54018, "matchType": "SYN", "from": 54011, "text": "ADVANCED"}}, {"uri": "http://purl.obolibrary.org/obo/HP_0100660", "annotation": {"to": 49011, "matchType": "PREF", "from": 49002, "text": "DYSKINESIA"}}, {"uri": "http://purl.obolibrary.org/obo/PATO_0001177", "annotation": {"to": 49310, "matchType": "PREF", "from": 49306, "text": "BLIND"}}, {"uri": "http://purl.obolibrary.org/obo/PATO_0001177", "annotation": {"to": 52613, "matchType": "PREF", "from": 52609, "text": "BLIND"}}, {"uri": "http://purl.obolibrary.org/obo/GO_0032502", "annotation": {"to": 51595, "matchType": "SYN", "from": 51585, "text": "DEVELOPMENT"}}, {"uri": "http://purl.obolibrary.org/obo/HP_0100022", "annotation": {"to": 55518, "matchType": "SYN", "from": 55502, "text": "MOVEMENT DISORDER"}}, {"uri": "http://purl.org/sig/ont/fma/fma74549", "annotation": {"to": 49781, "matchType": "PREF", "from": 49774, "text": "INTERNAL"}}, {"uri": "http://purl.org/sig/ont/fma/fma61835", "annotation": {"to": 50307, "matchType": "PREF", "from": 50293, "text": "GLOBUS PALLIDUS"}}, {"uri": "http://purl.org/sig/ont/fma/fma61835", "annotation": {"to": 50732, "matchType": "PREF", "from": 50718, "text": "GLOBUS PALLIDUS"}}, {"uri": "http://purl.obolibrary.org/obo/PATO_0001863", "annotation": {"to": 50918, "matchType": "PREF", "from": 50912, "text": "CHRONIC"}}, {"uri": "http://purl.obolibrary.org/obo/PATO_0001863", "annotation": {"to": 51993, "matchType": "PREF", "from": 51987, "text": "CHRONIC"}}, {"uri": "http://purl.obolibrary.org/obo/PATO_0001863", "annotation": {"to": 52348, "matchType": "PREF", "from": 52342, "text": "CHRONIC"}}, {"uri": "http://purl.obolibrary.org/obo/PATO_0001863", "annotation": {"to": 52810, "matchType": "PREF", "from": 52804, "text": "CHRONIC"}}, {"uri": "http://purl.obolibrary.org/obo/PATO_0001863", "annotation": {"to": 55075, "matchType": "PREF", "from": 55069, "text": "CHRONIC"}}, {"uri": "http://purl.obolibrary.org/obo/PATO_0001863", "annotation": {"to": 55312, "matchType": "PREF", "from": 55306, "text": "CHRONIC"}}, {"uri": "http://purl.obolibrary.org/obo/PATO_0000498", "annotation": {"to": 50918, "matchType": "SYN", "from": 50912, "text": "CHRONIC"}}, {"uri": "http://purl.obolibrary.org/obo/PATO_0000498", "annotation": {"to": 51993, "matchType": "SYN", "from": 51987, "text": "CHRONIC"}}, {"uri": "http://purl.obolibrary.org/obo/PATO_0000498", "annotation": {"to": 52348, "matchType": "SYN", "from": 52342, "text": "CHRONIC"}}, {"uri": "http://purl.obolibrary.org/obo/PATO_0000498", "annotation": {"to": 52810, "matchType": "SYN", "from": 52804, "text": "CHRONIC"}}, {"uri": "http://purl.obolibrary.org/obo/PATO_0000498", "annotation": {"to": 55075, "matchType": "SYN", "from": 55069, "text": "CHRONIC"}}, {"uri": "http://purl.obolibrary.org/obo/PATO_0000498", "annotation": {"to": 55312, "matchType": "SYN", "from": 55306, "text": "CHRONIC"}}, {"uri": "http://purl.obolibrary.org/obo/HP_0011010", "annotation": {"to": 50918, "matchType": "PREF", "from": 50912, "text": "CHRONIC"}}, {"uri": "http://purl.obolibrary.org/obo/HP_0011010", "annotation": {"to": 51993, "matchType": "PREF", "from": 51987, "text": "CHRONIC"}}, {"uri": "http://purl.obolibrary.org/obo/HP_0011010", "annotation": {"to": 52348, "matchType": "PREF", "from": 52342, "text": "CHRONIC"}}, {"uri": "http://purl.obolibrary.org/obo/HP_0011010", "annotation": {"to": 52810, "matchType": "PREF", "from": 52804, "text": "CHRONIC"}}, {"uri": "http://purl.obolibrary.org/obo/HP_0011010", "annotation": {"to": 55075, "matchType": "PREF", "from": 55069, "text": "CHRONIC"}}, {"uri": "http://purl.obolibrary.org/obo/HP_0011010", "annotation": {"to": 55312, "matchType": "PREF", "from": 55306, "text": "CHRONIC"}}, {"uri": "http://purl.obolibrary.org/obo/PATO_0001020", "annotation": {"to": 50907, "matchType": "PREF", "from": 50902, "text": "DAMAGE"}}, {"uri": "http://purl.org/sig/ont/fma/fma9637", "annotation": {"to": 50900, "matchType": "SYN", "from": 50895, "text": "TISSUE"}}, {"uri": "http://purl.obolibrary.org/obo/HP_0001337", "annotation": {"to": 51982, "matchType": "PREF", "from": 51977, "text": "TREMOR"}}, {"uri": "http://purl.obolibrary.org/obo/HP_0001337", "annotation": {"to": 54588, "matchType": "PREF", "from": 54583, "text": "TREMOR"}}, {"uri": "http://purl.obolibrary.org/obo/PATO_0000044", "annotation": {"to": 48754, "matchType": "PREF", "from": 48746, "text": "FREQUENCY"}}, {"uri": "http://purl.obolibrary.org/obo/PATO_0000224", "annotation": {"to": 54417, "matchType": "PREF", "from": 54404, "text": "MOTOR FUNCTION"}}, {"uri": "http://purl.obolibrary.org/obo/PATO_0000173", "annotation": {"to": 54417, "matchType": "PREF", "from": 54410, "text": "FUNCTION"}}, {"uri": "http://purl.obolibrary.org/obo/PATO_0000173", "annotation": {"to": 55146, "matchType": "PREF", "from": 55139, "text": "FUNCTION"}}, {"uri": "http://purl.org/sig/ont/fma/fma256693", "annotation": {"to": 52050, "matchType": "SYN", "from": 52035, "text": "THALAMIC NUCLEUS"}}, {"uri": "http://purl.obolibrary.org/obo/GO_0019013", "annotation": {"to": 51406, "matchType": "SYN", "from": 51403, "text": "CORE"}}, {"uri": "http://purl.obolibrary.org/obo/PATO_0000573", "annotation": {"to": 51955, "matchType": "SYN", "from": 51952, "text": "LONG"}}, {"uri": "http://purl.obolibrary.org/obo/PATO_0000201", "annotation": {"to": 54888, "matchType": "PREF", "from": 54883, "text": "MEMORY"}}, {"uri": "http://purl.obolibrary.org/obo/GO_0007613", "annotation": {"to": 54888, "matchType": "PREF", "from": 54883, "text": "MEMORY"}}, {"uri": "http://purl.obolibrary.org/obo/PATO_0000574", "annotation": {"to": 54121, "matchType": "SYN", "from": 54117, "text": "SHORT"}}, {"uri": "http://purl.obolibrary.org/obo/PATO_0000569", "annotation": {"to": 54121, "matchType": "SYN", "from": 54117, "text": "SHORT"}}, {"uri": "http://purl.obolibrary.org/obo/PATO_0000057", "annotation": {"to": 48997, "matchType": "SYN", "from": 48989, "text": "INCIDENCE"}}, {"uri": "http://purl.obolibrary.org/obo/HP_0003674", "annotation": {"to": 49258, "matchType": "PREF", "from": 49254, "text": "ONSET"}}, {"uri": "http://purl.obolibrary.org/obo/HP_0003674", "annotation": {"to": 49817, "matchType": "PREF", "from": 49813, "text": "ONSET"}}, {"uri": "http://purl.obolibrary.org/obo/PATO_0000309", "annotation": {"to": 49811, "matchType": "PREF", "from": 49807, "text": "YOUNG"}}, {"uri": "http://purl.org/sig/ont/fma/fma61840", "annotation": {"to": 50316, "matchType": "SYN", "from": 50293, "text": "GLOBUS PALLIDUS INTERNUS"}}, {"uri": "http://purl.obolibrary.org/obo/PATO_0001484", "annotation": {"to": 51717, "matchType": "PREF", "from": 51712, "text": "RECENT"}}, {"uri": "http://purl.org/sig/ont/fma/fma74534", "annotation": {"to": 52020, "matchType": "PREF", "from": 52014, "text": "VENTRAL"}}, {"uri": "http://purl.org/sig/ont/fma/fma74531", "annotation": {"to": 52033, "matchType": "PREF", "from": 52022, "text": "INTERMEDIATE"}}, {"uri": "http://purl.org/sig/ont/fma/fma62007", "annotation": {"to": 52426, "matchType": "PREF", "from": 52419, "text": "THALAMUS"}}, {"uri": "http://purl.org/sig/ont/fma/fma25000", "annotation": {"to": 53490, "matchType": "SYN", "from": 53487, "text": "SOLE"}}, {"uri": "http://purl.obolibrary.org/obo/GO_0007610", "annotation": {"to": 54187, "matchType": "SYN", "from": 54179, "text": "BEHAVIOUR"}}, {"uri": "http://purl.obolibrary.org/obo/PATO_0001264", "annotation": {"to": 55037, "matchType": "SYN", "from": 55033, "text": "BLOND"}}], "end": 55901, "struct": "DoCO:Bibliography", "CoreSc": "Bac", "text": "", "start": 48601, "sid": "166"}]